Workbook
Name amc_cost: '[1]CAPEX Savings Sheet'!$D$12
Name block_days: '[1]OPEX Savings Sheet'!$D$12
Name gst: '[1]CAPEX Savings Sheet'!$D$8
Name p50_percentage: '[1]OPEX Savings Sheet'!$I$11
Name p50_value: '[1]OPEX Savings Sheet'!$D$11
Name Railing: '[1]Bidcell BOM (LTS)'!#REF!
Name Railing: '[2]Bidcell BOM (LTS)'!#REF!
Name solar_capacity: '[1]OPEX Savings Sheet'!$D$10
Name spp_capacity: '[1]Consumption analysis (BD)'!$E$25

Sheet Proposal Inputs
A1: FOURTH PARTNER ENERGY — CAPEX Proposal Inputs
A2: Yellow cells = your inputs | Pink = mandatory | Blue = optional | Formulas are fine — the document shows the value exactly as Excel displays it
A3: Key | B3: Field | C3: Your Value | D3: Example | E3: Mandatory | F3: Page
A4: 1 · COVER PAGE & EXECUTIVE SUMMARY
A5: PH_001 | B5: Proposed Capacity (kWp) | D5: 910 | E5: MANUAL | F5: 1,2
A6: PH_002 | B6: Installation Technology | C6: Rooftop-Shed | D6: Rooftop - Shed | E6: MANUAL | F6: 1
A7: PH_003 | B7: Estimated Generation (kWh/year) | D7: 12,50,000 | E7: AUTOMATIC - Input and Output SHEET | F7: 1,4
A8: PH_004 | B8: % Consumption Replaced | D8: ~42% | E8: MANUAL | F8: 4
A9: PH_005 | B9: Net Metering (Yes/No) | C9: Yes | D9: Yes | E9: MANUAL | F9: 4
A10: PH_006 | B10: Key Components — Modules | C10: Renewsys 585+ Wp | D10: Renewsys 595 Wp | E10: MANUAL | F10: 4
A11: PH_007 | B11: Key Components — Inverters | C11: Solis | D11: Solis | E11: MANUAL | F11: 4
A12: PH_008 | B12: Project Timeline | C12: 4 + 1 Months | D12: 4–5 months | E12: MANUAL | F12: 4
A13: PH_009 | B13: Exclusions (Exec summary) | C13: Spare feeder, Internet connectivity | D13: Spare feeder; Net meter infra; Internet | E13: MANUAL | F13: 4
A14: PH_010 | B14: Commercial — Investment (Rs. Crs) | C14: =C139/10000000 -> 0 | D14: 3.50 | E14: AUTOMATIC - Working Sheet | F14: 4
A15: PH_011 | B15: Commercial — Payment Terms | C15: 30% advance + 70% via BG/LC | D15: 30% advance + 70% via BG/LC | E15: MANUAL | F15: 4
A16: PH_012 | B16: Commercial — AMC Cost | C16: ₹ 650/kWp/yr with 5% escalation | D16: ₹ 650/kWp/yr with 5% escalation | E16: MANUAL | F16: 4
A17: PH_013 | B17: Commercial — Payback Period | D17: 4.2 years | E17: AUTOMATIC - Working Sheet | F17: 4
A18: PH_014 | B18: Commercial — Net Savings over 25 Years (₹ Cr) | C18: =C156/100 -> 6.9797713 | D18: 12.5 | E18: AUTOMATIC - Working Sheet | F18: 4
A19: PH_015 | B19: Commercial — CO₂ Reduction (Tonnes/year) | C19: ='Environmental Benefits (2)'!F17 -> #DIV/0! | D19: 816 | E19: AUTOMATIC - ENV | F19: 4
A20: PH_016 | B20: Proposal Submitted by | C20: Carl Aaron | carl.aaron@fourthpartner.co | +91-9551062519 | D20: Carl Aaron | E20: Optional | F20: 4
A21: PH_017 | B21: Proposal Submitted on | C21: =DAY(TODAY())&IF(AND(DAY(TODAY())>=11,DAY(TODAY())<=13),"th",CHOOSE(MIN(5,MOD(DAY(TODAY()),10)+1),"th","st","nd","rd","th"))&" "&TEXT(TODAY(),"mmmm yyyy") -> 10th August 2026 | D21: 31st Jul 2025 | E21: AUTOMATIC | F21: 4
A22: PH_018 | B22: Proposal Validity | C22: 15 days | D22: 15 days | E22: Optional | F22: 4
A23: 2 · SITE DETAILS (1.1 Customer & 1.2 Site)
A24: PH_019 | B24: Customer Name | D24: IFGL Refractories Ltd. | E24: MANUAL | F24: 1,5,13
A25: PH_020 | B25: Customer Address (short) | D25: Kandla, Gujarat | E25: MANUAL | F25: 1,5,13
A26: PH_021 | B26: Contact Person | D26: Mr. A. Sharma | E26: MANUAL | F26: 5
A27: PH_022 | B27: Mobile | D27: +91-98XXXXXXXX | E27: MANUAL | F27: 5
A28: PH_023 | B28: Email | D28: name@company.com | E28: MANUAL | F28: 5
A29: PH_024 | B29: Site Address (full) | D29: Kandla, Gujarat | E29: MANUAL | F29: 5
A30: PH_025 | B30: Latitude | D30: 23.0339 | E30: MANUAL | F30: 5
A31: PH_026 | B31: Longitude | D31: 70.2167 | E31: MANUAL | F31: 5
A32: PH_027 | B32: Type of Installation | D32: Rooftop - Shed | E32: MANUAL | F32: 5
A33: PH_028 | B33: Type of Roofs | D33: Metal Sheet | E33: MANUAL | F33: 5
A34: PH_029 | B34: Availability of Water | D34: Yes | E34: Optional | F34: 5
A35: PH_030 | B35: Shading | D35: Shadow-free | E35: Optional | F35: 5
A36: PH_031 | B36: Site GMap Image Path | D36: C:\Proposals\site.png | E36: Optional | F36: 5
A37: 3 · CAPACITY ASSESSMENT (2.1)
A38: PH_032 | B38: Capacity — Shadow-free area: kWp | D38: 910 | E38: Yes | F38: 6
A39: PH_033 | B39: Capacity — Shadow-free area: Notes | C39: Usable shadow-free roof area | D39: Usable shadow-free roof area | E39: Optional | F39: 6
A40: PH_034 | B40: Capacity — Electricity consumption: kWp | D40: 910 | E40: Yes | F40: 6
A41: PH_035 | B41: Capacity — Electricity consumption: Notes | C41: ~42% of annual consumption | D41: ~42% of annual consumption | E41: Optional | F41: 6
A42: PH_036 | B42: Capacity — State regulatory limit: kWp | D42: No limit | E42: Optional | F42: 6
A43: PH_037 | B43: Capacity — State regulatory limit: Notes | C43: Net metering norms | D43: Net metering norms | E43: Optional | F43: 6
A44: PH_038 | B44: Capacity — Proposed Capacity: kWp | D44: 910 | E44: Yes | F44: 6
A45: PH_039 | B45: Capacity — Proposed Capacity: Notes | C45: Final proposed plant size | D45: Final proposed plant size | E45: Optional | F45: 6
A46: 4 · PLANT LAYOUT (2.2)
A47: PH_040 | B47: Plant Layout — Type of Installation | D47: Rooftop - Shed | E47: Yes | F47: 6-8
A48: PH_041 | B48: Plant Layout — Type of Mounting | D48: Metal sheet roof mounting | E48: Yes | F48: 6-8
A49: PH_042 | B49: Plant Layout — Power Evacuation | D49: LT side, synchronised with grid | E49: Yes | F49: 6-8
A50: PH_043 | B50: Rooftop · Row1 — Shed/Building | D50: Shed A | E50: Optional | F50: 6-8
A51: PH_044 | B51: Rooftop · Row1 — Capacity (kWp) | D51: 300 | E51: Optional | F51: 6-8
A52: PH_045 | B52: Rooftop · Row1 — Tilt | D52: 10° | E52: Optional | F52: 6-8
A53: PH_046 | B53: Rooftop · Row1 — Azimuth | D53: 180° | E53: Optional | F53: 6-8
A54: PH_047 | B54: Rooftop · Row1 — Walkways/Lifeline | D54: Yes | E54: Optional | F54: 6-8
A55: PH_048 | B55: Rooftop · Row2 — Shed/Building | D55: Shed B | E55: Optional | F55: 6-8
A56: PH_049 | B56: Rooftop · Row2 — Capacity (kWp) | D56: 300 | E56: Optional | F56: 6-8
A57: PH_050 | B57: Rooftop · Row2 — Tilt | D57: 10° | E57: Optional | F57: 6-8
A58: PH_051 | B58: Rooftop · Row2 — Azimuth | D58: 180° | E58: Optional | F58: 6-8
A59: PH_052 | B59: Rooftop · Row2 — Walkways/Lifeline | D59: Yes | E59: Optional | F59: 6-8
A60: PH_053 | B60: Rooftop · Total Capacity (kWp) | C60: =C51+C56&" kWp" -> 0 kWp | D60: 600 | E60: Optional | F60: 6-8
A61: PH_054 | B61: Shed · Row1 — Shed/Building | D61: Shed A | E61: Optional | F61: 6-8
A62: PH_055 | B62: Shed · Row1 — Capacity (kWp) | D62: 300 | E62: Optional | F62: 6-8
A63: PH_056 | B63: Shed · Row1 — Tilt | D63: 10° | E63: Optional | F63: 6-8
A64: PH_057 | B64: Shed · Row1 — Azimuth | D64: 180° | E64: Optional | F64: 6-8
A65: PH_058 | B65: Shed · Row1 — Walkways/Lifeline/Railings | D65: Yes | E65: Optional | F65: 6-8
A66: PH_059 | B66: Shed · Row2 — Shed/Building | D66: Shed B | E66: Optional | F66: 6-8
A67: PH_060 | B67: Shed · Row2 — Capacity (kWp) | D67: 300 | E67: Optional | F67: 6-8
A68: PH_061 | B68: Shed · Row2 — Tilt | D68: 10° | E68: Optional | F68: 6-8
A69: PH_062 | B69: Shed · Row2 — Azimuth | D69: 180° | E69: Optional | F69: 6-8
A70: PH_063 | B70: Shed · Row2 — Walkways/Lifeline/Railings | D70: Yes | E70: Optional | F70: 6-8
A71: PH_064 | B71: Shed · Total Capacity (kWp) | C71: =C62+C67&" kWp" -> 0 kWp | D71: 600 | E71: Optional | F71: 6-8
A72: PH_065 | B72: Ground · Type of Installation | D72: Ground Mount | E72: Optional | F72: 7
A73: PH_066 | B73: Ground · Azimuth (deg) | D73: 180° | E73: Optional | F73: 7
A74: PH_067 | B74: Ground · Tilt (deg) | D74: 15° | E74: Optional | F74: 7
A75: PH_068 | B75: Ground · Type of Mounting | D75: Fixed tilt | E75: Optional | F75: 7
A76: PH_069 | B76: Ground · Power Evacuation | D76: HT side | E76: Optional | F76: 7
A77: PH_070 | B77: Ground · Fencing | D77: Chain-link, 6 ft | E77: Optional | F77: 7
A78: PH_071 | B78: Ground · Plant Lighting | D78: Yes | E78: Optional | F78: 7
A79: PH_072 | B79: Carport/Float · Type of Installation | D79: Carport | E79: Optional | F79: 7
A80: PH_073 | B80: Carport/Float · Azimuth (deg) | D80: 180° | E80: Optional | F80: 7
A81: PH_074 | B81: Carport/Float · Tilt (deg) | D81: 10° | E81: Optional | F81: 7
A82: PH_075 | B82: Carport/Float · Type of Mounting | D82: Steel structure | E82: Optional | F82: 7
A83: PH_076 | B83: Carport/Float · Power Evacuation | D83: LT side | E83: Optional | F83: 7
... A85: PH_078 | B85: Carport/Float · Plant Lighting | D85: Yes | E85: Optional | F85: 7
A86: 5 · ESTIMATED GENERATION (2.3)
A87: PH_079 | B87: Gen — Type of System | D87: Grid-tied rooftop solar | E87: MANUAL | F87: 9
A88: PH_080 | B88: Gen — Estimated Generation (kWh/year) | D88: 12,50,000 | E88: Yes | F88: 9
A89: PH_081 | B89: Gen — Degradation | D89: 2.5% Yr-1, 0.7% p.a. thereafter | E89: Optional | F89: 9
A90: PH_082 | B90: Gen — Guaranteed Generation (kWh/year) | D90: 11,25,000 | E90: Yes | F90: 9
A91: PH_083 | B91: Gen — Plant Life (Years) | D91: 25 | E91: MANUAL | F91: 9
A92: PH_084 | B92: Gen — Irradiation (kWh/m²/yr) | D92: 1,850 | E92: MANUAL | F92: 9
A93: 6 · BILL OF MATERIAL (2.4) — Specifications
A94: PH_085 | B94: BOM · PV Module — Type | C94: ='BOM Inputs'!D3 -> Monocrystalline PERC | D94: Monocrystalline PERC | E94: Yes | F94: 10-11
A95: PH_086 | B95: BOM · PV Module — Make / Model | C95: ='BOM Inputs'!D4 -> Renewsys 595 Wp | D95: Renewsys 595 Wp | E95: Yes | F95: 10-11
A96: PH_087 | B96: BOM · PV Module — Efficiency | C96: ='BOM Inputs'!D5 -> 21.3% | D96: 21.3% | E96: Optional | F96: 10-11
A97: PH_088 | B97: BOM · Inverter — Type | C97: ='BOM Inputs'!D6 -> String inverter | D97: String inverter | E97: Yes | F97: 10-11
A98: PH_089 | B98: BOM · Inverter — Env. Class / Location | C98: ='BOM Inputs'!D7 -> IP66, outdoor | D98: IP66, outdoor | E98: Optional | F98: 10-11
A99: PH_090 | B99: BOM · Inverter — Make / Model | C99: ='BOM Inputs'!D8 -> Solis | D99: Solis | E99: Yes | F99: 10-11
A100: PH_091 | B100: BOM · Mounting Structure — Type | C100: ='BOM Inputs'!D9 -> Galvanised steel | D100: Galvanised steel | E100: Yes | F100: 10-11
A101: PH_092 | B101: BOM · Mounting Structure — Make | C101: ='BOM Inputs'!D10 -> Standard GI | D101: Standard GI | E101: Optional | F101: 10-11
...

Sheet BOM Inputs
B3: PH_085 | C3: BOM · PV Module — Type | D3: Monocrystalline PERC
B4: PH_086 | C4: BOM · PV Module — Make / Model | D4: Renewsys 595 Wp
B5: PH_087 | C5: BOM · PV Module — Efficiency | D5: 21.3%
B6: PH_088 | C6: BOM · Inverter — Type | D6: String inverter
B7: PH_089 | C7: BOM · Inverter — Env. Class / Location | D7: IP66, outdoor
B8: PH_090 | C8: BOM · Inverter — Make / Model | D8: Solis
B9: PH_091 | C9: BOM · Mounting Structure — Type | D9: Galvanised steel
B10: PH_092 | C10: BOM · Mounting Structure — Make | D10: Standard GI
B11: PH_093 | C11: BOM · DC Cable — Make / Size | D11: Polycab, 4/6 sq.mm
B12: PH_094 | C12: BOM · AC Cable — Make / Size | D12: Polycab, as per design
B13: PH_095 | C13: BOM · Cable Tray — Type / Size | D13: GI perforated
B14: PH_096 | C14: BOM · LT Switchgear — Type/Make/Rating | D14: ABB/Schneider, as per design
... B37: PH_119 | C37: BOM · Net Metering Cubicle — Make | D37: As per design

Sheet Environmental Benefits (2)
B2: Environmental Impact Cumulative Impact
B3: Emmission Data (kg/kWh) consumed / emmitted
B4: Coal* | C4: 0.47 | D4: kg/kWh
B5: Cox* | C5: 0.97 | D5: kg/kWh
B6: Sox** | C6: 0.007 | D6: kg/kWh
B7: Nox** | C7: 0.0043 | D7: kg/kWh
B8: Water*** | C8: 2.3 | D8: L/kWh
B9: CO2 absorption by trees**** | C9: =48/2.20462 -> 21.77246 | D9: kgs / tree year
B10: Total Capacity Installed | C10: ='Proposal Inputs'!C5 -> 0 | D10: KWp
B11: P50 Value - KWH/kWp per day | C11: 4 | D11: KWH/kWp per day
B12: Estimated Generation | C12: =C11*365*C10 -> 0 | D12: KWH
B13: Average CUF | C13: =C12/(C10*365*24) -> #DIV/0! | D13: %
B15: Average reduction when compared to a coal powered plant (Tons / Year)
B16: System | C16: Coal | D16: Sulphur oxides | E16: Nitrogen oxides | F16: Carbon oxides | G16: Water (Litres)
B17: Option | C17: =C10*C13*24*365*C4/10^3 -> #DIV/0! | D17: =C10*C13*24*365*C6/10^3 -> #DIV/0! | E17: =C10*C13*24*365*C7/10^3 -> #DIV/0! | F17: =C10*C13*24*365*C5/10^3 -> #DIV/0! | G17: =C10*C13*24*365*C8 -> #DIV/0!
B19: Carbon offset expressed as number of mature trees planted | C19: =F17/C9*10^3 -> #DIV/0!
B20: *https://www.eia.gov
B21: **https://www3.epa.gov/ttnchie1/conference/ei20/session5/mmittal.pdf
B22: ***http://breakingenergy.com/2014/03/24/infographic-water-used-by-power-plants/
B23: ****http://www.arborenvironmentalalliance.com/carbon-tree-facts.asp

Sheet Inputs and Output
C3: PROJECT INPUTS & ASSUMPTIONS | G3: OUTPUT | Y3: Institutional | Z3: Yes | AA3: Apr-Sept
Y4: Corporate | Z4: No | AA4: Oct-Mar
C5: Project Data | G5: Item | H5: Unit | I5: Value
C6: Capacity | D6: 500 | E6: kWp | G6: System Size | H6: kWp | I6: =Workings!D3 -> 500
C7: Project cost (excls. GST) | D7: 43.950051 | E7: INR/Wp | G7: System cost (including GST) | H7: Rs. Lacs | I7: =Workings!D4/10^5 -> 239.30803 | Y7: Tax Calculation
C8: GST | D8: =D7*8.9% -> 3.9115546 | E8: INR | L8: Things to note | Y8: Old | Z8: New
C9: Project Cost (incls. of GST) | D9: =D7+D8 -> 47.861606 | E9: INR/Wp | G9: GST Input Credit | H9: Rs. Lacs | I9: =Workings!D6/10^5 -> 19.557773 | K9: 1 | L9: The project cost in Cell D7 to be input is exclusive of GST cost. | Y9: =30%*1.12*1.04 -> 0.34944 | Z9: =22%*1.12*1.04 -> 0.256256
C10: Project Life | D10: 25 | E10: Years | G10: Net cost to client | H10: Rs. Lacs | I10: =I7-I8-I9 -> 219.75026 | K10: 2 | L10: If you are giving AMC free for the 1st year, kindly modify the formula in the workingsaccodingly.
C11: Inverter Life | D11: 5 | E11: Years | G11: AMC cost | H11: Rs. Lacs/year | I11: =Workings!D8/10^5 -> 3.25 | K11: 3 | L11: Please Select Yes/No in cell D16 in client is able to claim GST Input Credit.
C12: O&M Cost | D12: 650 | E12: INR/kWp | G12: Solar Units generated in the first year. | H12: Units / year | I12: =Workings!D12 -> 657000 | AO12: `
C13: O&M Escalation | D13: 0.05 | E13: % p.a. | G13: Present Power tariff | H13: Rs/ unit | I13: =Workings!D13 -> 7.08
C14: Daily Generation | D14: 3.6 | E14: kWh/kWp/day | G14: Avg. EB tariff increase | H14: % p.a. | I14: =Workings!D14 -> 0.02
C15: Insurance | D15: 0.002 | E15: Book value | G15: Savings in Year 1 (post tax) | H15: Rs. Lacs | I15: =Workings!D15/10^5 -> 50.964649
C16: Equipment change | D16: 0.01 | E16: Project cost | G16: Payback period | H16: Years | I16: =Workings!D16 -> 5.1375593
C17: GST Input Credit | D17: Yes | G17: Project life | H17: Years | I17: =Workings!D17 -> 25
G18: Inverter life | H18: Years | I18: =Workings!D18 -> 5
C19: Entity type | D19: Corporate | G19: Net savings over project life | H19: Rs. Lacs | I19: =Workings!D19/10^5 -> 697.97713
C20: Additional depreciation (20%) | D20: =IF(D30="No","Yes","No") -> No | G20: Total units generated over project life | H20: Lac Units | I20: =Workings!D20/10^5 -> 152.424
C21: Commissioning period | D21: Apr-Sept | G21: Project IRR - Post Tax | H21: % | I21: =Workings!D22 -> 0.17679782
G22: Equity IRR - Post Tax | H22: % | I22: =Workings!D23 -> 0.35802673
C23: Module Degradation | G23: Levalized cost of generation | H23: Rs / kWh | I23: =Workings!D21 -> 3.8853246
C24: Year 0 | D24: 0 | E24: % p.a. | G24: *The above analysis is post tax and includes expenses expected to be incurred for operation of the solar project
C25: Year 1 | D25: 0.006 | E25: % p.a.
C26: Year 2-11 | D26: 0.006 | E26: % p.a.
C27: Year 12-25 | D27: 0.006 | E27: % p.a.
C29: AD Benefit
C30: New Tax Applicable | D30: Yes
C31: Depreciation Rate | D31: 0.4 | E31: % p.a.
C32: Tax Rate | D32: =IF(D30="No",Y9,Z9) -> 0.256256 | E32: %
C33: Disc. Rate (for NPV) | D33: 0.12 | E33: %
C34: EB Data
C35: Current Tariff | D35: =8.5-1.42 -> 7.08 | E35: INR/kWh
C36: EB Tariff Escalation | D36: 0.02 | E36: % p.a.
C38: Leverage
C39: Debt | D39: 0.7 | E39: %
C40: Interest rate | D40: 0.1 | E40: %
C41: Tenure | D41: 10 | E41: years

Sheet Workings
B2: Item | C2: Unit | D2: Value (with 40% AD) | F2: AD Benefit (Rs.) | L2: Corporate Depreciation (Rs.) | R2: Loan Calculator
B3: System Size | C3: kWp | D3: ='Inputs and Output'!D6 -> 500 | G3: Opening Val | H3: Depreciation | I3: WDV-Closing | J3: AD Benefit | M3: Opening Val | N3: Depreciation | O3: Closing WDV | R3: Years | S3: Opening Val | T3: EMI | U3: Interest | V3: Principal | W3: Closing | X3: Check
B4: System cost | C4: Rs | D4: =D3*'Inputs and Output'!D9*1000 -> 23930803 | F4: Year 0 | G4: =IF('Inputs and Output'!D17="Yes",'Inputs and Output'!D6*'Inputs and Output'!D7*1000,'Inputs and Output'!D6*'Inputs and Output'!D9*1000) -> 21975026 | H4: =IF('Inputs and Output'!D21="Oct-Mar",G4*('Inputs and Output'!$D$31+IF('Inputs and Output'!D20="Yes",20%,0))*1/2,G4*('Inputs and Output'!$D$31+IF('Inputs and Output'!D20="Yes",20%,0))) -> 8790010.3 | I4: =G4-H4 -> 13185015 | J4: =H4*'Inputs and Output'!$D$32 -> 2252492.9 | L4: Year 0 | M4: =G4 -> 21975026 | N4: =M4*$D$11 -> 2480980.4 | O4: =M4-N4 -> 19494045 | R4: 0 | S4: 0 | W4: =D4*'Inputs and Output'!D39 -> 16751562 | X4: =IF(R4>'Inputs and Output'!$D$41,0,1) -> 1
B5: Tax benefit of depreciation (in year 0) | C5: Rs | F5: Year 1 | G5: =I4 -> 13185015 | H5: =IF('Inputs and Output'!D21="Oct-Mar",(G5*'Inputs and Output'!$D$31)+(Workings!G4*10%),(G5*'Inputs and Output'!$D$31)) -> 5274006.2 | I5: =G5-H5 -> 7911009.3 | J5: =H5*'Inputs and Output'!$D$32 -> 1351495.7 | L5: Year 1 | M5: =O4 -> 19494045 | N5: =M5*$D$11 -> 2200877.7 | O5: =M5-N5 -> 17293168 | R5: 1 | S5: =W4 -> 16751562 | T5: =PMT('Inputs and Output'!D40,'Inputs and Output'!D41,-Workings!$W$4) -> 2726239.6 | U5: =S5*'Inputs and Output'!$D$40 -> 1675156.2 | V5: =T5-U5 -> 1051083.4 | W5: =S5-V5 -> 15700479 | X5: =IF(R5>'Inputs and Output'!$D$41,0,1) -> 1
B6: GST Input Credit | C6: Rs. | D6: =IF('Inputs and Output'!$D$17="Yes",'Inputs and Output'!D6*'Inputs and Output'!D8*1000,0) -> 1955777.3 | F6: Year 2 | G6: =I5 -> 7911009.3 | H6: =G6*'Inputs and Output'!$D$31 -> 3164403.7 | I6: =G6-H6 -> 4746605.6 | J6: =H6*'Inputs and Output'!$D$32 -> 810897.44 | L6: Year 2 | M6: =O5 -> 17293168 | N6: =M6*$D$11 -> 1952398.6 | O6: =M6-N6 -> 15340769 | R6: 2 | S6: =W5 -> 15700479 | T6: =T5*X6 -> 2726239.6 | U6: =S6*'Inputs and Output'!$D$40 -> 1570047.9 | V6: =T6-U6 -> 1156191.7 | W6: =S6-V6 -> 14544287 | X6: =IF(R6>'Inputs and Output'!$D$41,0,1) -> 1
B7: Net cost to client | C7: Rs | D7: =D4-D5-D6 -> 21975026 | F7: Year 3 | G7: =I6 -> 4746605.6 | H7: =G7*'Inputs and Output'!$D$31 -> 1898642.2 | I7: =G7-H7 -> 2847963.3 | J7: =H7*'Inputs and Output'!$D$32 -> 486538.46 | L7: Year 3 | M7: =O6 -> 15340769 | N7: =M7*$D$11 -> 1731972.8 | O7: =M7-N7 -> 13608796 | R7: 3 | S7: =W6 -> 14544287 | T7: =T6*X7 -> 2726239.6 | U7: =S7*'Inputs and Output'!$D$40 -> 1454428.7 | V7: =T7-U7 -> 1271810.9 | W7: =S7-V7 -> 13272476 | X7: =IF(R7>'Inputs and Output'!$D$41,0,1) -> 1
B8: AMC cost (For the 1st year) | C8: Rs/year | D8: =D3*'Inputs and Output'!D12 -> 325000 | F8: Year 4 | G8: =I7 -> 2847963.3 | H8: =G8*'Inputs and Output'!$D$31 -> 1139185.3 | I8: =G8-H8 -> 1708778 | J8: =H8*'Inputs and Output'!$D$32 -> 291923.08 | L8: Year 4 | M8: =O7 -> 13608796 | N8: =M8*$D$11 -> 1536433.1 | O8: =M8-N8 -> 12072363 | R8: 4 | S8: =W7 -> 13272476 | T8: =T7*X8 -> 2726239.6 | U8: =S8*'Inputs and Output'!$D$40 -> 1327247.6 | V8: =T8-U8 -> 1398992 | W8: =S8-V8 -> 11873484 | X8: =IF(R8>'Inputs and Output'!$D$41,0,1) -> 1
B9: Insurance | C9: Book value | D9: ='Inputs and Output'!D15 -> 0.002 | F9: Year 5 | G9: =I8 -> 1708778 | H9: =G9*'Inputs and Output'!$D$31 -> 683511.2 | I9: =G9-H9 -> 1025266.8 | J9: =H9*'Inputs and Output'!$D$32 -> 175153.85 | L9: Year 5 | M9: =O8 -> 12072363 | N9: =M9*$D$11 -> 1362969.8 | O9: =M9-N9 -> 10709393 | R9: 5 | S9: =W8 -> 11873484 | T9: =T8*X9 -> 2726239.6 | U9: =S9*'Inputs and Output'!$D$40 -> 1187348.4 | V9: =T9-U9 -> 1538891.2 | W9: =S9-V9 -> 10334593 | X9: =IF(R9>'Inputs and Output'!$D$41,0,1) -> 1
B10: Equipment change | C10: p.a. | D10: ='Inputs and Output'!D16 -> 0.01 | F10: Year 6 | G10: =I9 -> 1025266.8 | H10: =G10*'Inputs and Output'!$D$31 -> 410106.72 | I10: =G10-H10 -> 615160.08 | J10: =H10*'Inputs and Output'!$D$32 -> 105092.31 | L10: Year 6 | M10: =O9 -> 10709393 | N10: =M10*$D$11 -> 1209090.5 | O10: =M10-N10 -> 9500302.8 | R10: 6 | S10: =W9 -> 10334593 | T10: =T9*X10 -> 2726239.6 | U10: =S10*'Inputs and Output'!$D$40 -> 1033459.3 | V10: =T10-U10 -> 1692780.3 | W10: =S10-V10 -> 8641812.7 | X10: =IF(R10>'Inputs and Output'!$D$41,0,1) -> 1
B11: Companies Act depreciation | D11: 0.1129 | F11: Year 7 | G11: =I10 -> 615160.08 | H11: =G11*'Inputs and Output'!$D$31 -> 246064.03 | I11: =G11-H11 -> 369096.05 | J11: =H11*'Inputs and Output'!$D$32 -> 63055.385 | L11: Year 7 | M11: =O10 -> 9500302.8 | N11: =M11*$D$11 -> 1072584.2 | O11: =M11-N11 -> 8427718.6 | R11: 7 | S11: =W10 -> 8641812.7 | T11: =T10*X11 -> 2726239.6 | U11: =S11*'Inputs and Output'!$D$40 -> 864181.27 | V11: =T11-U11 -> 1862058.3 | W11: =S11-V11 -> 6779754.4 | X11: =IF(R11>'Inputs and Output'!$D$41,0,1) -> 1
B12: Avg. solar units generated | C12: units / year | D12: =D3*'Inputs and Output'!$D$14*365 -> 657000 | F12: Year 8 | G12: =I11 -> 369096.05 | H12: =G12*'Inputs and Output'!$D$31 -> 147638.42 | I12: =G12-H12 -> 221457.63 | J12: =H12*'Inputs and Output'!$D$32 -> 37833.231 | L12: Year 8 | M12: =O11 -> 8427718.6 | N12: =M12*$D$11 -> 951489.43 | O12: =M12-N12 -> 7476229.2 | R12: 8 | S12: =W11 -> 6779754.4 | T12: =T11*X12 -> 2726239.6 | U12: =S12*'Inputs and Output'!$D$40 -> 677975.44 | V12: =T12-U12 -> 2048264.2 | W12: =S12-V12 -> 4731490.2 | X12: =IF(R12>'Inputs and Output'!$D$41,0,1) -> 1
B13: Present Power tariff | C13: Rs/ unit | D13: ='Inputs and Output'!D35 -> 7.08 | F13: Year 9 | G13: =I12 -> 221457.63 | H13: =G13*'Inputs and Output'!$D$31 -> 88583.052 | I13: =G13-H13 -> 132874.58 | J13: =H13*'Inputs and Output'!$D$32 -> 22699.938 | L13: Year 9 | M13: =O12 -> 7476229.2 | N13: =M13*$D$11 -> 844066.27 | O13: =M13-N13 -> 6632162.9 | R13: 9 | S13: =W12 -> 4731490.2 | T13: =T12*X13 -> 2726239.6 | U13: =S13*'Inputs and Output'!$D$40 -> 473149.02 | V13: =T13-U13 -> 2253090.6 | W13: =S13-V13 -> 2478399.6 | X13: =IF(R13>'Inputs and Output'!$D$41,0,1) -> 1
B14: Avg. EB tariff increase | C14: % p.a. | D14: ='Inputs and Output'!D36 -> 0.02 | F14: Year 10 | G14: =I13 -> 132874.58 | H14: =G14*'Inputs and Output'!$D$31 -> 53149.831 | I14: =G14-H14 -> 79724.746 | J14: =H14*'Inputs and Output'!$D$32 -> 13619.963 | L14: Year 10 | M14: =O13 -> 6632162.9 | N14: =M14*$D$11 -> 748771.19 | O14: =M14-N14 -> 5883391.7 | R14: 10 | S14: =W13 -> 2478399.6 | T14: =T13*X14 -> 2726239.6 | U14: =S14*'Inputs and Output'!$D$40 -> 247839.96 | V14: =T14-U14 -> 2478399.6 | W14: =S14-V14 -> -1.44355e-08 | X14: =IF(R14>'Inputs and Output'!$D$41,0,1) -> 1
B15: Savings in Year 1 (post tax) | C15: Rs. For 1st year | D15: =R36 -> 5096464.9 | F15: Year 11 | G15: =I14 -> 79724.746 | H15: =G15*'Inputs and Output'!$D$31 -> 31889.899 | I15: =G15-H15 -> 47834.848 | J15: =H15*'Inputs and Output'!$D$32 -> 8171.9779 | L15: Year 11 | M15: =O14 -> 5883391.7 | N15: =M15*$D$11 -> 664234.92 | O15: =M15-N15 -> 5219156.8 | R15: 11 | S15: =W14 -> -1.44355e-08 | T15: =T14*X15 -> 0 | U15: =S15*'Inputs and Output'!$D$40 -> -1.44355e-09 | V15: =T15-U15 -> 1.44355e-09 | W15: =S15-V15 -> -1.587905e-08 | X15: =IF(R15>'Inputs and Output'!$D$41,0,1) -> 0
B16: Payback period | C16: Years | D16: =MIN(AB36:AB60) -> 5.1375593 | F16: Year 12 | G16: =I15 -> 47834.848 | H16: =G16*'Inputs and Output'!$D$31 -> 19133.939 | I16: =G16-H16 -> 28700.909 | J16: =H16*'Inputs and Output'!$D$32 -> 4903.1867 | L16: Year 12 | M16: =O15 -> 5219156.8 | N16: =M16*$D$11 -> 589242.8 | O16: =M16-N16 -> 4629914 | R16: 12 | S16: =W15 -> -1.587905e-08 | T16: =T15*X16 -> 0 | U16: =S16*'Inputs and Output'!$D$40 -> -1.587905e-09 | V16: =T16-U16 -> 1.587905e-09 | W16: =S16-V16 -> -1.7466955e-08 | X16: =IF(R16>'Inputs and Output'!$D$41,0,1) -> 0
B17: Project life | C17: Years | D17: ='Inputs and Output'!D10 -> 25 | F17: Year 13 | G17: =I16 -> 28700.909 | H17: =G17*'Inputs and Output'!$D$31 -> 11480.363 | I17: =G17-H17 -> 17220.545 | J17: =H17*'Inputs and Output'!$D$32 -> 2941.912 | L17: Year 13 | M17: =O16 -> 4629914 | N17: =M17*$D$11 -> 522717.29 | O17: =M17-N17 -> 4107196.7 | R17: 13 | S17: =W16 -> -1.7466955e-08 | T17: =T16*X17 -> 0 | U17: =S17*'Inputs and Output'!$D$40 -> -1.7466955e-09 | V17: =T17-U17 -> 1.7466955e-09 | W17: =S17-V17 -> -1.921365e-08 | X17: =IF(R17>'Inputs and Output'!$D$41,0,1) -> 0
B18: Inverter life | C18: Years | D18: ='Inputs and Output'!D11 -> 5 | F18: Year 14 | G18: =I17 -> 17220.545 | H18: =G18*'Inputs and Output'!$D$31 -> 6888.2181 | I18: =G18-H18 -> 10332.327 | J18: =H18*'Inputs and Output'!$D$32 -> 1765.1472 | L18: Year 14 | M18: =O17 -> 4107196.7 | N18: =M18*$D$11 -> 463702.51 | O18: =M18-N18 -> 3643494.2 | R18: 14 | S18: =W17 -> -1.921365e-08 | T18: =T17*X18 -> 0 | U18: =S18*'Inputs and Output'!$D$40 -> -1.921365e-09 | V18: =T18-U18 -> 1.921365e-09 | W18: =S18-V18 -> -2.1135015e-08 | X18: =IF(R18>'Inputs and Output'!$D$41,0,1) -> 0
B19: Net savings over project life | C19: Rs. | D19: =R61 -> 69797713 | F19: Year 15 | G19: =I18 -> 10332.327 | H19: =G19*'Inputs and Output'!$D$31 -> 4132.9309 | I19: =G19-H19 -> 6199.3963 | J19: =H19*'Inputs and Output'!$D$32 -> 1059.0883 | L19: Year 15 | M19: =O18 -> 3643494.2 | N19: =M19*$D$11 -> 411350.49 | O19: =M19-N19 -> 3232143.7 | R19: 15 | S19: =W18 -> -2.1135015e-08 | T19: =T18*X19 -> 0 | U19: =S19*'Inputs and Output'!$D$40 -> -2.1135015e-09 | V19: =T19-U19 -> 2.1135015e-09 | W19: =S19-V19 -> -2.3248517e-08 | X19: =IF(R19>'Inputs and Output'!$D$41,0,1) -> 0
B20: Total units generated over project life | C20: units | D20: =E61 -> 15242400 | F20: Year 16 | G20: =I19 -> 6199.3963 | H20: =G20*'Inputs and Output'!$D$31 -> 2479.7585 | I20: =G20-H20 -> 3719.6378 | J20: =H20*'Inputs and Output'!$D$32 -> 635.453 | L20: Year 16 | M20: =O19 -> 3232143.7 | N20: =M20*$D$11 -> 364909.02 | O20: =M20-N20 -> 2867234.7 | R20: 16 | S20: =W19 -> -2.3248517e-08 | T20: =T19*X20 -> 0 | U20: =S20*'Inputs and Output'!$D$40 -> -2.3248517e-09 | V20: =T20-U20 -> 2.3248517e-09 | W20: =S20-V20 -> -2.5573369e-08 | X20: =IF(R20>'Inputs and Output'!$D$41,0,1) -> 0
B21: Cost of Generation (Post Tax) | C21: Rs / unit | D21: =NPV('Inputs and Output'!D33,Workings!X35:X60)/NPV('Inputs and Output'!D33,Workings!E36:E60) -> 3.8853246 | F21: Year 17 | G21: =I20 -> 3719.6378 | H21: =G21*'Inputs and Output'!$D$31 -> 1487.8551 | I21: =G21-H21 -> 2231.7827 | J21: =H21*'Inputs and Output'!$D$32 -> 381.2718 | L21: Year 17 | M21: =O20 -> 2867234.7 | N21: =M21*$D$11 -> 323710.79 | O21: =M21-N21 -> 2543523.9 | R21: 17 | S21: =W20 -> -2.5573369e-08 | T21: =T20*X21 -> 0 | U21: =S21*'Inputs and Output'!$D$40 -> -2.5573369e-09 | V21: =T21-U21 -> 2.5573369e-09 | W21: =S21-V21 -> -2.8130706e-08 | X21: =IF(R21>'Inputs and Output'!$D$41,0,1) -> 0
B22: Project IRR | C22: % | D22: =IRR(Y35:Y60) -> 0.17679782 | F22: Year 18 | G22: =I21 -> 2231.7827 | H22: =G22*'Inputs and Output'!$D$31 -> 892.71306 | I22: =G22-H22 -> 1339.0696 | J22: =H22*'Inputs and Output'!$D$32 -> 228.76308 | L22: Year 18 | M22: =O21 -> 2543523.9 | N22: =M22*$D$11 -> 287163.85 | O22: =M22-N22 -> 2256360 | R22: 18 | S22: =W21 -> -2.8130706e-08 | T22: =T21*X22 -> 0 | U22: =S22*'Inputs and Output'!$D$40 -> -2.8130706e-09 | V22: =T22-U22 -> 2.8130706e-09 | W22: =S22-V22 -> -3.0943776e-08 | X22: =IF(R22>'Inputs and Output'!$D$41,0,1) -> 0
B23: Equity IRR | C23: % | D23: =IRR(R35:R60) -> 0.35802673 | F23: Year 19 | G23: =I22 -> 1339.0696 | H23: =G23*'Inputs and Output'!$D$31 -> 535.62784 | I23: =G23-H23 -> 803.44176 | J23: =H23*'Inputs and Output'!$D$32 -> 137.25785 | L23: Year 19 | M23: =O22 -> 2256360 | N23: =M23*$D$11 -> 254743.05 | O23: =M23-N23 -> 2001617 | R23: 19 | S23: =W22 -> -3.0943776e-08 | T23: =T22*X23 -> 0 | U23: =S23*'Inputs and Output'!$D$40 -> -3.0943776e-09 | V23: =T23-U23 -> 3.0943776e-09 | W23: =S23-V23 -> -3.4038154e-08 | X23: =IF(R23>'Inputs and Output'!$D$41,0,1) -> 0
F24: Year 20 | G24: =I23 -> 803.44176 | H24: =G24*'Inputs and Output'!$D$31 -> 321.3767 | I24: =G24-H24 -> 482.06506 | J24: =H24*'Inputs and Output'!$D$32 -> 82.354709 | L24: Year 20 | M24: =O23 -> 2001617 | N24: =M24*$D$11 -> 225982.56 | O24: =M24-N24 -> 1775634.4 | R24: 20 | S24: =W23 -> -3.4038154e-08 | T24: =T23*X24 -> 0 | U24: =S24*'Inputs and Output'!$D$40 -> -3.4038154e-09 | V24: =T24-U24 -> 3.4038154e-09 | W24: =S24-V24 -> -3.7441969e-08 | X24: =IF(R24>'Inputs and Output'!$D$41,0,1) -> 0
F25: Year 21 | G25: =I24 -> 482.06506 | H25: =G25*'Inputs and Output'!$D$31 -> 192.82602 | I25: =G25-H25 -> 289.23903 | J25: =H25*'Inputs and Output'!$D$32 -> 49.412825 | L25: Year 21 | M25: =O24 -> 1775634.4 | N25: =M25*$D$11 -> 200469.13 | O25: =M25-N25 -> 1575165.3 | R25: 21 | S25: =W24 -> -3.7441969e-08 | T25: =T24*X25 -> 0 | U25: =S25*'Inputs and Output'!$D$40 -> -3.7441969e-09 | V25: =T25-U25 -> 3.7441969e-09 | W25: =S25-V25 -> -4.1186166e-08 | X25: =IF(R25>'Inputs and Output'!$D$41,0,1) -> 0
F26: Year 22 | G26: =I25 -> 289.23903 | H26: =G26*'Inputs and Output'!$D$31 -> 115.69561 | I26: =G26-H26 -> 173.54342 | J26: =H26*'Inputs and Output'!$D$32 -> 29.647695 | L26: Year 22 | M26: =O25 -> 1575165.3 | N26: =M26*$D$11 -> 177836.16 | O26: =M26-N26 -> 1397329.1 | R26: 22 | S26: =W25 -> -4.1186166e-08 | T26: =T25*X26 -> 0 | U26: =S26*'Inputs and Output'!$D$40 -> -4.1186166e-09 | V26: =T26-U26 -> 4.1186166e-09 | W26: =S26-V26 -> -4.5304783e-08 | X26: =IF(R26>'Inputs and Output'!$D$41,0,1) -> 0
F27: Year 23 | G27: =I26 -> 173.54342 | H27: =G27*'Inputs and Output'!$D$31 -> 69.417368 | I27: =G27-H27 -> 104.12605 | J27: =H27*'Inputs and Output'!$D$32 -> 17.788617 | L27: Year 23 | M27: =O26 -> 1397329.1 | N27: =M27*$D$11 -> 157758.46 | O27: =M27-N27 -> 1239570.7 | R27: 23 | S27: =W26 -> -4.5304783e-08 | T27: =T26*X27 -> 0 | U27: =S27*'Inputs and Output'!$D$40 -> -4.5304783e-09 | V27: =T27-U27 -> 4.5304783e-09 | W27: =S27-V27 -> -4.9835261e-08 | X27: =IF(R27>'Inputs and Output'!$D$41,0,1) -> 0
F28: Year 24 | G28: =I27 -> 104.12605 | H28: =G28*'Inputs and Output'!$D$31 -> 41.650421 | I28: =G28-H28 -> 62.475631 | J28: =H28*'Inputs and Output'!$D$32 -> 10.67317 | L28: Year 24 | M28: =O27 -> 1239570.7 | N28: =M28*$D$11 -> 139947.53 | O28: =M28-N28 -> 1099623.1 | R28: 24 | S28: =W27 -> -4.9835261e-08 | T28: =T27*X28 -> 0 | U28: =S28*'Inputs and Output'!$D$40 -> -4.9835261e-09 | V28: =T28-U28 -> 4.9835261e-09 | W28: =S28-V28 -> -5.4818787e-08 | X28: =IF(R28>'Inputs and Output'!$D$41,0,1) -> 0
F29: Year 25 | G29: =I28 -> 62.475631 | H29: =G29*'Inputs and Output'!$D$31 -> 24.990252 | I29: =G29-H29 -> 37.485379 | J29: =H29*'Inputs and Output'!$D$32 -> 6.4039021 | L29: Year 25 | M29: =O28 -> 1099623.1 | N29: =M29*$D$11 -> 124147.45 | O29: =M29-N29 -> 975475.69 | R29: 25 | S29: =W28 -> -5.4818787e-08 | T29: =T28*X29 -> 0 | U29: =S29*'Inputs and Output'!$D$40 -> -5.4818787e-09 | V29: =T29-U29 -> 5.4818787e-09 | W29: =S29-V29 -> -6.0300666e-08 | X29: =IF(R29>'Inputs and Output'!$D$41,0,1) -> 0
F31: Tax benefit of depreciation (in year 0) | J31: =J4 -> 2252492.9
I33: OPEX COSTS | L33: Interest, Depreciation & Tax Benefit | R33: Equity Returns | V33: Project Details
B34: Year | C34: Degradation | D34: Cum. Degradation | E34: Solar power generation | F34: EB tariff | G34: Grid cost | H34: Grid cost (Post Tax) | I34: AMC | J34: Insurance | K34: Equipment replacement | L34: Interest Cost on Loan | M34: Total Cost incurred | N34: Total Cost - tax benefit | O34: Depreciation tax benefit | P34: GST Benefit | Q34: Cost of Solar | R34: Net savings (post tax) | S34: Cum. Net savings | T34: Check | U34: Payback period | V34: Total Cost incurred | W34: Total Cost - tax benefit | X34: Cost of Solar | Y34: Net savings (post tax) | Z34: Cum. Net savings | AA34: Check | AB34: Payback period
B35: 0 | Q35: =D4*(1-'Inputs and Output'!D39) -> 7179240.9 | R35: =H35-Q35 -> -7179240.9 | S35: =R35 -> -7179240.9 | X35: =D4 -> 23930803 | Y35: =H35-X35 -> -23930803 | Z35: =Y35 -> -23930803 | AB35: =IF(AA34="",IF(AA35="","",B35-AA35/Y35),"")
B36: 1 | C36: ='Inputs and Output'!D24 -> 0 | D36: =C36 -> 0 | E36: =D12 -> 657000 | F36: =D13 -> 7.08 | G36: =E36*F36 -> 4651560 | H36: =G36*(1-'Inputs and Output'!$D$32) -> 3459569.8 | I36: =D8 -> 325000 | J36: =M4*$D$9 -> 43950.051 | L36: =U5 -> 1675156.2 | M36: =SUM(I36:L36) -> 2044106.3 | N36: =M36*'Inputs and Output'!$D$32 -> 523814.49 | O36: =J4 -> 2252492.9 | P36: =D6 -> 1955777.3 | Q36: =M36-N36-O36-P36 -> -2687978.4 | R36: =H36-Q36-V5 -> 5096464.9 | S36: =S35+R36 -> -2082776 | T36: =IF(S36<0,"",S36) | U36: =IF(T35="",IF(T36="","",B36-T36/R36),"") | V36: =SUM(I36:K36) -> 368950.05 | W36: =V36*'Inputs and Output'!$D$32 -> 94545.664 | X36: =V36-W36-O36-P36 -> -3933865.8 | Y36: =H36-X36 -> 7393435.6 | Z36: =Z35+Y36 -> -16537367 | AA36: =IF(Z36<0,"",Z36) | AB36: =IF(AA35="",IF(AA36="","",B36-AA36/Y36),"")
B37: 2 | C37: ='Inputs and Output'!D25 -> 0.006 | D37: =D36+C37 -> 0.006 | E37: =$E$36*(1-D37) -> 653058 | F37: =F36*(1+$D$14) -> 7.2216 | G37: =E37*F37 -> 4716123.7 | H37: =G37*(1-'Inputs and Output'!$D$32) -> 3507588.7 | I37: =$I$36*((1+'Inputs and Output'!$D$13)^(Workings!B37-1)) -> 341250 | J37: =M5*$D$9 -> 38988.091 | L37: =U6 -> 1570047.9 | M37: =SUM(I37:L37) -> 1950286 | N37: =M37*'Inputs and Output'!$D$32 -> 499772.48 | O37: =J5 -> 1351495.7 | Q37: =M37-N37-O37 -> 99017.758 | R37: =H37-Q37-V6 -> 2252379.2 | S37: =S36+R37 -> 169603.14 | T37: =IF(S37<0,"",S37) -> 169603.14 | U37: =IF(T36="",IF(T37="","",B37-T37/R37),"") -> 1.9247004 | V37: =SUM(I37:K37) -> 380238.09 | W37: =V37*'Inputs and Output'!$D$32 -> 97438.292 | X37: =V37-W37-O37-P37 -> -1068695.9 | Y37: =H37-X37 -> 4576284.6 | Z37: =Z36+Y37 -> -11961083 | AA37: =IF(Z37<0,"",Z37) | AB37: =IF(AA36="",IF(AA37="","",B37-AA37/Y37),"")
B38: 3 | C38: ='Inputs and Output'!D26 -> 0.006 | D38: =D37+C38 -> 0.012 | E38: =$E$36*(1-D38) -> 649116 | F38: =F37*(1+$D$14) -> 7.366032 | G38: =E38*F38 -> 4781409.2 | H38: =G38*(1-'Inputs and Output'!$D$32) -> 3556144.4 | I38: =$I$36*((1+'Inputs and Output'!$D$13)^(Workings!B38-1)) -> 358312.5 | J38: =M6*$D$9 -> 34586.335 | L38: =U7 -> 1454428.7 | M38: =SUM(I38:L38) -> 1847327.5 | N38: =M38*'Inputs and Output'!$D$32 -> 473388.77 | O38: =J6 -> 810897.44 | Q38: =M38-N38-O38 -> 563041.34 | R38: =H38-Q38-V7 -> 1721292.2 | S38: =S37+R38 -> 1890895.3 | T38: =IF(S38<0,"",S38) -> 1890895.3 | U38: =IF(T37="",IF(T38="","",B38-T38/R38),"") | V38: =SUM(I38:K38) -> 392898.84 | W38: =V38*'Inputs and Output'!$D$32 -> 100682.68 | X38: =V38-W38-O38-P38 -> -518681.29 | Y38: =H38-X38 -> 4074825.7 | Z38: =Z37+Y38 -> -7886257.1 | AA38: =IF(Z38<0,"",Z38) | AB38: =IF(AA37="",IF(AA38="","",B38-AA38/Y38),"")
B39: 4 | C39: =C38 -> 0.006 | D39: =D38+C39 -> 0.018 | E39: =$E$36*(1-D39) -> 645174 | F39: =F38*(1+$D$14) -> 7.5133526 | G39: =E39*F39 -> 4847419.8 | H39: =G39*(1-'Inputs and Output'!$D$32) -> 3605239.4 | I39: =$I$36*((1+'Inputs and Output'!$D$13)^(Workings!B39-1)) -> 376228.13 | J39: =M7*$D$9 -> 30681.538 | L39: =U8 -> 1327247.6 | M39: =SUM(I39:L39) -> 1734157.3 | N39: =M39*'Inputs and Output'!$D$32 -> 444388.21 | O39: =J7 -> 486538.46 | Q39: =M39-N39-O39 -> 803230.61 | R39: =H39-Q39-V8 -> 1403016.8 | S39: =S38+R39 -> 3293912.1 | T39: =IF(S39<0,"",S39) -> 3293912.1 | U39: =IF(T38="",IF(T39="","",B39-T39/R39),"") | V39: =SUM(I39:K39) -> 406909.66 | W39: =V39*'Inputs and Output'!$D$32 -> 104273.04 | X39: =V39-W39-O39-P39 -> -183901.84 | Y39: =H39-X39 -> 3789141.2 | Z39: =Z38+Y39 -> -4097115.9 | AA39: =IF(Z39<0,"",Z39) | AB39: =IF(AA38="",IF(AA39="","",B39-AA39/Y39),"")
B40: 5 | C40: =C39 -> 0.006 | D40: =D39+C40 -> 0.024 | E40: =$E$36*(1-D40) -> 641232 | F40: =F39*(1+$D$14) -> 7.6636197 | G40: =E40*F40 -> 4914158.2 | H40: =G40*(1-'Inputs and Output'!$D$32) -> 3654875.7 | I40: =$I$36*((1+'Inputs and Output'!$D$13)^(Workings!B40-1)) -> 395039.53 | J40: =M8*$D$9 -> 27217.592 | L40: =U9 -> 1187348.4 | M40: =SUM(I40:L40) -> 1609605.5 | N40: =M40*'Inputs and Output'!$D$32 -> 412471.08 | O40: =J8 -> 291923.08 | Q40: =M40-N40-O40 -> 905211.39 | R40: =H40-Q40-V9 -> 1210773.1 | S40: =S39+R40 -> 4504685.2 | T40: =IF(S40<0,"",S40) -> 4504685.2 | U40: =IF(T39="",IF(T40="","",B40-T40/R40),"") | V40: =SUM(I40:K40) -> 422257.12 | W40: =V40*'Inputs and Output'!$D$32 -> 108205.92 | X40: =V40-W40-O40-P40 -> 22128.125 | Y40: =H40-X40 -> 3632747.5 | Z40: =Z39+Y40 -> -464368.35 | AA40: =IF(Z40<0,"",Z40) | AB40: =IF(AA39="",IF(AA40="","",B40-AA40/Y40),"")
B41: 6 | C41: =C40 -> 0.006 | D41: =D40+C41 -> 0.03 | E41: =$E$36*(1-D41) -> 637290 | F41: =F40*(1+$D$14) -> 7.8168921 | G41: =E41*F41 -> 4981627.2 | H41: =G41*(1-'Inputs and Output'!$D$32) -> 3705055.3 | I41: =$I$36*((1+'Inputs and Output'!$D$13)^(Workings!B41-1)) -> 414791.51 | J41: =M9*$D$9 -> 24144.726 | K41: =$D$4*$D$10 -> 239308.03 | L41: =U10 -> 1033459.3 | M41: =SUM(I41:L41) -> 1711703.6 | N41: =M41*'Inputs and Output'!$D$32 -> 438634.31 | O41: =J9 -> 175153.85 | Q41: =M41-N41-O41 -> 1097915.4 | R41: =H41-Q41-V10 -> 914359.61 | S41: =S40+R41 -> 5419044.8 | T41: =IF(S41<0,"",S41) -> 5419044.8 | U41: =IF(T40="",IF(T41="","",B41-T41/R41),"") | V41: =SUM(I41:K41) -> 678244.26 | W41: =V41*'Inputs and Output'!$D$32 -> 173804.16 | X41: =V41-W41-O41-P41 -> 329286.26 | Y41: =H41-X41 -> 3375769.1 | Z41: =Z40+Y41 -> 2911400.7 | AA41: =IF(Z41<0,"",Z41) -> 2911400.7 | AB41: =IF(AA40="",IF(AA41="","",B41-AA41/Y41),"") -> 5.1375593
B42: 7 | C42: =C41 -> 0.006 | D42: =D41+C42 -> 0.036 | E42: =$E$36*(1-D42) -> 633348 | F42: =F41*(1+$D$14) -> 7.9732299 | G42: =E42*F42 -> 5049829.2 | H42: =G42*(1-'Inputs and Output'!$D$32) -> 3755780.2 | I42: =$I$36*((1+'Inputs and Output'!$D$13)^(Workings!B42-1)) -> 435531.08 | J42: =M10*$D$9 -> 21418.787 | K42: =$D$4*$D$10 -> 239308.03 | L42: =U11 -> 864181.27 | M42: =SUM(I42:L42) -> 1560439.2 | N42: =M42*'Inputs and Output'!$D$32 -> 399871.9 | O42: =J10 -> 105092.31 | Q42: =M42-N42-O42 -> 1055475 | R42: =H42-Q42-V11 -> 838246.9 | S42: =S41+R42 -> 6257291.7 | T42: =IF(S42<0,"",S42) -> 6257291.7 | U42: =IF(T41="",IF(T42="","",B42-T42/R42),"") | V42: =SUM(I42:K42) -> 696257.9 | W42: =V42*'Inputs and Output'!$D$32 -> 178420.26 | X42: =V42-W42-O42-P42 -> 412745.33 | Y42: =H42-X42 -> 3343034.9 | Z42: =Z41+Y42 -> 6254435.6 | AA42: =IF(Z42<0,"",Z42) -> 6254435.6 | AB42: =IF(AA41="",IF(AA42="","",B42-AA42/Y42),"")
B43: 8 | C43: =C42 -> 0.006 | D43: =D42+C43 -> 0.042 | E43: =$E$36*(1-D43) -> 629406 | F43: =F42*(1+$D$14) -> 8.1326945 | G43: =E43*F43 -> 5118766.7 | H43: =G43*(1-'Inputs and Output'!$D$32) -> 3807052 | I43: =$I$36*((1+'Inputs and Output'!$D$13)^(Workings!B43-1)) -> 457307.64 | J43: =M11*$D$9 -> 19000.606 | K43: =$D$4*$D$10 -> 239308.03 | L43: =U12 -> 677975.44 | M43: =SUM(I43:L43) -> 1393591.7 | N43: =M43*'Inputs and Output'!$D$32 -> 357116.24 | O43: =J11 -> 63055.385 | Q43: =M43-N43-O43 -> 973420.09 | R43: =H43-Q43-V12 -> 785367.8 | S43: =S42+R43 -> 7042659.5 | T43: =IF(S43<0,"",S43) -> 7042659.5 | U43: =IF(T42="",IF(T43="","",B43-T43/R43),"") | V43: =SUM(I43:K43) -> 715616.27 | W43: =V43*'Inputs and Output'!$D$32 -> 183380.96 | X43: =V43-W43-O43-P43 -> 469179.92 | Y43: =H43-X43 -> 3337872.1 | Z43: =Z42+Y43 -> 9592307.7 | AA43: =IF(Z43<0,"",Z43) -> 9592307.7 | AB43: =IF(AA42="",IF(AA43="","",B43-AA43/Y43),"")
B44: 9 | C44: =C43 -> 0.006 | D44: =D43+C44 -> 0.048 | E44: =$E$36*(1-D44) -> 625464 | F44: =F43*(1+$D$14) -> 8.2953484 | G44: =E44*F44 -> 5188441.8 | H44: =G44*(1-'Inputs and Output'!$D$32) -> 3858872.5 | I44: =$I$36*((1+'Inputs and Output'!$D$13)^(Workings!B44-1)) -> 480173.02 | J44: =M12*$D$9 -> 16855.437 | K44: =$D$4*$D$10 -> 239308.03 | L44: =U13 -> 473149.02 | M44: =SUM(I44:L44) -> 1209485.5 | N44: =M44*'Inputs and Output'!$D$32 -> 309937.92 | O44: =J12 -> 37833.231 | Q44: =M44-N44-O44 -> 861714.36 | R44: =H44-Q44-V13 -> 744067.53 | S44: =S43+R44 -> 7786727.1 | T44: =IF(S44<0,"",S44) -> 7786727.1 | U44: =IF(T43="",IF(T44="","",B44-T44/R44),"") | V44: =SUM(I44:K44) -> 736336.49 | W44: =V44*'Inputs and Output'!$D$32 -> 188690.64 | X44: =V44-W44-O44-P44 -> 509812.61 | Y44: =H44-X44 -> 3349059.8 | Z44: =Z43+Y44 -> 12941368 | AA44: =IF(Z44<0,"",Z44) -> 12941368 | AB44: =IF(AA43="",IF(AA44="","",B44-AA44/Y44),"")
B45: 10 | C45: =C44 -> 0.006 | D45: =D44+C45 -> 0.054 | E45: =$E$36*(1-D45) -> 621522 | F45: =F44*(1+$D$14) -> 8.4612554 | G45: =E45*F45 -> 5258856.4 | H45: =G45*(1-'Inputs and Output'!$D$32) -> 3911242.9 | I45: =$I$36*((1+'Inputs and Output'!$D$13)^(Workings!B45-1)) -> 504181.67 | J45: =M13*$D$9 -> 14952.458 | K45: =$D$4*$D$10 -> 239308.03 | L45: =U14 -> 247839.96 | M45: =SUM(I45:L45) -> 1006282.1 | N45: =M45*'Inputs and Output'!$D$32 -> 257865.83 | O45: =J13 -> 22699.938 | Q45: =M45-N45-O45 -> 725716.35 | R45: =H45-Q45-V14 -> 707126.89 | S45: =S44+R45 -> 8493854 | T45: =IF(S45<0,"",S45) -> 8493854 | U45: =IF(T44="",IF(T45="","",B45-T45/R45),"") | V45: =SUM(I45:K45) -> 758442.16 | W45: =V45*'Inputs and Output'!$D$32 -> 194355.35 | X45: =V45-W45-O45-P45 -> 541386.87 | Y45: =H45-X45 -> 3369856 | Z45: =Z44+Y45 -> 16311224 | AA45: =IF(Z45<0,"",Z45) -> 16311224 | AB45: =IF(AA44="",IF(AA45="","",B45-AA45/Y45),"")
B46: 11 | C46: =C45 -> 0.006 | D46: =D45+C46 -> 0.06 | E46: =$E$36*(1-D46) -> 617580 | F46: =F45*(1+$D$14) -> 8.6304805 | G46: =E46*F46 -> 5330012.1 | H46: =G46*(1-'Inputs and Output'!$D$32) -> 3964164.6 | I46: =$I$36*((1+'Inputs and Output'!$D$13)^(Workings!B46-1)) -> 529390.75 | J46: =M14*$D$9 -> 13264.326 | K46: =$D$4*$D$10 -> 239308.03 | L46: =U15 -> -1.44355e-09 | M46: =SUM(I46:L46) -> 781963.11 | N46: =M46*'Inputs and Output'!$D$32 -> 200382.74 | O46: =J14 -> 13619.963 | Q46: =M46-N46-O46 -> 567960.41 | R46: =H46-Q46-V15 -> 3396204.1 | S46: =S45+R46 -> 11890058 | T46: =IF(S46<0,"",S46) -> 11890058 | U46: =IF(T45="",IF(T46="","",B46-T46/R46),"") | V46: =SUM(I46:K46) -> 781963.11 | W46: =V46*'Inputs and Output'!$D$32 -> 200382.74 | X46: =V46-W46-O46-P46 -> 567960.41 | Y46: =H46-X46 -> 3396204.1 | Z46: =Z45+Y46 -> 19707428 | AA46: =IF(Z46<0,"",Z46) -> 19707428 | AB46: =IF(AA45="",IF(AA46="","",B46-AA46/Y46),"")
B47: 12 | C47: =C46 -> 0.006 | D47: =D46+C47 -> 0.066 | E47: =$E$36*(1-D47) -> 613638 | F47: =F46*(1+$D$14) -> 8.8030901 | G47: =E47*F47 -> 5401910.6 | H47: =G47*(1-'Inputs and Output'!$D$32) -> 4017638.6 | I47: =$I$36*((1+'Inputs and Output'!$D$13)^(Workings!B47-1)) -> 555860.29 | J47: =M15*$D$9 -> 11766.783 | K47: =$D$4*$D$10 -> 239308.03 | L47: =U16 -> -1.587905e-09 | M47: =SUM(I47:L47) -> 806935.11 | N47: =M47*'Inputs and Output'!$D$32 -> 206781.96 | O47: =J15 -> 8171.9779 | Q47: =M47-N47-O47 -> 591981.17 | R47: =H47-Q47-V16 -> 3425657.4 | S47: =S46+R47 -> 15315716 | T47: =IF(S47<0,"",S47) -> 15315716 | U47: =IF(T46="",IF(T47="","",B47-T47/R47),"") | V47: =SUM(I47:K47) -> 806935.11 | W47: =V47*'Inputs and Output'!$D$32 -> 206781.96 | X47: =V47-W47-O47-P47 -> 591981.17 | Y47: =H47-X47 -> 3425657.4 | Z47: =Z46+Y47 -> 23133085 | AA47: =IF(Z47<0,"",Z47) -> 23133085 | AB47: =IF(AA46="",IF(AA47="","",B47-AA47/Y47),"")
B48: 13 | C48: =C47 -> 0.006 | D48: =D47+C48 -> 0.072 | E48: =$E$36*(1-D48) -> 609696 | F48: =F47*(1+$D$14) -> 8.9791519 | G48: =E48*F48 -> 5474553 | H48: =G48*(1-'Inputs and Output'!$D$32) -> 4071665.9 | I48: =$I$36*((1+'Inputs and Output'!$D$13)^(Workings!B48-1)) -> 583653.31 | J48: =M16*$D$9 -> 10438.314 | K48: =$D$4*$D$10 -> 239308.03 | L48: =U17 -> -1.7466955e-09 | M48: =SUM(I48:L48) -> 833399.65 | N48: =M48*'Inputs and Output'!$D$32 -> 213563.66 | O48: =J16 -> 4903.1867 | Q48: =M48-N48-O48 -> 614932.8 | R48: =H48-Q48-V17 -> 3456733.1 | S48: =S47+R48 -> 18772449 | T48: =IF(S48<0,"",S48) -> 18772449 | U48: =IF(T47="",IF(T48="","",B48-T48/R48),"") | V48: =SUM(I48:K48) -> 833399.65 | W48: =V48*'Inputs and Output'!$D$32 -> 213563.66 | X48: =V48-W48-O48-P48 -> 614932.8 | Y48: =H48-X48 -> 3456733.1 | Z48: =Z47+Y48 -> 26589818 | AA48: =IF(Z48<0,"",Z48) -> 26589818 | AB48: =IF(AA47="",IF(AA48="","",B48-AA48/Y48),"")
B49: 14 | C49: =C48 -> 0.006 | D49: =D48+C49 -> 0.078 | E49: =$E$36*(1-D49) -> 605754 | F49: =F48*(1+$D$14) -> 9.1587349 | G49: =E49*F49 -> 5547940.3 | H49: =G49*(1-'Inputs and Output'!$D$32) -> 4126247.3 | I49: =$I$36*((1+'Inputs and Output'!$D$13)^(Workings!B49-1)) -> 612835.97 | J49: =M17*$D$9 -> 9259.828 | K49: =$D$4*$D$10 -> 239308.03 | L49: =U18 -> -1.921365e-09 | M49: =SUM(I49:L49) -> 861403.83 | N49: =M49*'Inputs and Output'!$D$32 -> 220739.9 | O49: =J17 -> 2941.912 | Q49: =M49-N49-O49 -> 637722.02 | R49: =H49-Q49-V18 -> 3488525.3 | S49: =S48+R49 -> 22260974 | T49: =IF(S49<0,"",S49) -> 22260974 | U49: =IF(T48="",IF(T49="","",B49-T49/R49),"") | V49: =SUM(I49:K49) -> 861403.83 | W49: =V49*'Inputs and Output'!$D$32 -> 220739.9 | X49: =V49-W49-O49-P49 -> 637722.02 | Y49: =H49-X49 -> 3488525.3 | Z49: =Z48+Y49 -> 30078344 | AA49: =IF(Z49<0,"",Z49) -> 30078344 | AB49: =IF(AA48="",IF(AA49="","",B49-AA49/Y49),"")
B50: 15 | C50: =C49 -> 0.006 | D50: =D49+C50 -> 0.084 | E50: =$E$36*(1-D50) -> 601812 | F50: =F49*(1+$D$14) -> 9.3419096 | G50: =E50*F50 -> 5622073.3 | H50: =G50*(1-'Inputs and Output'!$D$32) -> 4181383.3 | I50: =$I$36*((1+'Inputs and Output'!$D$13)^(Workings!B50-1)) -> 643477.77 | J50: =M18*$D$9 -> 8214.3934 | K50: =$D$4*$D$10 -> 239308.03 | L50: =U19 -> -2.1135015e-09 | M50: =SUM(I50:L50) -> 891000.19 | N50: =M50*'Inputs and Output'!$D$32 -> 228324.15 | O50: =J18 -> 1765.1472 | Q50: =M50-N50-O50 -> 660910.9 | R50: =H50-Q50-V19 -> 3520472.4 | S50: =S49+R50 -> 25781446 | T50: =IF(S50<0,"",S50) -> 25781446 | U50: =IF(T49="",IF(T50="","",B50-T50/R50),"") | V50: =SUM(I50:K50) -> 891000.19 | W50: =V50*'Inputs and Output'!$D$32 -> 228324.15 | X50: =V50-W50-O50-P50 -> 660910.9 | Y50: =H50-X50 -> 3520472.4 | Z50: =Z49+Y50 -> 33598816 | AA50: =IF(Z50<0,"",Z50) -> 33598816 | AB50: =IF(AA49="",IF(AA50="","",B50-AA50/Y50),"")
B51: 16 | C51: =C50 -> 0.006 | D51: =D50+C51 -> 0.09 | E51: =$E$36*(1-D51) -> 597870 | F51: =F50*(1+$D$14) -> 9.5287478 | G51: =E51*F51 -> 5696952.5 | H51: =G51*(1-'Inputs and Output'!$D$32) -> 4237074.2 | I51: =$I$36*((1+'Inputs and Output'!$D$13)^(Workings!B51-1)) -> 675651.66 | J51: =M19*$D$9 -> 7286.9884 | K51: =$D$4*$D$10 -> 239308.03 | L51: =U20 -> -2.3248517e-09 | M51: =SUM(I51:L51) -> 922246.68 | N51: =M51*'Inputs and Output'!$D$32 -> 236331.24 | O51: =J19 -> 1059.0883 | Q51: =M51-N51-O51 -> 684856.34 | R51: =H51-Q51-V20 -> 3552217.9 | S51: =S50+R51 -> 29333664 | T51: =IF(S51<0,"",S51) -> 29333664 | U51: =IF(T50="",IF(T51="","",B51-T51/R51),"") | V51: =SUM(I51:K51) -> 922246.68 | W51: =V51*'Inputs and Output'!$D$32 -> 236331.24 | X51: =V51-W51-O51-P51 -> 684856.34 | Y51: =H51-X51 -> 3552217.9 | Z51: =Z50+Y51 -> 37151034 | AA51: =IF(Z51<0,"",Z51) -> 37151034 | AB51: =IF(AA50="",IF(AA51="","",B51-AA51/Y51),"")
B52: 17 | C52: =C51 -> 0.006 | D52: =D51+C52 -> 0.096 | E52: =$E$36*(1-D52) -> 593928 | F52: =F51*(1+$D$14) -> 9.7193228 | G52: =E52*F52 -> 5772577.9 | H52: =G52*(1-'Inputs and Output'!$D$32) -> 4293320.2 | I52: =$I$36*((1+'Inputs and Output'!$D$13)^(Workings!B52-1)) -> 709434.24 | J52: =M20*$D$9 -> 6464.2874 | K52: =$D$4*$D$10 -> 239308.03 | L52: =U21 -> -2.5573369e-09 | M52: =SUM(I52:L52) -> 955206.56 | N52: =M52*'Inputs and Output'!$D$32 -> 244777.41 | O52: =J20 -> 635.453 | Q52: =M52-N52-O52 -> 709793.69 | R52: =H52-Q52-V21 -> 3583526.5 | S52: =S51+R52 -> 32917191 | T52: =IF(S52<0,"",S52) -> 32917191 | U52: =IF(T51="",IF(T52="","",B52-T52/R52),"") | V52: =SUM(I52:K52) -> 955206.56 | W52: =V52*'Inputs and Output'!$D$32 -> 244777.41 | X52: =V52-W52-O52-P52 -> 709793.69 | Y52: =H52-X52 -> 3583526.5 | Z52: =Z51+Y52 -> 40734560 | AA52: =IF(Z52<0,"",Z52) -> 40734560 | AB52: =IF(AA51="",IF(AA52="","",B52-AA52/Y52),"")
... B60: 25 | C60: =C59 -> 0.006 | D60: =D59+C60 -> 0.144 | E60: =$E$36*(1-D60) -> 562392 | F60: =F59*(1+$D$14) -> 11.387736 | G60: =E60*F60 -> 6404371.5 | H60: =G60*(1-'Inputs and Output'!$D$32) -> 4763212.9 | I60: =$I$36*((1+'Inputs and Output'!$D$13)^(Workings!B60-1)) -> 1048157.5 | J60: =M28*$D$9 -> 2479.1414 | K60: =$D$4*$D$10 -> 239308.03 | L60: =U29 -> -5.4818787e-09 | M60: =SUM(I60:L60) -> 1289944.7 | N60: =M60*'Inputs and Output'!$D$32 -> 330556.06 | O60: =J28 -> 10.67317 | Q60: =M60-N60-O60 -> 959377.92 | R60: =H60-Q60-V29 -> 3803834.9 | S60: =S59+R60 -> 62618472 | T60: =IF(S60<0,"",S60) -> 62618472 | U60: =IF(T59="",IF(T60="","",B60-T60/R60),"") | V60: =SUM(I60:K60) -> 1289944.7 | W60: =V60*'Inputs and Output'!$D$32 -> 330556.06 | X60: =V60-W60-O60-P60 -> 959377.92 | Y60: =H60-X60 -> 3803834.9 | Z60: =Z59+Y60 -> 70435842 | AA60: =IF(Z60<0,"",Z60) -> 70435842 | AB60: =IF(AA59="",IF(AA60="","",B60-AA60/Y60),"")
B61: Total | E61: =SUM(E36:E60) -> 15242400 | G61: =SUM(G36:G60) -> 1.3734674e+08 | R61: =SUM(R36:R60) -> 69797713 | Y61: =SUM(Y36:Y60) -> 94366645
B62: Average Generation | E62: =AVERAGE(E36:E60) -> 609696
