Workbook
Name ProjectOptions: 'Input''s from BD(Sales)'!$B$167:$D$200
Name Railing: 'Bidcell BOM (LTS)'!#REF!
Name TN_NOC: 'Bidcell BOM (LTS)'!$A$597:$B$612

Sheet Input's from BD(Sales)
C1: DOC. No: 4PEL/DES-SSR/109 #I01, R05.
C2: Issue Date: 23/02/2026. | P2: Client Scope | Q2: Client Scope | R2: Ground | S2: Cable Tray | T2: Required | U2: Domestic | V2: Client Scope | W2: Client Scope
C3: Control Copy No. 02. | P3: Trenching | Q3: Not Required | R3: Roof | S3: Client Scope | T3: Not Required | U3: Imported | V3: Already Exist | W3: 4PEL Scope
A4: Site Surrvey Request Form | P4: Existing Trench | Q4: 4PEL Scope | S4: Trenching | V4: 4PEL Scope | W4: Not Required
A5: Site Visit Request Form (To be filled by Sales Team) | C5: Remarks | D5: Remarks | P5: Cable Tray | V5: Not Required
A6: Name of BD Person | B6: Carl Aaron
A7: Mobile No. | B7: 9551062519
A8: Mail id | B8: carl.aaron@fourthpartner.co
A9: Site visit Request date
A10: State | B10: Maharashtra | C10: =IF(B10<>"","","Please fill the State to access further details")
A11: Client name | B11: West Pioneer Properties
A12: Mode of site survey | B12: Physical
A13: Location & address | B13: Metro Junction Mall, Kalyan - Shilphata Rd, Kalyan East, Kalyan, Maharashtra 421306
A14: Lat & Long details | B14: 19°13'45.98"N 73°07'23.94"E
A15: This Project having RFQ/RFP | B15: Yes | C15: =IF(B15<>"","","Further details to RFP/RFQ can be accessed only if RFP/RFQ details are filled")
A16: Plant Type (Capex/Opex) | B16: Capex
A17: Expected Cap in Kwp | B17: 400
A18: No. of locations | B18: 1
A19: Type of installation | B19: RCC
A20: Module wattage (Wp) | B20: 595 / 590 / 585
A21: Module Origin | B21: ALMM Approved
A22: Prefered Inverter make | B22: Solis / Sungrow / Equivalent
A23: DC/AC Ratio
A24: AMC & Module Cleaning | C24: =B16 & " Model" -> Capex Model
A25: No. of Years of AMC & Module cleaning | C25: =C24 -> Capex Model
A26: PBG Amount % | C26: =C25 -> Capex Model
A27: No. of Yrs BG is required to be maintained | C27: =C26 -> Capex Model
A28: Marketing Commission % | B28: 0 | C28: ='Bidcell BOM (LTS)'!F387 -> 0 | D28: /Wp
A29: EPC Margin % | B29: 0.1 | C29: ='Bidcell BOM (LTS)'!F386 -> 3.5242262 | D29: /Wp
A31: Scope of Work | C31: Remarks
A32: For Rooftop
A33: Access to the Roof | B33: Client Scope
A34: Gutter for cleaning/ Rain Water Harvesting | B34: Not Required
A35: Scope of mesh over the skylight | B35: Not Required
A36: Scope of Turbo vent | B36: Not Applicable
A37: Hand Railling | B37: 4PEL Scope
A38: Walkways materials | B38: FRP
A39: DC Cable Tray materials | B39: FRP
A40: AC Cable Tray materials (INV And ACCB panel) | B40: GI
A41: AC Cable Tray materials (ACCB And CLT panel) | B41: GI
A42: Roof puncturing permission from client for :
A43: Modules (MMS)
A44: Walkway Dimension (w)
A45: Lifeline location
A46: Anchoring permission for RCC
A47: PV Syst
A48: For Ground mounted/ Parking
A49: Soil Test (Ground /Parking)
A50: Land Leveling (Ground /Parking)
A51: Peripheral Plant Fencing
A52: Type of Peripheral Plant Fencing
A53: Peripheral Lighting
... A60: Common Factors for Rooftop & Ground mounted
A61: Spare Feeder (Termination Feeder) | B61: Client Scope
A62: CEIG Liaisoning / Minister cost | B62: 4PEL Scope
A63: Netmeter Liaisoning & NOC | B63: 4PEL Scope
A64: Type of Netmetering | B64: Net Metering/Net Billing
A65: Netmeter material & installation for Discom | B65: 4PEL Scope
A66: Metering Cubicle (CT&PT) with Installtion | B66: Client Scope
A67: Renewable Purchase Obligation (RPO) | B67: Client Scope
A68: Generation Panel before client termination | B68: 4PEL Scope
A69: Control Room | B69: Client Scope
A70: Spare Material Requirement | B70: Not Applicable
A71: Inverter Ext. warranty Requirement if any? | B71: No
A72: Plant Extra Warranty for BOS | B72: No
A73: No. of Year's Plant Extra Warranty for BOS | B73: 0
A75: Site Contact Person Details
A76: Contact Person at site | B76: Mr. Anil Kumar
A77: Mob No. | B77: 9324592021
A78: Land line no.
A79: Mail id
A80: Designation
A81: Power bills | B81: Collected
A82: CEIG report (Approval Status)
A83: Plant cad files | B83: Available
A84: Plant SLD cad file | B84: Available
A85: Mobile Access | B85: Yes, Client allows mobile usage inside their premises
A86: Roof Access | B86: Yes, Roof access available
A87: Preferring date (to be conf from survey coordinator)
A90: Comments(if any):
A146: Client Scope
A147: 4PEL Scope
A148: Not Required
A149: Already Exist
A150: Not Applicable
A151: Monkey
A152: Staircase
A153: Movable
A154: Not Applicable
A155: Required
A156: Not Required
A157: Not Applicable | B157: Pre-Fab Wall | C157: 3600
A158: Avenue Supermarts Limited | B158: Chain Link Mesh | C158: 1600
A159: ITC | B159: Not Applicable | C159: 0
A160: Net Metering/Net Billing
A161: Behind The Meter
B166: Formulas are there -------> | C166: selection by project type | E166: Formulas are there down
B167: Project type | C167: Category | D167: Options
B168: =C$230 -> Capex | C168: =A$38 -> Walkways materials | D168: GI | E168: =A38 -> Walkways materials | F168: {=_xlfn._xlws.FILTER(Table1[[#All],[Options]],(Table1[[#All],[Project type]]=B$16)*(Table1[[#All],[Category]]=A$38))} -> GI
B169: =C$230 -> Capex | C169: =A$38 -> Walkways materials | D169: FRP | F169: FRP
...

Sheet Consumption analysis (BD)
B1: Fourth Partner Energy Pvt. Ltd | E1: DOC. No: 4PEL/DES-CA/555 #I01, R00.
E2: Issue Date: 11/12/2023.
E3: Control Copy No. 02.
B4: Consumption Analysis
A5: A) | B5: E Bill Parameters
B7: 0 | I7: =277 -> 277 | K7: 277
B8: Months | C8: Off Peak hrs (10 PM-05:30 AM) | D8: Normal hrs 05:30 AM-05:30 PM) | E8: Peak Hrs (TOU) (05:30 PM-10PM) | F8: Total Monthly consumption from DISCOM | G8: Generation at 277kWp | I8: Energy Per kWp (kWh) | J8: Capacity (kWP) as per day time consumption | L8: Difference of Consumption vs Generation (kWH) | M8: Banking Charges | O8: Note - 1. TOD zone will differ as per state regulatories norms, State DISCOM's 2.Yield will differ as per location & type of installation, module type. 3. Actual proposed size is based on shadow free area on roof/ground , state regulatories norms
B9: May'24 | G9: 30.74 | H9: =G9*93.18% -> 28.643532 | I9: =(H9/$I$7)*1000 -> 103.40625 | J9: =C9/I9 -> 0 | K9: =I9*$K$7 -> 28643.532 | L9: =C9-K9 -> -28643.532 | M9: =IF(L9<0, L9*1.5, 0) -> -42965.298
B10: April'24 | G10: 34.39 | H10: =G10*93.18% -> 32.044602 | I10: =(H10/$I$7)*1000 -> 115.68448 | J10: =C10/I10 -> 0 | K10: =I10*$K$7 -> 32044.602 | L10: =C10-K10 -> -32044.602 | M10: =IF(L10<0, L10*1.5, 0) -> -48066.903
G11: 29.89 | H11: =G11*93.18% -> 27.851502 | I11: =(H11/$I$7)*1000 -> 100.54694 | J11: =C11/I11 -> 0 | K11: =I11*$K$7 -> 27851.502 | L11: =C11-K11 -> -27851.502 | M11: =IF(L11<0, L11*1.5, 0) -> -41777.253
B12: Total | F12: =F9+F10 -> 0 | J12: =MIN(J11:J11) -> 0
B13: Considering Day time consumption only | E13: Considering Overall consumption | J13: =MIN(J12,J9:J10) -> 0
B14: Monthly Min Consumption | C14: =AVERAGE(D9:D10) -> #DIV/0! | E14: Monthly Avg Consumption | F14: =AVERAGE(F9:F11) -> #DIV/0! | H14: Minimum Capacity (kWP) considering 12 months
B15: 70% of Avergae Consumption to avoid Banking charges | C15: =C14*0.7 -> #DIV/0! | E15: Min offtake Guarantee to Discom (If any) | F15: 0 | H15: *March , April'2020 not considered due to COVID
B16: Net consumption available for offset by Solar | C16: =C15 -> #DIV/0! | E16: Net consumption available for offset by Solar | F16: =F14-F15 -> #DIV/0!
B17: Daily Avg Consumption | C17: =C16/30 -> #DIV/0! | E17: Daily Avg Consumption | F17: =F16/30 -> #DIV/0!
B18: Yield | E18: Yield
B19: SPP Size based on consumption (kWp) | C19: =C17/C18 -> #DIV/0! | E19: SPP Size based on consumption (kWp) | F19: =F17/F18 -> #DIV/0!
B21: Actual Proposed SPP size (kWp) | F21: 0
B22: % day time consumption replaced | D22: =D21*30*C18/C14 -> #DIV/0!
B23: % overall consumption replaced | D23: =D21*30*C18/F14 -> #DIV/0!
A25: B) | B25: Operational Parameters
B27: What is manufactured/Processed? Any heat / exhaust issues?
B28: Describe the load pattern? Constant/Seasonal/Order based
B29: Check the feasibility of obtaining 15 min load profile from client?
B30: No. of days per week plant is operational
B31: No. of shifts in which plant is operational
B32: Age of facility
B33: If ToD data not available, what is % day time consumption as per client input/experience
A36: C) | B36: Capacity assesment
B38: Parameters | C38: Maximum Installed Capacity (kWp) | D38: Remarks
B39: Based on G-Map | C39: 0
B40: Based on Consumption analysis
B41: Based on State regulatory norms (Net Metering or Min offtake commitment to Discom) | C41: 0
B43: Proposed Capacity | C43: 0
A46: D) | B46: Bill Analysis
B48: May'24 | F48: Billing Month
B49: Sanctioned Load/CD- 4950KVA | F49: March
B50: Particulars | C50: Units | D50: Rate | E50: Amount
B51: Total Charges | D51: =E51/C51 -> #DIV/0!
B52: Less : Demand Charges/Fixed Charges | D52: =E52/C52 -> #DIV/0!
B53: Grid Variable cost/ Landed cost of power | C53: =C51 -> 0 | D53: =E53/C53 -> #DIV/0! | E53: =E51-E52 -> 0
B55: Breakup of LCOP
B56: Energy Cost | C56: =C51 -> 0 | D56: =E56/C56 -> #DIV/0!
B57: Meter Rent | C57: =C56 -> 0 | D57: =E57/C57 -> #DIV/0!
B58: ED | C58: =C53 -> 0 | D58: =E58/C58 -> #DIV/0!
B59: Delayed Payment Surcharge | C59: =C58 -> 0 | D59: =E59/C59 -> #DIV/0!
B60: IDF | C60: =C59 -> 0 | D60: =E60/C60 -> #DIV/0!
B61: TCS Rate | C61: =C56 -> 0 | D61: =E61/C61 -> #DIV/0!
B62: PF Incentive | C62: =C57 -> 0 | D62: =E62/C62 -> #DIV/0!
B63: Customer Service Charge | C63: =C58 -> 0 | D63: =E63/C63 -> #DIV/0!
B64: Incentive on TODs | C64: =C59 -> 0 | D64: =E64/C64 -> #DIV/0!
B65: for check 1 | E65: =SUM(E56:E64) -> 0
E66: =E53-E65 -> 0
A68: E) | B68: Savings
C70: Annual Energy Consumption (kWh) | D70: Est Variable Grid Tariff (₹/kWh) | E70: Proposed Rooftop Capacity (kWp) | F70: Est Annual Solar Generation (kWh) | O70: % savngs in Variable Grid Tariff | P70: Annual Savings Per Site (₹) | Q70: Overall Savings %
B71: Onsite | C71: =F12 -> 0 | D71: =D53 -> #DIV/0! | E71: =C43 -> 0 | F71: =3.96*365*E71 -> 0 | O71: =((D71-#REF!)/D71) -> #DIV/0! | P71: =F71*(D71-#REF!) -> #DIV/0! | Q71: =((D71-#REF!)/D71)*#REF! -> #DIV/0!
B72: Offsite

Sheet ESG (Design)
B1: INITIAL SITE SURVEY – ESG CHECKLIST | F1: DOC. No: 4PEL/DES-ISS/554 #I01, R00.
F2: Issue Date: 11/12/2023.
F3: Control Copy No.: 02.
A4: Name of Project Site | B4: Metro Junction mall
A5: Location/Address | B5: Metro Junction mall, Kalyan East | D5: State | F5: Maharashtra
A6: Country | B6: India
A7: Name of Surveyor | B7: Sagar Chavan | D7: Date | F7: 46153
A8: Department of Surveyor | B8: Design
A9: Name of Verifier
A10: Department of Verifier
A12: Aspects to check | C12: Yes | D12: No | E12: NA | F12: Remarks
A13: Key safety checks (evidence shall be provided against each significant check point with appropriate remark)
A14: Is suitable instrument available for taking actual measurements? | C14: yes
A15: Is any other technology other than manual measurement being used? (Ex. Drone etc.) | D15: No
A16: Is proper roof access available for roof? | C16: Yes
A17: If yes, what type of access is available, Monkey ladder, Step ladder or other? (Provide details in remark)
A18: If monkey ladder height is more than 10 meters, then is/are the rest platforms provided? | E18: NA
A19: (After every 10 meters there shall be minimum 10 meters gap between two platforms)
A20: Is ladder extended 1 meter above the roof? | E20: NA
A21: Is/are skylight(s) available on the roof? | E21: NA
A22: (If yes, please mention quantity and dimensions of the skylight)
A23: Is/are existing lifeline(s) available? | E23: NA
A24: If yes, please provide details. (Attach photographs)
A25: If 2 or more roofs are interconnected, is safe access available for roof-to-roof access? | E25: NA
A26: Please provide the access details.
A27: Is/are Turbo wind ventilator(s) available on roof? | E27: NA
A28: (If yes, please provide total numbers)
A29: Is alternative access available for the roof? | C29: Yes
A30: Has client provided Wire mesh below/above skylights for fall protection? | E30: NA
A31: If yes, does all the skylights on the roof are being covered?
A32: Is there any chemical / Hazardous waste emission on top of the roof? | D32: No
A33: Is there any Electric cables/ Pipes/Unprojected pipes routed on the roof? | C33: Yes
A34: Is lightning arrester available? If yes, does it cover all the roof area? | C34: Yes | F34: under exectuion, may not cover entire roof
A36: Are guard rails provided on the roof? | C36: Yes
A37: Are any measures of water harvesting provided on the roof? | C37: Yes
A38: Does client/off-taker has existing waste management policy?
A39: Is the client ready to provide material storage area during the development phase of plant? | C39: Yes
A40: Is any scrap yard available in client’s premises?
A41: Is the structural stability of the roof rust & prominent?
A42: Please mention: If any other Unsafe conditions observed on site | F42: out door ahu unit, piping & cable crossing etc

Sheet Input's from Site Visit
A1: Fourth Partner Energy Pvt. Ltd | F1: DOC. No: 4PEL/DES-ISS/110 #I01, R02.
F2: Issue Date: 11/12/2023.
F3: Control Copy No. 02.
A4: Inputs - Site Survey Form
A5: DETAILED PROJECT SITE SURVEY REPORT
A6: Client name | B6: ='Site Vist fomat (Design)'!B6 -> Metro Junction mall | E6: Power bills | F6: ='Input''s from BD(Sales)'!B81 -> Collected
A7: Client address | B7: ='Input''s from BD(Sales)'!B13 -> Metro Junction Mall, Kalyan - Shilphata Rd, Kalyan East, Kalyan, Maharashtra 421306 | E7: Contract demand * | F7: ='Site Vist fomat (Design)'!D18 -> 449 KVA
A8: Contact person name | B8: ='Site Vist fomat (Design)'!B7 -> 0 | E8: Incommer trans. rating* | F8: ='Site Vist fomat (Design)'!C19 -> Rating- kVA
A9: GPS Cordinates | B9: ='Site Vist fomat (Design)'!B9 -> 19.229564° N | E9: Netmetring voltage level | F9: ='Site Vist fomat (Design)'!B16 -> 0.45 kV | G9: Voltage level in kV | H9: =F9 -> 0.45 kV
A10: GPS Cordinates | B10: ='Site Vist fomat (Design)'!C9 -> 73.123271° E | E10: No. of Transformer | F10: ='Site Vist fomat (Design)'!B19 -> Qty - _01 Nos | G10: Voltage ratio | H10: ='Site Vist fomat (Design)'!D19 -> Voltage Ratio - ___/____
A11: Mob. No. | B11: ='Site Vist fomat (Design)'!E7 -> 0 | E11: Metering cubical (Class) | F11: ='Site Vist fomat (Design)'!B25 -> Class _____________
A12: Mail id | B12: ='Site Vist fomat (Design)'!G7 -> 0 | E12: ceig report | F12: ='Input''s from BD(Sales)'!B82 -> 0
A13: Proposed Kwp | B13: ='Site Vist fomat (Design)'!B15 -> kWp MwH | E13: Plant cad files | F13: ='Input''s from BD(Sales)'!B83 -> Available | J13: Locked Cell
A14: Project type | B14: ='Input''s from BD(Sales)'!B16 -> Capex | E14: plant SLD cad file | F14: ='Input''s from BD(Sales)'!B84 -> Available | J14: Editable cell
A15: Power Consumptions (Min.) | C15: Max. | E15: Hand sketch SLD | J15: *Mandatory
A16: APFC availability | C16: Solar termination | E16: No. of locations | F16: ='Input''s from BD(Sales)'!B18 -> 1 | G16: After Site Visit. | J16: Drop Down
A17: CT input for PFC | E17: Best Network operator | F17: <mention best oprator>
A18: ='Site Vist fomat (Design)'!C26 -> Metering CT& PT Details / Class | B18: ='Site Vist fomat (Design)'!D26 -> 0 | E18: Min & Max. Weather Temp.
A19: Plant Holiday/Power Holidays* | B19: ='Site Vist fomat (Design)'!B23 -> Days | E19: DG capacities * | F19: ='Site Vist fomat (Design)'!F23 -> Rating - _1010 kVA
A20: No. of service connection* | B20: ='Site Vist fomat (Design)'!B26 -> 2 | E20: No. of DGs * | F20: ='Site Vist fomat (Design)'!E23 -> Qty - __03 Nos
A21: PF maintaining | B21: ='Site Vist fomat (Design)'!G18 -> Power Factor: 0.89-0.995 | E21: Reverse Protections | F21: ='Site Vist fomat (Design)'!G24 -> (Yes/No)
A22: Any exsiting Plants | B22: Yes | C22: If yes | D22: ='Site Vist fomat (Design)'!B24 -> NO | E22: Metering class | F22: ='Site Vist fomat (Design)'!B25 -> Class _____________ | G22: rating, make ,model no. | H22: ='Site Vist fomat (Design)'!C25 -> Make: ___________________
A23: Plant details
B24: Plant 1 | C24: Plant 2 | D24: Plant 3 | E24: Plant 4 | F24: Plant 5 | G24: Plant 6 | H24: Plant 7 | I24: Plant 8 | J24: Plant 9 | K24: Plant 10 | L24: Plant 11 | M24: Plant 12 | N24: Plant 13 | O24: Plant 14 | P24: Plant 15
A25: Type of plant * | B25: Shed | C25: Shed | D25: Shed | E25: Shed | F25: Shed | G25: Shed | H25: Shed | I25: Shed | J25: Shed | K25: Shed | L25: Ground | M25: Ground | N25: Ground | O25: Ground | P25: Ground
A26: ='Site Vist fomat (Design)'!A27 -> Electrical Details
A27: ='Site Vist fomat (Design)'!A28 -> Name of the building (As per customer's nomenclature) | B27: ='Site Vist fomat (Design)'!B28 -> Main RCC B Block at LG | C27: ='Site Vist fomat (Design)'!C28 -> Main RCC D Block at LG | D27: ='Site Vist fomat (Design)'!D28 -> Parking | E27: ='Site Vist fomat (Design)'!E28 -> 0 | F27: ='Site Vist fomat (Design)'!F28 -> 0 | G27: ='Site Vist fomat (Design)'!G28 -> 0 | H27: ='Site Vist fomat (Design)'!H28 -> 0 | ... P27: ='Site Vist fomat (Design)'!P28 -> 0
A28: ='Site Vist fomat (Design)'!A31 -> Termination distance in mtrs | B28: ='Site Vist fomat (Design)'!B31 -> 170 | C28: ='Site Vist fomat (Design)'!C31 -> 220 | D28: ='Site Vist fomat (Design)'!D31 -> 200 | E28: ='Site Vist fomat (Design)'!E31 -> 0 | F28: ='Site Vist fomat (Design)'!F31 -> 0 | G28: ='Site Vist fomat (Design)'!G31 -> 0 | H28: ='Site Vist fomat (Design)'!H31 -> 0 | ... P28: ='Site Vist fomat (Design)'!P31 -> 0
A29: ='Site Vist fomat (Design)'!A32 -> Tentative location of inverter & LT Panel | B29: ='Site Vist fomat (Design)'!B32 -> at terrace level | C29: ='Site Vist fomat (Design)'!C32 -> at terrace level | D29: ='Site Vist fomat (Design)'!D32 -> At parking area | E29: ='Site Vist fomat (Design)'!E32 -> 0 | F29: ='Site Vist fomat (Design)'!F32 -> 0 | G29: ='Site Vist fomat (Design)'!G32 -> 0 | H29: ='Site Vist fomat (Design)'!H32 -> 0 | ... P29: ='Site Vist fomat (Design)'!P32 -> 0
A30: ='Site Vist fomat (Design)'!A33 -> Spare feeder avilability (mention as rating) | B30: ='Site Vist fomat (Design)'!B33 -> No | C30: ='Site Vist fomat (Design)'!C33 -> No | D30: ='Site Vist fomat (Design)'!D33 -> No | E30: ='Site Vist fomat (Design)'!E33 -> 0 | F30: ='Site Vist fomat (Design)'!F33 -> 0 | G30: ='Site Vist fomat (Design)'!G33 -> 0 | H30: ='Site Vist fomat (Design)'!H33 -> 0 | ... P30: ='Site Vist fomat (Design)'!P33 -> 0
A31: ='Site Vist fomat (Design)'!A34 -> Bus bar extensions required? Scope? | B31: ='Site Vist fomat (Design)'!B34 -> 0 | C31: ='Site Vist fomat (Design)'!C34 -> 0 | D31: ='Site Vist fomat (Design)'!D34 -> 0 | E31: ='Site Vist fomat (Design)'!E34 -> 0 | F31: ='Site Vist fomat (Design)'!F34 -> 0 | G31: ='Site Vist fomat (Design)'!G34 -> 0 | H31: ='Site Vist fomat (Design)'!H34 -> 0 | ... P31: ='Site Vist fomat (Design)'!P34 -> 0
A32: ='Site Vist fomat (Design)'!A35 -> Existing Bus Bar Size Material- Al/Cu./Type | B32: ='Site Vist fomat (Design)'!B35 -> 0 | C32: ='Site Vist fomat (Design)'!C35 -> 0 | D32: ='Site Vist fomat (Design)'!D35 -> 0 | E32: ='Site Vist fomat (Design)'!E35 -> 0 | F32: ='Site Vist fomat (Design)'!F35 -> 0 | G32: ='Site Vist fomat (Design)'!G35 -> 0 | H32: ='Site Vist fomat (Design)'!H35 -> 0 | ... P32: ='Site Vist fomat (Design)'!P35 -> 0
A33: ='Site Vist fomat (Design)'!A36 -> Main Incomer Rating | B33: ='Site Vist fomat (Design)'!B36 -> 0 | C33: ='Site Vist fomat (Design)'!C36 -> 0 | D33: ='Site Vist fomat (Design)'!D36 -> 0 | E33: ='Site Vist fomat (Design)'!E36 -> 0 | F33: ='Site Vist fomat (Design)'!F36 -> 0 | G33: ='Site Vist fomat (Design)'!G36 -> 0 | H33: ='Site Vist fomat (Design)'!H36 -> 0 | ... P33: ='Site Vist fomat (Design)'!P36 -> 0
A34: ='Site Vist fomat (Design)'!A37 -> Transmission method/ Method of Cable laying | B34: ='Site Vist fomat (Design)'!B37 -> 0 | C34: ='Site Vist fomat (Design)'!C37 -> 0 | D34: ='Site Vist fomat (Design)'!D37 -> 0 | E34: ='Site Vist fomat (Design)'!E37 -> 0 | F34: ='Site Vist fomat (Design)'!F37 -> 0 | G34: ='Site Vist fomat (Design)'!G37 -> 0 | H34: ='Site Vist fomat (Design)'!H37 -> 0 | ... P34: ='Site Vist fomat (Design)'!P37 -> 0
A35: ='Site Vist fomat (Design)'!A38 -> Termination LT Panel image | B35: ='Site Vist fomat (Design)'!B38 -> Attached | C35: ='Site Vist fomat (Design)'!C38 -> Attached | D35: ='Site Vist fomat (Design)'!D38 -> Attached | E35: ='Site Vist fomat (Design)'!E38 -> 0 | F35: ='Site Vist fomat (Design)'!F38 -> 0 | G35: ='Site Vist fomat (Design)'!G38 -> 0 | H35: ='Site Vist fomat (Design)'!H38 -> 0 | ... P35: ='Site Vist fomat (Design)'!P38 -> 0
A36: ='Site Vist fomat (Design)'!A39 -> Common Inputs
A37: ='Site Vist fomat (Design)'!A40 -> Distance from the sea shore? In Km | B37: ='Site Vist fomat (Design)'!B40 -> 40km | C37: ='Site Vist fomat (Design)'!C40 -> 40km | D37: ='Site Vist fomat (Design)'!D40 -> 40km | E37: ='Site Vist fomat (Design)'!E40 -> 0 | F37: ='Site Vist fomat (Design)'!F40 -> 0 | G37: ='Site Vist fomat (Design)'!G40 -> 0 | H37: ='Site Vist fomat (Design)'!H40 -> 0 | ... P37: ='Site Vist fomat (Design)'!P40 -> 0
A38: ='Site Vist fomat (Design)'!A41 -> Earth pit location identification | B38: ='Site Vist fomat (Design)'!B41 -> South (front side) | C38: ='Site Vist fomat (Design)'!C41 -> South (front side) | D38: ='Site Vist fomat (Design)'!D41 -> At parking area | E38: ='Site Vist fomat (Design)'!E41 -> 0 | F38: ='Site Vist fomat (Design)'!F41 -> 0 | G38: ='Site Vist fomat (Design)'!G41 -> 0 | H38: ='Site Vist fomat (Design)'!H41 -> 0 | ... P38: ='Site Vist fomat (Design)'!P41 -> 0
A39: ='Site Vist fomat (Design)'!A42 -> Availability of water system/Water tank for module cleaning | B39: ='Site Vist fomat (Design)'!B42 -> Available | C39: ='Site Vist fomat (Design)'!C42 -> Available | D39: ='Site Vist fomat (Design)'!D42 -> 0 | E39: ='Site Vist fomat (Design)'!E42 -> 0 | F39: ='Site Vist fomat (Design)'!F42 -> 0 | G39: ='Site Vist fomat (Design)'!G42 -> 0 | H39: ='Site Vist fomat (Design)'!H42 -> 0 | ... P39: ='Site Vist fomat (Design)'!P42 -> 0
A40: ='Site Vist fomat (Design)'!A43 -> Type of Water / Quality of water PPM (TDS Level) | B40: ='Site Vist fomat (Design)'!B43 -> 0 | C40: ='Site Vist fomat (Design)'!C43 -> 0 | D40: ='Site Vist fomat (Design)'!D43 -> 0 | E40: ='Site Vist fomat (Design)'!E43 -> 0 | F40: ='Site Vist fomat (Design)'!F43 -> 0 | G40: ='Site Vist fomat (Design)'!G43 -> 0 | H40: ='Site Vist fomat (Design)'!H43 -> 0 | ... P40: ='Site Vist fomat (Design)'!P43 -> 0
A41: ='Site Vist fomat (Design)'!A44 -> Permanent Access to roof location (None / Monkey Ladder / Step or Staricage Ladder) | B41: ='Site Vist fomat (Design)'!B44 -> Available | C41: ='Site Vist fomat (Design)'!C44 -> Available | D41: ='Site Vist fomat (Design)'!D44 -> NA | E41: ='Site Vist fomat (Design)'!E44 -> 0 | F41: ='Site Vist fomat (Design)'!F44 -> 0 | G41: ='Site Vist fomat (Design)'!G44 -> 0 | H41: ='Site Vist fomat (Design)'!H44 -> 0 | ... P41: ='Site Vist fomat (Design)'!P44 -> 0
A42: ='Site Vist fomat (Design)'!A45 -> Scope of Roof Access | B42: ='Site Vist fomat (Design)'!B45 -> Client | C42: ='Site Vist fomat (Design)'!C45 -> Client | D42: ='Site Vist fomat (Design)'!D45 -> Client | E42: ='Site Vist fomat (Design)'!E45 -> 0 | F42: ='Site Vist fomat (Design)'!F45 -> 0 | G42: ='Site Vist fomat (Design)'!G45 -> 0 | H42: ='Site Vist fomat (Design)'!H45 -> 0 | ... P42: ='Site Vist fomat (Design)'!P45 -> 0
A43: ='Site Vist fomat (Design)'!A46 -> Exisiting Lightening protection system & Coverage radius | B43: ='Site Vist fomat (Design)'!B46 -> 0 | C43: ='Site Vist fomat (Design)'!C46 -> 0 | D43: ='Site Vist fomat (Design)'!D46 -> 0 | E43: ='Site Vist fomat (Design)'!E46 -> 0 | F43: ='Site Vist fomat (Design)'!F46 -> 0 | G43: ='Site Vist fomat (Design)'!G46 -> 0 | H43: ='Site Vist fomat (Design)'!H46 -> 0 | ... P43: ='Site Vist fomat (Design)'!P46 -> 0
A44: ='Site Vist fomat (Design)'!A47 -> Parapet wall availability and Height | B44: ='Site Vist fomat (Design)'!B47 -> 1.2m | C44: ='Site Vist fomat (Design)'!C47 -> 1.2m | D44: ='Site Vist fomat (Design)'!D47 -> 0 | E44: ='Site Vist fomat (Design)'!E47 -> 0 | F44: ='Site Vist fomat (Design)'!F47 -> 0 | G44: ='Site Vist fomat (Design)'!G47 -> 0 | H44: ='Site Vist fomat (Design)'!H47 -> 0 | ... P44: ='Site Vist fomat (Design)'!P47 -> 0
A45: ='Site Vist fomat (Design)'!A48 -> Presence of intermediate column, if yes, height, spacing & dimension of the column | B45: ='Site Vist fomat (Design)'!B48 -> yes, 10m & 7m | C45: ='Site Vist fomat (Design)'!C48 -> yes, 10m & 7m | D45: ='Site Vist fomat (Design)'!D48 -> 0 | E45: ='Site Vist fomat (Design)'!E48 -> 0 | F45: ='Site Vist fomat (Design)'!F48 -> 0 | G45: ='Site Vist fomat (Design)'!G48 -> 0 | H45: ='Site Vist fomat (Design)'!H48 -> 0 | ... P45: ='Site Vist fomat (Design)'!P48 -> 0
A46: ='Site Vist fomat (Design)'!A49 -> Water harvesting availability | B46: ='Site Vist fomat (Design)'!B49 -> 0 | C46: ='Site Vist fomat (Design)'!C49 -> 0 | D46: ='Site Vist fomat (Design)'!D49 -> 0 | E46: ='Site Vist fomat (Design)'!E49 -> 0 | F46: ='Site Vist fomat (Design)'!F49 -> 0 | G46: ='Site Vist fomat (Design)'!G49 -> 0 | H46: ='Site Vist fomat (Design)'!H49 -> 0 | ... P46: ='Site Vist fomat (Design)'!P49 -> 0
A47: ='Site Vist fomat (Design)'!A50 -> Roof penetration is allowed or not (penetration if any shall be sealed properly) | B47: ='Site Vist fomat (Design)'!B50 -> 0 | C47: ='Site Vist fomat (Design)'!C50 -> 0 | D47: ='Site Vist fomat (Design)'!D50 -> 0 | E47: ='Site Vist fomat (Design)'!E50 -> 0 | F47: ='Site Vist fomat (Design)'!F50 -> 0 | G47: ='Site Vist fomat (Design)'!G50 -> 0 | H47: ='Site Vist fomat (Design)'!H50 -> 0 | ... P47: ='Site Vist fomat (Design)'!P50 -> 0
A48: ='Site Vist fomat (Design)'!A51 -> Any Observations/Remarks | B48: ='Site Vist fomat (Design)'!B51 -> intermediate columns, AHU unit, Water tank present at roof | C48: ='Site Vist fomat (Design)'!C51 -> intermediate columns, AHU unit, Water tank present at roof | D48: ='Site Vist fomat (Design)'!D51 -> 0 | E48: ='Site Vist fomat (Design)'!E51 -> 0 | F48: ='Site Vist fomat (Design)'!F51 -> 0 | G48: ='Site Vist fomat (Design)'!G51 -> 0 | H48: ='Site Vist fomat (Design)'!H51 -> 0 | ... P48: ='Site Vist fomat (Design)'!P51 -> 0
A49: ='Site Vist fomat (Design)'!A123 -> Logistic, Storage & Execution Details
A50: ='Site Vist fomat (Design)'!A124 -> Is Site reachable through road? | B50: ='Site Vist fomat (Design)'!B124 -> Yes | C50: ='Site Vist fomat (Design)'!C124 -> No
A51: ='Site Vist fomat (Design)'!D124 -> Storage Space for materials (L x W) | B51: ='Site Vist fomat (Design)'!E124 -> 0 | C51: ='Site Vist fomat (Design)'!F124 -> Place | D51: ='Site Vist fomat (Design)'!G124 -> Distance
A52: ='Site Vist fomat (Design)'!A125 -> Can a truck of 40 feet container reach site? (Observation/Dimension/Photo) | B52: ='Site Vist fomat (Design)'!B125 -> 0
A53: ='Site Vist fomat (Design)'!C125 -> Can a Hydra or Crane can move around structures on side (Yes/No) East ____, West ___, North ___, South ___ Attach Photos | B53: ='Site Vist fomat (Design)'!D125 -> 0 | C53: ='Site Vist fomat (Design)'!E125 -> 0 | D53: ='Site Vist fomat (Design)'!F125 -> 0 | E53: ='Site Vist fomat (Design)'!G125 -> 0
A54: ='Site Vist fomat (Design)'!A126 -> No of Working Hours allowed for execution? | B54: ='Site Vist fomat (Design)'!B126 -> 0
A55: ='Site Vist fomat (Design)'!C126 -> No of Workers allowed at Site? | B55: ='Site Vist fomat (Design)'!D126 -> 0
A56: ='Site Vist fomat (Design)'!E126 -> Any other restrictions related to execution | B56: ='Site Vist fomat (Design)'!F126 -> 0 | C56: ='Site Vist fomat (Design)'!G126 -> 0
A57: ='Site Vist fomat (Design)'!A52 -> RCC Roof Details
A58: ='Site Vist fomat (Design)'!A53 -> Water proofing type & Thickness in mm | B58: ='Site Vist fomat (Design)'!B53 -> 0 | C58: ='Site Vist fomat (Design)'!C53 -> 0 | D58: ='Site Vist fomat (Design)'!D53 -> 0 | E58: ='Site Vist fomat (Design)'!E53 -> 0 | F58: ='Site Vist fomat (Design)'!F53 -> 0 | G58: ='Site Vist fomat (Design)'!G53 -> 0 | H58: ='Site Vist fomat (Design)'!H53 -> 0 | ... P58: ='Site Vist fomat (Design)'!P53 -> 0
A59: ='Site Vist fomat (Design)'!A54 -> Waterproofing removal permission (Yes/No) | B59: ='Site Vist fomat (Design)'!B54 -> 0 | C59: ='Site Vist fomat (Design)'!C54 -> 0 | D59: ='Site Vist fomat (Design)'!D54 -> 0 | E59: ='Site Vist fomat (Design)'!E54 -> 0 | F59: ='Site Vist fomat (Design)'!F54 -> 0 | G59: ='Site Vist fomat (Design)'!G54 -> 0 | H59: ='Site Vist fomat (Design)'!H54 -> 0 | ... P59: ='Site Vist fomat (Design)'!P54 -> 0
A60: ='Site Vist fomat (Design)'!A55 -> Height of Building in mtrs | B60: ='Site Vist fomat (Design)'!B55 -> 0 | C60: ='Site Vist fomat (Design)'!C55 -> 0 | D60: ='Site Vist fomat (Design)'!D55 -> 0 | E60: ='Site Vist fomat (Design)'!E55 -> 0 | F60: ='Site Vist fomat (Design)'!F55 -> 0 | G60: ='Site Vist fomat (Design)'!G55 -> 0 | H60: ='Site Vist fomat (Design)'!H55 -> 0 | ... P60: ='Site Vist fomat (Design)'!P55 -> 0
A61: ='Site Vist fomat (Design)'!A56 -> Permission for chipping | B61: ='Site Vist fomat (Design)'!B56 -> 0 | C61: ='Site Vist fomat (Design)'!C56 -> 0 | D61: ='Site Vist fomat (Design)'!D56 -> 0 | E61: ='Site Vist fomat (Design)'!E56 -> 0 | F61: ='Site Vist fomat (Design)'!F56 -> 0 | G61: ='Site Vist fomat (Design)'!G56 -> 0 | H61: ='Site Vist fomat (Design)'!H56 -> 0 | ... P61: ='Site Vist fomat (Design)'!P56 -> 0
A62: ='Site Vist fomat (Design)'!A57 -> Year of construction | B62: ='Site Vist fomat (Design)'!B57 -> 0 | C62: ='Site Vist fomat (Design)'!C57 -> 2010 around | D62: ='Site Vist fomat (Design)'!D57 -> 0 | E62: ='Site Vist fomat (Design)'!E57 -> 0 | F62: ='Site Vist fomat (Design)'!F57 -> 0 | G62: ='Site Vist fomat (Design)'!G57 -> 0 | H62: ='Site Vist fomat (Design)'!H57 -> 0 | ... P62: ='Site Vist fomat (Design)'!P57 -> 0
A63: ='Site Vist fomat (Design)'!A58 -> Roof Area (Sqm) | B63: ='Site Vist fomat (Design)'!B58 -> 0 | C63: ='Site Vist fomat (Design)'!C58 -> 0 | D63: ='Site Vist fomat (Design)'!D58 -> 0 | E63: ='Site Vist fomat (Design)'!E58 -> 0 | F63: ='Site Vist fomat (Design)'!F58 -> 0 | G63: ='Site Vist fomat (Design)'!G58 -> 0 | H63: ='Site Vist fomat (Design)'!H58 -> 0 | ... P63: ='Site Vist fomat (Design)'!P58 -> 0
A64: ='Site Vist fomat (Design)'!A59 -> Roof area available for solar installation (Sqm) | B64: ='Site Vist fomat (Design)'!B59 -> 250 | C64: ='Site Vist fomat (Design)'!C59 -> 2030 | D64: ='Site Vist fomat (Design)'!D59 -> 0 | E64: ='Site Vist fomat (Design)'!E59 -> 0 | F64: ='Site Vist fomat (Design)'!F59 -> 0 | G64: ='Site Vist fomat (Design)'!G59 -> 0 | H64: ='Site Vist fomat (Design)'!H59 -> 0 | ... P64: ='Site Vist fomat (Design)'!P59 -> 0
A65: ='Site Vist fomat (Design)'!A61 -> Thickness of slab in mm | B65: ='Site Vist fomat (Design)'!B61 -> 0 | C65: ='Site Vist fomat (Design)'!C61 -> 0 | D65: ='Site Vist fomat (Design)'!D61 -> 0 | E65: ='Site Vist fomat (Design)'!E61 -> 0 | F65: ='Site Vist fomat (Design)'!F61 -> 0 | G65: ='Site Vist fomat (Design)'!G61 -> 0 | H65: ='Site Vist fomat (Design)'!H61 -> 0 | ... P65: ='Site Vist fomat (Design)'!P61 -> 0
A66: ='Site Vist fomat (Design)'!A62 -> Proposed structure height in mm | B66: ='Site Vist fomat (Design)'!B62 -> 3m | C66: ='Site Vist fomat (Design)'!C62 -> 3m | D66: ='Site Vist fomat (Design)'!D62 -> 0 | E66: ='Site Vist fomat (Design)'!E62 -> 0 | F66: ='Site Vist fomat (Design)'!F62 -> 0 | G66: ='Site Vist fomat (Design)'!G62 -> 0 | H66: ='Site Vist fomat (Design)'!H62 -> 0 | ... P66: ='Site Vist fomat (Design)'!P62 -> 0
A67: ='Site Vist fomat (Design)'!A63 -> Shed Roof Details
A68: ='Site Vist fomat (Design)'!A64 -> Height of the building at edge in mtrs | B68: ='Site Vist fomat (Design)'!B64 -> 0 | C68: ='Site Vist fomat (Design)'!C64 -> 0 | D68: ='Site Vist fomat (Design)'!D64 -> 0 | E68: ='Site Vist fomat (Design)'!E64 -> 0 | F68: ='Site Vist fomat (Design)'!F64 -> 0 | G68: ='Site Vist fomat (Design)'!G64 -> 0 | H68: ='Site Vist fomat (Design)'!H64 -> 0 | ... P68: ='Site Vist fomat (Design)'!P64 -> 0
A69: ='Site Vist fomat (Design)'!A65 -> Height of the building at ridge in mtrs | B69: ='Site Vist fomat (Design)'!B65 -> 0 | C69: ='Site Vist fomat (Design)'!C65 -> 0 | D69: ='Site Vist fomat (Design)'!D65 -> 0 | E69: ='Site Vist fomat (Design)'!E65 -> 0 | F69: ='Site Vist fomat (Design)'!F65 -> 0 | G69: ='Site Vist fomat (Design)'!G65 -> 0 | H69: ='Site Vist fomat (Design)'!H65 -> 0 | ... P69: ='Site Vist fomat (Design)'!P65 -> 0
A70: ='Site Vist fomat (Design)'!A66 -> Type of Shed Asbestos/Trapezoidal sheet/Puff Sheet/Standing seam | B70: ='Site Vist fomat (Design)'!B66 -> 0 | C70: ='Site Vist fomat (Design)'!C66 -> 0 | D70: ='Site Vist fomat (Design)'!D66 -> 0 | E70: ='Site Vist fomat (Design)'!E66 -> 0 | F70: ='Site Vist fomat (Design)'!F66 -> 0 | G70: ='Site Vist fomat (Design)'!G66 -> 0 | H70: ='Site Vist fomat (Design)'!H66 -> 0 | ... P70: ='Site Vist fomat (Design)'!P66 -> 0
A71: ='Site Vist fomat (Design)'!A67 -> Thickness of roof sheet (mm) | B71: ='Site Vist fomat (Design)'!B67 -> 0 | C71: ='Site Vist fomat (Design)'!C67 -> 0 | D71: ='Site Vist fomat (Design)'!D67 -> 0 | E71: ='Site Vist fomat (Design)'!E67 -> 0 | F71: ='Site Vist fomat (Design)'!F67 -> 0 | G71: ='Site Vist fomat (Design)'!G67 -> 0 | H71: ='Site Vist fomat (Design)'!H67 -> 0 | ... P71: ='Site Vist fomat (Design)'!P67 -> 0
A72: ='Site Vist fomat (Design)'!A68 -> Tilt/Angle of shed | B72: ='Site Vist fomat (Design)'!B68 -> 0 | C72: ='Site Vist fomat (Design)'!C68 -> 0 | D72: ='Site Vist fomat (Design)'!D68 -> 0 | E72: ='Site Vist fomat (Design)'!E68 -> 0 | F72: ='Site Vist fomat (Design)'!F68 -> 0 | G72: ='Site Vist fomat (Design)'!G68 -> 0 | H72: ='Site Vist fomat (Design)'!H68 -> 0 | ... P72: ='Site Vist fomat (Design)'!P68 -> 0
A73: ='Site Vist fomat (Design)'!A69 -> Railing required ? | B73: ='Site Vist fomat (Design)'!B69 -> 0 | C73: ='Site Vist fomat (Design)'!C69 -> 0 | D73: ='Site Vist fomat (Design)'!D69 -> 0 | E73: ='Site Vist fomat (Design)'!E69 -> 0 | F73: ='Site Vist fomat (Design)'!F69 -> 0 | G73: ='Site Vist fomat (Design)'!G69 -> 0 | H73: ='Site Vist fomat (Design)'!H69 -> 0 | ... P73: ='Site Vist fomat (Design)'!P69 -> 0
A74: ='Site Vist fomat (Design)'!A70 -> Activities under the roof (Manufacturing, Heating work, Chemical Emission, Paint shop, others) (Capture specific activity having impact on the generation) | B74: ='Site Vist fomat (Design)'!B70 -> 0 | C74: ='Site Vist fomat (Design)'!C70 -> 0 | D74: ='Site Vist fomat (Design)'!D70 -> 0 | E74: ='Site Vist fomat (Design)'!E70 -> 0 | F74: ='Site Vist fomat (Design)'!F70 -> 0 | G74: ='Site Vist fomat (Design)'!G70 -> 0 | H74: ='Site Vist fomat (Design)'!H70 -> 0 | ... P74: ='Site Vist fomat (Design)'!P70 -> 0
A75: ='Site Vist fomat (Design)'!A71 -> Distance between Machinery & Shed? Any heating furnace operations below the shed? | B75: ='Site Vist fomat (Design)'!B71 -> 0 | C75: ='Site Vist fomat (Design)'!C71 -> 0 | D75: ='Site Vist fomat (Design)'!D71 -> 0 | E75: ='Site Vist fomat (Design)'!E71 -> 0 | F75: ='Site Vist fomat (Design)'!F71 -> 0 | G75: ='Site Vist fomat (Design)'!G71 -> 0 | H75: ='Site Vist fomat (Design)'!H71 -> 0 | ... P75: ='Site Vist fomat (Design)'!P71 -> 0
A76: ='Site Vist fomat (Design)'!A72 -> Last major refurbishment (sheet change, leakage repairs, water proofing etc) | B76: ='Site Vist fomat (Design)'!B72 -> 0 | C76: ='Site Vist fomat (Design)'!C72 -> 0 | D76: ='Site Vist fomat (Design)'!D72 -> 0 | E76: ='Site Vist fomat (Design)'!E72 -> 0 | F76: ='Site Vist fomat (Design)'!F72 -> 0 | G76: ='Site Vist fomat (Design)'!G72 -> 0 | H76: ='Site Vist fomat (Design)'!H72 -> 0 | ... P76: ='Site Vist fomat (Design)'!P72 -> 0
A77: ='Site Vist fomat (Design)'!A73 -> Shadow Casting Objects on or near to the roof (Trees,Buildings,Water tank, Exhaust pipes, chillers, Turbo Fan, etc) | B77: ='Site Vist fomat (Design)'!B55 -> 0 | C77: ='Site Vist fomat (Design)'!C55 -> 0 | D77: ='Site Vist fomat (Design)'!D55 -> 0 | E77: ='Site Vist fomat (Design)'!E55 -> 0 | F77: ='Site Vist fomat (Design)'!F55 -> 0 | G77: ='Site Vist fomat (Design)'!G55 -> 0 | H77: ='Site Vist fomat (Design)'!H55 -> 0 | I77: ='Site Vist fomat (Design)'!I55 -> 0 | ... P77: ='Site Vist fomat (Design)'!P55 -> 0
A78: ='Site Vist fomat (Design)'!A74 -> Roof Condition (Good/Leakages / repairs / others) | B78: ='Site Vist fomat (Design)'!B74 -> 0 | C78: ='Site Vist fomat (Design)'!C74 -> 0 | D78: ='Site Vist fomat (Design)'!D74 -> 0 | E78: ='Site Vist fomat (Design)'!E74 -> 0 | F78: ='Site Vist fomat (Design)'!F74 -> 0 | G78: ='Site Vist fomat (Design)'!G74 -> 0 | H78: ='Site Vist fomat (Design)'!H74 -> 0 | ... P78: ='Site Vist fomat (Design)'!P74 -> 0
A79: ='Site Vist fomat (Design)'!A75 -> Year of construction | B79: ='Site Vist fomat (Design)'!B75 -> 0 | C79: ='Site Vist fomat (Design)'!C75 -> 0 | D79: ='Site Vist fomat (Design)'!D75 -> 0 | E79: ='Site Vist fomat (Design)'!E75 -> 0 | F79: ='Site Vist fomat (Design)'!F75 -> 0 | G79: ='Site Vist fomat (Design)'!G75 -> 0 | H79: ='Site Vist fomat (Design)'!H75 -> 0 | ... P79: ='Site Vist fomat (Design)'!P75 -> 0
A80: ='Site Vist fomat (Design)'!A76 -> Skylight Nos & Dimensions in mm | B80: ='Site Vist fomat (Design)'!B76 -> 0 | C80: ='Site Vist fomat (Design)'!C76 -> 0 | D80: ='Site Vist fomat (Design)'!D76 -> 0 | E80: ='Site Vist fomat (Design)'!E76 -> 0 | F80: ='Site Vist fomat (Design)'!F76 -> 0 | G80: ='Site Vist fomat (Design)'!G76 -> 0 | H80: ='Site Vist fomat (Design)'!H76 -> 0 | ... P80: ='Site Vist fomat (Design)'!P76 -> 0
A81: ='Site Vist fomat (Design)'!A77 -> Sky light to sky light distance in mm | B81: ='Site Vist fomat (Design)'!B77 -> 0 | C81: ='Site Vist fomat (Design)'!C77 -> 0 | D81: ='Site Vist fomat (Design)'!D77 -> 0 | E81: ='Site Vist fomat (Design)'!E77 -> 0 | F81: ='Site Vist fomat (Design)'!F77 -> 0 | G81: ='Site Vist fomat (Design)'!G77 -> 0 | H81: ='Site Vist fomat (Design)'!H77 -> 0 | ... P81: ='Site Vist fomat (Design)'!P77 -> 0
A82: ='Site Vist fomat (Design)'!A78 -> Existing Gutter length in mtrs | B82: ='Site Vist fomat (Design)'!B78 -> 0 | C82: ='Site Vist fomat (Design)'!C78 -> 0 | D82: ='Site Vist fomat (Design)'!D78 -> 0 | E82: ='Site Vist fomat (Design)'!E78 -> 0 | F82: ='Site Vist fomat (Design)'!F78 -> 0 | G82: ='Site Vist fomat (Design)'!G78 -> 0 | H82: ='Site Vist fomat (Design)'!H78 -> 0 | ... P82: ='Site Vist fomat (Design)'!P78 -> 0
A83: ='Site Vist fomat (Design)'!A79 -> Turbo vent dimensions in mm | B83: ='Site Vist fomat (Design)'!B79 -> 0 | C83: ='Site Vist fomat (Design)'!C79 -> 0 | D83: ='Site Vist fomat (Design)'!D79 -> 0 | E83: ='Site Vist fomat (Design)'!E79 -> 0 | F83: ='Site Vist fomat (Design)'!F79 -> 0 | G83: ='Site Vist fomat (Design)'!G79 -> 0 | H83: ='Site Vist fomat (Design)'!H79 -> 0 | ... P83: ='Site Vist fomat (Design)'!P79 -> 0
A84: ='Site Vist fomat (Design)'!A80 -> Turbo vent to turbo vent distance in mm | B84: ='Site Vist fomat (Design)'!B80 -> 0 | C84: ='Site Vist fomat (Design)'!C80 -> 0 | D84: ='Site Vist fomat (Design)'!D80 -> 0 | E84: ='Site Vist fomat (Design)'!E80 -> 0 | F84: ='Site Vist fomat (Design)'!F80 -> 0 | G84: ='Site Vist fomat (Design)'!G80 -> 0 | H84: ='Site Vist fomat (Design)'!H80 -> 0 | ... P84: ='Site Vist fomat (Design)'!P80 -> 0
A85: ='Site Vist fomat (Design)'!A81 -> Any level difference in roof location (indicate location on Roof plan) | B85: ='Site Vist fomat (Design)'!B81 -> 0 | C85: ='Site Vist fomat (Design)'!C81 -> 0 | D85: ='Site Vist fomat (Design)'!D81 -> 0 | E85: ='Site Vist fomat (Design)'!E81 -> 0 | F85: ='Site Vist fomat (Design)'!F81 -> 0 | G85: ='Site Vist fomat (Design)'!G81 -> 0 | H85: ='Site Vist fomat (Design)'!H81 -> 0 | ... P85: ='Site Vist fomat (Design)'!P81 -> 0
A86: ='Site Vist fomat (Design)'!A82 -> Additional load bearing capacity of the roof for Solar PV & installation / maintenance (Indicative distributed load capacity of 20kg/m2, point load capacity 80 kg/m2.) | B86: ='Site Vist fomat (Design)'!B82 -> 0 | C86: ='Site Vist fomat (Design)'!C82 -> 0 | D86: ='Site Vist fomat (Design)'!D82 -> 0 | E86: ='Site Vist fomat (Design)'!E82 -> 0 | F86: ='Site Vist fomat (Design)'!F82 -> 0 | G86: ='Site Vist fomat (Design)'!G82 -> 0 | H86: ='Site Vist fomat (Design)'!H82 -> 0 | ... P86: ='Site Vist fomat (Design)'!P82 -> 0
A87: ='Site Vist fomat (Design)'!A83 -> Exisiting Lifeline / Walkway availability (indicate location on Roof plan) | B87: ='Site Vist fomat (Design)'!B83 -> 0 | C87: ='Site Vist fomat (Design)'!C83 -> 0 | D87: ='Site Vist fomat (Design)'!D83 -> 0 | E87: ='Site Vist fomat (Design)'!E83 -> 0 | F87: ='Site Vist fomat (Design)'!F83 -> 0 | G87: ='Site Vist fomat (Design)'!G83 -> 0 | H87: ='Site Vist fomat (Design)'!H83 -> 0 | ... P87: ='Site Vist fomat (Design)'!P83 -> 0
A88: Metal Sheet Profile Diagram
A89: ='Site Vist fomat (Design)'!A85 -> Diagram --> | B89: ='Site Vist fomat (Design)'!B85 -> 0 | C89: ='Site Vist fomat (Design)'!C85 -> 0 | D89: ='Site Vist fomat (Design)'!D85 -> 0 | E89: ='Site Vist fomat (Design)'!E85 -> 0 | F89: ='Site Vist fomat (Design)'!F85 -> 0 | G89: ='Site Vist fomat (Design)'!G85 -> 0 | H89: ='Site Vist fomat (Design)'!H85 -> 0 | ... P89: ='Site Vist fomat (Design)'!P85 -> 0
A90: Metal Sheet & Purlin Pictures
A91: ='Site Vist fomat (Design)'!A87 -> Photo 1 --> | B91: ='Site Vist fomat (Design)'!B87 -> 0 | C91: ='Site Vist fomat (Design)'!C87 -> 0 | D91: ='Site Vist fomat (Design)'!D87 -> 0 | E91: ='Site Vist fomat (Design)'!E87 -> 0 | F91: ='Site Vist fomat (Design)'!F87 -> 0 | G91: ='Site Vist fomat (Design)'!G87 -> 0 | H91: ='Site Vist fomat (Design)'!H87 -> 0 | ... P91: ='Site Vist fomat (Design)'!P87 -> 0
A92: ='Site Vist fomat (Design)'!A88 -> Photo 2 --> | B92: ='Site Vist fomat (Design)'!B88 -> 0 | C92: ='Site Vist fomat (Design)'!C88 -> 0 | D92: ='Site Vist fomat (Design)'!D88 -> 0 | E92: ='Site Vist fomat (Design)'!E88 -> 0 | F92: ='Site Vist fomat (Design)'!F88 -> 0 | G92: ='Site Vist fomat (Design)'!G88 -> 0 | H92: ='Site Vist fomat (Design)'!H88 -> 0 | ... P92: ='Site Vist fomat (Design)'!P88 -> 0
A93: ='Site Vist fomat (Design)'!A89 -> Ground Details
A94: ='Site Vist fomat (Design)'!A90 -> Is Land Clear? (Yes/No) | B94: ='Site Vist fomat (Design)'!B90 -> 0 | C94: ='Site Vist fomat (Design)'!C90 -> 0 | D94: ='Site Vist fomat (Design)'!D90 -> 0 | E94: ='Site Vist fomat (Design)'!E90 -> 0 | F94: ='Site Vist fomat (Design)'!F90 -> 0 | G94: ='Site Vist fomat (Design)'!G90 -> 0 | H94: ='Site Vist fomat (Design)'!H90 -> 0 | ... P94: ='Site Vist fomat (Design)'!P90 -> 0
A95: ='Site Vist fomat (Design)'!A91 -> If No then please mention type of obstacles | B95: ='Site Vist fomat (Design)'!B91 -> 0 | C95: ='Site Vist fomat (Design)'!C91 -> 0 | D95: ='Site Vist fomat (Design)'!D91 -> 0 | E95: ='Site Vist fomat (Design)'!E91 -> 0 | F95: ='Site Vist fomat (Design)'!F91 -> 0 | G95: ='Site Vist fomat (Design)'!G91 -> 0 | H95: ='Site Vist fomat (Design)'!H91 -> 0 | ... P95: ='Site Vist fomat (Design)'!P91 -> 0
A96: ='Site Vist fomat (Design)'!A92 -> Photo 1 --> | B96: ='Site Vist fomat (Design)'!B92 -> 0 | C96: ='Site Vist fomat (Design)'!C92 -> 0 | D96: ='Site Vist fomat (Design)'!D92 -> 0 | E96: ='Site Vist fomat (Design)'!E92 -> 0 | F96: ='Site Vist fomat (Design)'!F92 -> 0 | G96: ='Site Vist fomat (Design)'!G92 -> 0 | H96: ='Site Vist fomat (Design)'!H92 -> 0 | ... P96: ='Site Vist fomat (Design)'!P92 -> 0
A97: ='Site Vist fomat (Design)'!A93 -> Photo 2 --> | B97: ='Site Vist fomat (Design)'!B93 -> 0 | C97: ='Site Vist fomat (Design)'!C93 -> 0 | D97: ='Site Vist fomat (Design)'!D93 -> 0 | E97: ='Site Vist fomat (Design)'!E93 -> 0 | F97: ='Site Vist fomat (Design)'!F93 -> 0 | G97: ='Site Vist fomat (Design)'!G93 -> 0 | H97: ='Site Vist fomat (Design)'!H93 -> 0 | ... P97: ='Site Vist fomat (Design)'!P93 -> 0
A98: ='Site Vist fomat (Design)'!A94 -> Available Ground area in acres | B98: ='Site Vist fomat (Design)'!B94 -> 0 | C98: ='Site Vist fomat (Design)'!C94 -> 0 | D98: ='Site Vist fomat (Design)'!D94 -> 0 | E98: ='Site Vist fomat (Design)'!E94 -> 0 | F98: ='Site Vist fomat (Design)'!F94 -> 0 | G98: ='Site Vist fomat (Design)'!G94 -> 0 | H98: ='Site Vist fomat (Design)'!H94 -> 0 | ... P98: ='Site Vist fomat (Design)'!P94 -> 0
A99: ='Site Vist fomat (Design)'!A95 -> Land Levelling required? (Yes/No) | B99: ='Site Vist fomat (Design)'!B95 -> 0 | C99: ='Site Vist fomat (Design)'!C95 -> 0 | D99: ='Site Vist fomat (Design)'!D95 -> 0 | E99: ='Site Vist fomat (Design)'!E95 -> 0 | F99: ='Site Vist fomat (Design)'!F95 -> 0 | G99: ='Site Vist fomat (Design)'!G95 -> 0 | H99: ='Site Vist fomat (Design)'!H95 -> 0 | ... P99: ='Site Vist fomat (Design)'!P95 -> 0
A100: ='Site Vist fomat (Design)'!A96 -> Scope of Vegetation/Trees/obstacle clearing. | B100: ='Site Vist fomat (Design)'!B96 -> 0 | C100: ='Site Vist fomat (Design)'!C96 -> 0 | D100: ='Site Vist fomat (Design)'!D96 -> 0 | E100: ='Site Vist fomat (Design)'!E96 -> 0 | F100: ='Site Vist fomat (Design)'!F96 -> 0 | G100: ='Site Vist fomat (Design)'!G96 -> 0 | H100: ='Site Vist fomat (Design)'!H96 -> 0 | ... P100: ='Site Vist fomat (Design)'!P96 -> 0
...

Sheet Site Vist fomat  (Design)
A1: Fourth Partner Energy Pvt. Ltd. | E1: DOC. No: | F1: 4PEL/DES-SSR/553 #I01, R00.
E2: Issue Date : | F2: 11/12/2023.
E3: Control Copy No : | F3: 2
A4: SITE SURVEY REPORT | E4: Survey Date : | F4: 46153
A5: General Information
A6: Name of the Customer | B6: Metro Junction mall
A7: Contact Person's Name & Designation | D7: Mobile No | F7: Email Id
A8: Site Address : | B8: Metro Junction Mall, Kalyan - Shilphata Rd, Kalyan East, Kalyan, Maharashtra 421306
A9: GPS Cordinates | B9: 19.229564° N | C9: 73.123271° E | D9: Nearest Railway Station | E9: Kalyan | F9: Nearest Highway | G9: Kalyan-Shil phata
A10: Industry Type | B10: Cement/Paint/FMCG/Metal/ITES/Auto & Auto Ancillary/Textile/Pharma/Plastic& Rubber/Infra/Telecom/Financial Srevices/Others (Specify) - Mall
A11: Type of business operation at site | B11: Manufacturing | C11: Warehousing | D11: Packaging | E11: Retail | F11: Service | G11: Others (Specify) - Mall
A12: Type of Installation | C12: RCC | E12: Parking
A13: Ownership | B13: Owned | C13: Leased | D13: Lease expiry after yrs | E13: Right to Install SPP --> | F13: Yes | G13: No
A14: Customer RE Requirement
A15: Expected Solar PV / Storage Capacity | B15: kWp MwH | C15: CT | D15: Gross Metering | E15: Captive | F15: On Grid | G15: Off Grid
A16: Proposed SPP Evacuation Voltage | B16: 0.45 kV | C16: (If Evacuation Voltage >=11 KV, check space available to construct substation)
A17: Existing Electrical Infrastructure
A18: Discom Name | B18: MSEDCL | C18: Contract Demand | D18: 449 KVA | E18: Total Connected Load | F18: kW | G18: Power Factor: 0.89-0.995
A19: Distribution Transformer (DT) Details | B19: Qty - _01 Nos | C19: Rating- kVA | D19: Voltage Ratio - ___/____ | E19: Vector Group- _______ | F19: Shortcircuit Level (HT VCB Level) - _______ Kv | G19: Make & Model for each transformer -
A20: Sources of Power Available for synchronizing | B20: EB Supply | C20: DG Supply | D20: CPP | E20: Others (specify) | F20: Synchronisation | G20: Manual/Automatic - Automatic
A21: Grid Outage Data | B21: No. of Hours/day :__________ | C21: Operational Days in a Year | D21: Days | E21: Grid Frequency/Voltage Fluctuations (Yes/No) | F21: Yes | G21: No
B22: No. of times/Day: ______________ | C22: No of Off Days for Maintenance & Load | D22: Days | E22: kW | F22: Operational Hours in a Day: ________ | G22: No of Shifts/Day: __________
A23: No of Off Days for Holidays & Load | B23: Days | C23: kW | D23: Installed DG Set | E23: Qty - __03 Nos | F23: Rating - _1010 kVA | G23: Voltage _400 V
A24: Existing Solar Capacity in KWp (DC capacity) | B24: NO | C24: 0 | D24: Is the existing plant Net Metered? | E24: (Yes/No) | F24: Is the existing plant installed with RPR? | G24: (Yes/No)
A25: EB Meter Details | B25: Class _____________ | C25: Make: ___________________ | D25: STC Rating ____________ | E25: APFC Panel (Location & Rating) type( automatice/manual)
A26: No. of service connection (Qty.) | B26: 2 | C26: Metering CT& PT Details / Class | E26: Earth resistivity & Standards/Specifications | F26: 2 ohm- convetional type/ chemical
A27: Electrical Details | H27: Electrical Details
A28: Name of the building (As per customer's nomenclature) | B28: Main RCC B Block at LG | C28: Main RCC D Block at LG | D28: Parking
A29: Location wise Exisiting LT panel breker capacity | B29: LT Room B Block at LG Main termination is in Ground floor | C29: LT Room D Block at LG Main termination is in Ground floor | D29: LT Room B Block at LG Main termination is in Ground floor
A30: Incomer Cable runs and size
A31: Termination distance in mtrs | B31: 170 | C31: 220 | D31: 200
A32: Tentative location of inverter & LT Panel | B32: at terrace level | C32: at terrace level | D32: At parking area
A33: Spare feeder avilability (mention as rating) | B33: No | C33: No | D33: No
A34: Bus bar extensions required? Scope?
A35: Existing Bus Bar Size Material- Al/Cu./Type
A36: Main Incomer Rating
A37: Transmission method/ Method of Cable laying
A38: Termination LT Panel image | B38: Attached | C38: Attached | D38: Attached
A39: Common Inputs | H39: Commen inputs
A40: Distance from the sea shore? In Km | B40: 40km | C40: 40km | D40: 40km
A41: Earth pit location identification | B41: South (front side) | C41: South (front side) | D41: At parking area
A42: Availability of water system/Water tank for module cleaning | B42: Available | C42: Available
A43: Type of Water / Quality of water PPM (TDS Level)
A44: Permanent Access to roof location (None / Monkey Ladder / Step or Staricage Ladder) | B44: Available | C44: Available | D44: NA
A45: Scope of Roof Access | B45: Client | C45: Client | D45: Client
A46: Exisiting Lightening protection system & Coverage radius
A47: Parapet wall availability and Height | B47: 1.2m | C47: 1.2m
A48: Presence of intermediate column, if yes, height, spacing & dimension of the column | B48: yes, 10m & 7m | C48: yes, 10m & 7m
A49: Water harvesting availability
A50: Roof penetration is allowed or not (penetration if any shall be sealed properly)
A51: Any Observations/Remarks | B51: intermediate columns, AHU unit, Water tank present at roof | C51: intermediate columns, AHU unit, Water tank present at roof
A52: RCC Roof Details | H52: RCC Roof details
A53: Water proofing type & Thickness in mm
A54: Waterproofing removal permission (Yes/No)
A55: Height of Building in mtrs
A56: Permission for chipping
A57: Year of construction | C57: 2010 around
A58: Roof Area (Sqm)
A59: Roof area available for solar installation (Sqm) | B59: 250 | C59: 2030
A60: Near by obj. moving shadow | B60: mall buidling | C60: theatre shed, dome, tanks, adjacent building
A61: Thickness of slab in mm
A62: Proposed structure height in mm | B62: 3m | C62: 3m
A63: Shed Roof Details | H63: Shed Roof details
A64: Height of the building at edge in mtrs
A65: Height of the building at ridge in mtrs
A66: Type of Shed Asbestos/Trapezoidal sheet/Puff Sheet/Standing seam
A67: Thickness of roof sheet (mm)
A68: Tilt/Angle of shed
A69: Railing required ?
A70: Activities under the roof (Manufacturing, Heating work, Chemical Emission, Paint shop, others) (Capture specific activity having impact on the generation)
A71: Distance between Machinery & Shed? Any heating furnace operations below the shed?
A72: Last major refurbishment (sheet change, leakage repairs, water proofing etc)
A73: Shadow Casting Objects on or near to the roof (Trees,Buildings,Water tank, Exhaust pipes, chillers, Turbo Fan, etc)
A74: Roof Condition (Good/Leakages / repairs / others)
A75: Year of construction
... A83: Exisiting Lifeline / Walkway availability (indicate location on Roof plan)
B84: Metal Sheet Profile Diagram | C84: Metal Sheet Profile Diagram | D84: Metal Sheet Profile Diagram | E84: Metal Sheet Profile Diagram | F84: Metal Sheet Profile Diagram | G84: Metal Sheet Profile Diagram | H84: Metal Sheet Profile Diagram | I84: Metal Sheet Profile Diagram | J84: Metal Sheet Profile Diagram | K84: Metal Sheet Profile Diagram | L84: Metal Sheet Profile Diagram | M84: Metal Sheet Profile Diagram | N84: Metal Sheet Profile Diagram | O84: Metal Sheet Profile Diagram | P84: Metal Sheet Profile Diagram
A85: Diagram -->
B86: Metal Sheet & Purlin Pictures | C86: Metal Sheet & Purlin Pictures | D86: Metal Sheet & Purlin Pictures | E86: Metal Sheet & Purlin Pictures | F86: Metal Sheet & Purlin Pictures | G86: Metal Sheet & Purlin Pictures | H86: Metal Sheet & Purlin Pictures | I86: Metal Sheet & Purlin Pictures | J86: Metal Sheet & Purlin Pictures | K86: Metal Sheet & Purlin Pictures | L86: Metal Sheet & Purlin Pictures | M86: Metal Sheet & Purlin Pictures | N86: Metal Sheet & Purlin Pictures | O86: Metal Sheet & Purlin Pictures | P86: Metal Sheet & Purlin Pictures
A87: Photo 1 -->
A88: Photo 2 -->
A89: Ground Details | H89: Ground Details
A90: Is Land Clear? (Yes/No)
A91: If No then please mention type of obstacles
A92: Photo 1 -->
A93: Photo 2 -->
A94: Available Ground area in acres
A95: Land Levelling required? (Yes/No)
A96: Scope of Vegetation/Trees/obstacle clearing.
A97: Perminsion of Vegetation/Trees/obstacle clearing.
A98: Soil test report available? (Yes/No)
A99: Scope of Soil test
A100: Specify soil type (if possible) Wet soil/Dry soil/Hard rock/Fissured rock)
A101: Whether Rock area? At what depth
... A109: Remark (If any) :-
A110: Car Parking Details | H110: Car Parking Details
A111: Type of Ground Whether Tiles/ PCC/ RCC/ soil Ground | C111: paver block
A112: If RCC, Client is ready to Anchoring / Isolated foundation?
A113: No of Cars Parking | C113: as per area
A114: Any transmission lines passing over Parking area? | C114: No
...

Sheet Input's from Initial Design
C1: Fourth Partner Energy Pvt. Ltd | Q1: DOC. No: 4PEL/DES-IDS/039 #I01, R05.
Q2: Issue Date: 23/02/2026.
Q3: Control Copy No. 02.
C4: Initial Design Sheet
A5: DETAILED INITIAL DESIGN REPORT | L5: =IF(OR('Site Vist fomat (Design)'!B24=0,'Site Vist fomat (Design)'!C24=0),"Please fill Existing Plant details","") -> Please fill Existing Plant details | M5: Inputs for initial design from BD | R5: Information Sheet (String Inv. LT)
A6: Availability of RFP/RFQ | C6: =IF('Input''s from BD(Sales)'!B15="", "Not Updated", IFERROR('Input''s from BD(Sales)'!B15, "Not Updated")) -> Yes | F6: Is Design prepared According to RFP/RFQ | I6: Yes | M6: Module wattage (Wp) | O6: ='Input''s from BD(Sales)'!B20 -> 595 / 590 / 585
A7: Site Name & State | C7: ='Input''s from Site Visit'!B6 -> Metro Junction mall | F7: ='Input''s from BD(Sales)'!B10 -> Maharashtra | I7: Comment | M7: Module Origin | O7: ='Input''s from BD(Sales)'!B21 -> ALMM Approved | R7: Shed | S7: =IF($C$25=R7,$G$25,0)+IF($C$26=R7,$G$26,0)+IF($C$27=R7,$G$27,0)+IF($C$28=R7,$G$28,0)+IF($C$29=R7,$G$29)+IF($C$30=R7,$G$30,0)+IF($C$31=R7,$G$31,0)+IF($C$32=R7,$G$32,0)+IF($C$33=R7,$G$33,0)+IF($C$34=R7,$G$34)+IF($C$35=R7,$G$35,0)+IF($C$36=R7,$G$36,0)+IF($C$37=R7,$G$37,0)+IF($C$38=R7,$G$38,0)+IF($C$39=R7,$G$39,0)+IF($C$40=R7,$G$40,0)+IF($C$41=R7,$G$41,0)+IF($C$42=R7,$G$42,0)+IF($C$43=R7,$G$43,0)+IF($C$44=R7,$G$44,0)+IF($C$45=R7,$G$45,0)+IF($C$46=R7,$G$46,0)+IF($C$47=R7,$G$47,0)+IF($C$48=R7,$G$48,0)+IF($C$49=R7,$G$49,0)+IF($C$50=R7,$G$50,0)+IF($C$51=R7,$G$51,0)+IF($C$52=R7,$G$52,0)+IF($C$53=R7,$G$53,0)+IF($C$54=R7,$G$54,0) -> 0
A8: Address & Lat Long | C8: ='Input''s from Site Visit'!B7 -> Metro Junction Mall, Kalyan - Shilphata Rd, Kalyan East, Kalyan, Maharashtra 421306 | F8: ='Input''s from BD(Sales)'!B14 -> 19°13'45.98"N 73°07'23.94"E | M8: Prefered Inverter make | O8: ='Input''s from BD(Sales)'!B22 -> Solis / Sungrow / Equivalent | R8: Long Rail | S8: =IF($C$25=R8,$G$25,0)+IF($C$26=R8,$G$26,0)+IF($C$27=R8,$G$27,0)+IF($C$28=R8,$G$28,0)+IF($C$29=R8,$G$29)+IF($C$30=R8,$G$30,0)+IF($C$31=R8,$G$31,0)+IF($C$32=R8,$G$32,0)+IF($C$33=R8,$G$33,0)+IF($C$34=R8,$G$34)+IF($C$35=R8,$G$35,0)+IF($C$36=R8,$G$36,0)+IF($C$37=R8,$G$37,0)+IF($C$38=R8,$G$38,0)+IF($C$39=R8,$G$39,0)+IF($C$40=R8,$G$40,0)+IF($C$41=R8,$G$41,0)+IF($C$42=R8,$G$42,0)+IF($C$43=R8,$G$43,0)+IF($C$44=R8,$G$44,0)+IF($C$45=R8,$G$45,0)+IF($C$46=R8,$G$46,0)+IF($C$47=R8,$G$47,0)+IF($C$48=R8,$G$48,0)+IF($C$49=R8,$G$49,0)+IF($C$50=R8,$G$50,0)+IF($C$51=R8,$G$51,0)+IF($C$52=R8,$G$52,0)+IF($C$53=R8,$G$53,0)+IF($C$54=R8,$G$54,0) -> 0
A9: Approval Details | C9: Name of the Person | F9: Approval Date | M9: DC/AC Ratio | O9: ='Input''s from BD(Sales)'!B23 -> 0 | R9: RCC | S9: =IF($C$25=R9,$G$25,0)+IF($C$26=R9,$G$26,0)+IF($C$27=R9,$G$27,0)+IF($C$28=R9,$G$28,0)+IF($C$29=R9,$G$29)+IF($C$30=R9,$G$30,0)+IF($C$31=R9,$G$31,0)+IF($C$32=R9,$G$32,0)+IF($C$33=R9,$G$33,0)+IF($C$34=R9,$G$34)+IF($C$35=R9,$G$35,0)+IF($C$36=R9,$G$36,0)+IF($C$37=R9,$G$37,0)+IF($C$38=R9,$G$38,0)+IF($C$39=R9,$G$39,0)+IF($C$40=R9,$G$40,0)+IF($C$41=R9,$G$41,0)+IF($C$42=R9,$G$42,0)+IF($C$43=R9,$G$43,0)+IF($C$44=R9,$G$44,0)+IF($C$45=R9,$G$45,0)+IF($C$46=R9,$G$46,0)+IF($C$47=R9,$G$47,0)+IF($C$48=R9,$G$48,0)+IF($C$49=R9,$G$49,0)+IF($C$50=R9,$G$50,0)+IF($C$51=R9,$G$51,0)+IF($C$52=R9,$G$52,0)+IF($C$53=R9,$G$53,0)+IF($C$54=R9,$G$54,0) -> 0
A10: Initial Design Done By | C10: Ashish A | F10: Date: | G10: 46199 | M10: Roof Puncturing permission from client | R10: RCC Raised | S10: =IF($C$25=R10,$G$25,0)+IF($C$26=R10,$G$26,0)+IF($C$27=R10,$G$27,0)+IF($C$28=R10,$G$28,0)+IF($C$29=R10,$G$29)+IF($C$30=R10,$G$30,0)+IF($C$31=R10,$G$31,0)+IF($C$32=R10,$G$32,0)+IF($C$33=R10,$G$33,0)+IF($C$34=R10,$G$34)+IF($C$35=R10,$G$35,0)+IF($C$36=R10,$G$36,0)+IF($C$37=R10,$G$37,0)+IF($C$38=R10,$G$38,0)+IF($C$39=R10,$G$39,0)+IF($C$40=R10,$G$40,0)+IF($C$41=R10,$G$41,0)+IF($C$42=R10,$G$42,0)+IF($C$43=R10,$G$43,0)+IF($C$44=R10,$G$44,0)+IF($C$45=R10,$G$45,0)+IF($C$46=R10,$G$46,0)+IF($C$47=R10,$G$47,0)+IF($C$48=R10,$G$48,0)+IF($C$49=R10,$G$49,0)+IF($C$50=R10,$G$50,0)+IF($C$51=R10,$G$51,0)+IF($C$52=R10,$G$52,0)+IF($C$53=R10,$G$53,0)+IF($C$54=R10,$G$54,0) -> 400.52
A11: Initial Design Approved By | C11: Sagar C | G11: 46199 | M11: ='Input''s from BD(Sales)'!A43 -> Modules (MMS) | O11: ='Input''s from BD(Sales)'!B43 -> 0 | R11: RCC Raised on Pillars | S11: =IF($C$25=R11,$G$25,0)+IF($C$26=R11,$G$26,0)+IF($C$27=R11,$G$27,0)+IF($C$28=R11,$G$28,0)+IF($C$29=R11,$G$29)+IF($C$30=R11,$G$30,0)+IF($C$31=R11,$G$31,0)+IF($C$32=R11,$G$32,0)+IF($C$33=R11,$G$33,0)+IF($C$34=R11,$G$34)+IF($C$35=R11,$G$35,0)+IF($C$36=R11,$G$36,0)+IF($C$37=R11,$G$37,0)+IF($C$38=R11,$G$38,0)+IF($C$39=R11,$G$39,0)+IF($C$40=R11,$G$40,0)+IF($C$41=R11,$G$41,0)+IF($C$42=R11,$G$42,0)+IF($C$43=R11,$G$43,0)+IF($C$44=R11,$G$44,0)+IF($C$45=R11,$G$45,0)+IF($C$46=R11,$G$46,0)+IF($C$47=R11,$G$47,0)+IF($C$48=R11,$G$48,0)+IF($C$49=R11,$G$49,0)+IF($C$50=R11,$G$50,0)+IF($C$51=R11,$G$51,0)+IF($C$52=R11,$G$52,0)+IF($C$53=R11,$G$53,0)+IF($C$54=R11,$G$54,0) -> 0
I12: =IF(I6=0,"Please fill RFQ/RFP details","") | M12: ='Input''s from BD(Sales)'!A45 -> Lifeline location | O12: ='Input''s from BD(Sales)'!B45 -> 0 | R12: Ground Mounted | S12: =IF($C$25=R12,$G$25,0)+IF($C$26=R12,$G$26,0)+IF($C$27=R12,$G$27,0)+IF($C$28=R12,$G$28,0)+IF($C$29=R12,$G$29)+IF($C$30=R12,$G$30,0)+IF($C$31=R12,$G$31,0)+IF($C$32=R12,$G$32,0)+IF($C$33=R12,$G$33,0)+IF($C$34=R12,$G$34)+IF($C$35=R12,$G$35,0)+IF($C$36=R12,$G$36,0)+IF($C$37=R12,$G$37,0)+IF($C$38=R12,$G$38,0)+IF($C$39=R12,$G$39,0)+IF($C$40=R12,$G$40,0)+IF($C$41=R12,$G$41,0)+IF($C$42=R12,$G$42,0)+IF($C$43=R12,$G$43,0)+IF($C$44=R12,$G$44,0)+IF($C$45=R12,$G$45,0)+IF($C$46=R12,$G$46,0)+IF($C$47=R12,$G$47,0)+IF($C$48=R12,$G$48,0)+IF($C$49=R12,$G$49,0)+IF($C$50=R12,$G$50,0)+IF($C$51=R12,$G$51,0)+IF($C$52=R12,$G$52,0)+IF($C$53=R12,$G$53,0)+IF($C$54=R12,$G$54,0) -> 0
A13: Revision No. | C13: DR1 * | D13: DR2 * | E13: DR3 * | F13: DR4 * | G13: DR5 * | H13: DR6 * | I13: Notes for Design from BD | M13: Walkway Dimension (W) | O13: ='Input''s from BD(Sales)'!B44 -> 0 | R13: Parking- Car/Bike | S13: =IF($C$25=R13,$G$25,0)+IF($C$26=R13,$G$26,0)+IF($C$27=R13,$G$27,0)+IF($C$28=R13,$G$28,0)+IF($C$29=R13,$G$29)+IF($C$30=R13,$G$30,0)+IF($C$31=R13,$G$31,0)+IF($C$32=R13,$G$32,0)+IF($C$33=R13,$G$33,0)+IF($C$34=R13,$G$34)+IF($C$35=R13,$G$35,0)+IF($C$36=R13,$G$36,0)+IF($C$37=R13,$G$37,0)+IF($C$38=R13,$G$38,0)+IF($C$39=R13,$G$39,0)+IF($C$40=R13,$G$40,0)+IF($C$41=R13,$G$41,0)+IF($C$42=R13,$G$42,0)+IF($C$43=R13,$G$43,0)+IF($C$44=R13,$G$44,0)+IF($C$45=R13,$G$45,0)+IF($C$46=R13,$G$46,0)+IF($C$47=R13,$G$47,0)+IF($C$48=R13,$G$48,0)+IF($C$49=R13,$G$49,0)+IF($C$50=R13,$G$50,0)+IF($C$51=R13,$G$51,0)+IF($C$52=R13,$G$52,0)+IF($C$53=R13,$G$53,0)+IF($C$54=R13,$G$54,0) -> 0
A14: Receive date | C14: 46163 | D14: 46177 | E14: 46199 | I14: ='Input''s from BD(Sales)'!A91 -> 0 | M14: Anchoring permission for RCC | O14: ='Input''s from BD(Sales)'!B46 -> 0 | R14: Parking-Truck/Bus | S14: =IF($C$25=R14,$G$25,0)+IF($C$26=R14,$G$26,0)+IF($C$27=R14,$G$27,0)+IF($C$28=R14,$G$28,0)+IF($C$29=R14,$G$29)+IF($C$30=R14,$G$30,0)+IF($C$31=R14,$G$31,0)+IF($C$32=R14,$G$32,0)+IF($C$33=R14,$G$33,0)+IF($C$34=R14,$G$34)+IF($C$35=R14,$G$35,0)+IF($C$36=R14,$G$36,0)+IF($C$37=R14,$G$37,0)+IF($C$38=R14,$G$38,0)+IF($C$39=R14,$G$39,0)+IF($C$40=R14,$G$40,0)+IF($C$41=R14,$G$41,0)+IF($C$42=R14,$G$42,0)+IF($C$43=R14,$G$43,0)+IF($C$44=R14,$G$44,0)+IF($C$45=R14,$G$45,0)+IF($C$46=R14,$G$46,0)+IF($C$47=R14,$G$47,0)+IF($C$48=R14,$G$48,0)+IF($C$49=R14,$G$49,0)+IF($C$50=R14,$G$50,0)+IF($C$51=R14,$G$51,0)+IF($C$52=R14,$G$52,0)+IF($C$53=R14,$G$53,0)+IF($C$54=R14,$G$54,0) -> 0
A15: Reason for Revision | C15: Initial Design | D15: Capacity increased | E15: AS per client reuirement layout revised | M15: PV Syst | O15: ='Input''s from BD(Sales)'!B47 -> 0 | R15: Floating | S15: =IF($C$25=R15,$G$25,0)+IF($C$26=R15,$G$26,0)+IF($C$27=R15,$G$27,0)+IF($C$28=R15,$G$28,0)+IF($C$29=R15,$G$29)+IF($C$30=R15,$G$30,0)+IF($C$31=R15,$G$31,0)+IF($C$32=R15,$G$32,0)+IF($C$33=R15,$G$33,0)+IF($C$34=R15,$G$34)+IF($C$35=R15,$G$35,0)+IF($C$36=R15,$G$36,0)+IF($C$37=R15,$G$37,0)+IF($C$38=R15,$G$38,0)+IF($C$39=R15,$G$39,0)+IF($C$40=R15,$G$40,0)+IF($C$41=R15,$G$41,0)+IF($C$42=R15,$G$42,0)+IF($C$43=R15,$G$43,0)+IF($C$44=R15,$G$44,0)+IF($C$45=R15,$G$45,0)+IF($C$46=R15,$G$46,0)+IF($C$47=R15,$G$47,0)+IF($C$48=R15,$G$48,0)+IF($C$49=R15,$G$49,0)+IF($C$50=R15,$G$50,0)+IF($C$51=R15,$G$51,0)+IF($C$52=R15,$G$52,0)+IF($C$53=R15,$G$53,0)+IF($C$54=R15,$G$54,0) -> 0
R16: Total Capacity | S16: =SUM(S8:S15) -> 400.52
A17: Date of Sent | C17: 46164 | D17: 46177 | E17: 46199
S19: Inverter Over loading indication | V19: NIL | W19: 0 to 1 | X19: 1 to 1.25
D20: =IF('Site Vist fomat (Design)'!B26=0,"Please fill number of service connections in Site Visit sheet","") | V20: 1.25-1.4 | W20: 1.4-1.45 | X20: Above 1.45
A21: String Inverter Initial Design | D21: Module Make & Origin | F21: Renewsys | G21: Indian ALMM | H21: =IF(F21=0,"Please fill Module Wp details","") | K21: =IF(G21=0,"Please fill Module Make details","") | L21: Select the Optimazer Model for Solar edge inverter | O21: Optimizers- Model-S 1400/ S 1500 | S21: Module Tilt | V21: < 5 | W21: < 8 | X21: > 8 | Z21: Click to check the Earth strip selection | AG21: =IF('Input''s from BD(Sales)'!B10='Input''s from BD(Sales)'!A298,"Consider Conventional LA for Tamilnadu"," ") | AJ21: =IF(OR('Input''s from BD(Sales)'!B10='Input''s from BD(Sales)'!A282,'Input''s from BD(Sales)'!B10='Input''s from BD(Sales)'!A298),"Railings are mandate for Tamilnadu/Haryana","Consider Railings for Module tilt >=8") -> Consider Railings for Module tilt >=8
D22: Module Wattage | F22: 620 | G22: Wp
A23: Sl.No | B23: Building/Location Name | C23: Type of Installation | D23: Type of sheet | E23: Available Modules | F23: No. of Modules Utilized | G23: DC Capacity in kWp | H23: Solis | R23: AC Capacity in kW | S23: Inverter Overloading DC/AC Ratio | V23: Common item for Rooftop and Ground mounted | AP23: For Rooftop site's | BB23: For Ground Mounted Site's
H24: =IF($H$23=$D$512,F512,IF($H$23=$D$514,F514,IF($H$23=$D$516,F516,IF($H$23=$D$518,F518,IF($H$23=$D$520,F520,IF($H$23=$D$522,F522,IF($H$23=$D$524,F524,IF($H$23=$D$526,F526,IF($H$23=$D$528,F528,IF($H$23=$D$530,F530,IF($H$23=$D$532,F532,IF($H$23=$D$534,F534,IF($H$23=$D$536,F536,""))))))))))))) -> 150 | I24: =IF($H$23=$D$512,G512,IF($H$23=$D$514,G514,IF($H$23=$D$516,G516,IF($H$23=$D$518,G518,IF($H$23=$D$520,G520,IF($H$23=$D$522,G522,IF($H$23=$D$524,G524,IF($H$23=$D$526,G526,IF($H$23=$D$528,G528,IF($H$23=$D$530,G530,IF($H$23=$D$532,G532,IF($H$23=$D$534,G534,IF($H$23=$D$536,G536,""))))))))))))) -> 125 | J24: =IF($H$23=$D$512,H512,IF($H$23=$D$514,H514,IF($H$23=$D$516,H516,IF($H$23=$D$518,H518,IF($H$23=$D$520,H520,IF($H$23=$D$522,H522,IF($H$23=$D$524,H524,IF($H$23=$D$526,H526,IF($H$23=$D$528,H528,IF($H$23=$D$530,H530,IF($H$23=$D$532,H532,IF($H$23=$D$534,H534,IF($H$23=$D$536,H536,""))))))))))))) -> 80 | K24: =IF($H$23=$D$512,I512,IF($H$23=$D$514,I514,IF($H$23=$D$516,I516,IF($H$23=$D$518,I518,IF($H$23=$D$520,I520,IF($H$23=$D$522,I522,IF($H$23=$D$524,I524,IF($H$23=$D$526,I526,IF($H$23=$D$528,I528,IF($H$23=$D$530,I530,IF($H$23=$D$532,I532,IF($H$23=$D$534,I534,IF($H$23=$D$536,I536,""))))))))))))) -> 60 | L24: =IF($H$23=$D$512,J512,IF($H$23=$D$514,J514,IF($H$23=$D$516,J516,IF($H$23=$D$518,J518,IF($H$23=$D$520,J520,IF($H$23=$D$522,J522,IF($H$23=$D$524,J524,IF($H$23=$D$526,J526,IF($H$23=$D$528,J528,IF($H$23=$D$530,J530,IF($H$23=$D$532,J532,IF($H$23=$D$534,J534,IF($H$23=$D$536,J536,""))))))))))))) -> 50 | M24: =IF($H$23=$D$512,K512,IF($H$23=$D$514,K514,IF($H$23=$D$516,K516,IF($H$23=$D$518,K518,IF($H$23=$D$520,K520,IF($H$23=$D$522,K522,IF($H$23=$D$524,K524,IF($H$23=$D$526,K526,IF($H$23=$D$528,K528,IF($H$23=$D$530,K530,IF($H$23=$D$532,K532,IF($H$23=$D$534,K534,IF($H$23=$D$536,K536,""))))))))))))) -> 30 | N24: =IF($H$23=$D$512,L512,IF($H$23=$D$514,L514,IF($H$23=$D$516,L516,IF($H$23=$D$518,L518,IF($H$23=$D$520,L520,IF($H$23=$D$522,L522,IF($H$23=$D$524,L524,IF($H$23=$D$526,L526,IF($H$23=$D$528,L528,IF($H$23=$D$530,L530,IF($H$23=$D$532,L532,IF($H$23=$D$534,L534,IF($H$23=$D$536,L536,""))))))))))))) -> 25 | O24: =IF($H$23=$D$512,M512,IF($H$23=$D$514,M514,IF($H$23=$D$516,M516,IF($H$23=$D$518,M518,IF($H$23=$D$520,M520,IF($H$23=$D$522,M522,IF($H$23=$D$524,M524,IF($H$23=$D$526,M526,IF($H$23=$D$528,M528,IF($H$23=$D$530,M530,IF($H$23=$D$532,M532,IF($H$23=$D$534,M534,IF($H$23=$D$536,M536,""))))))))))))) -> 20 | ... Q24: =IF($H$23=$D$512,O512,IF($H$23=$D$514,O514,IF($H$23=$D$516,O516,IF($H$23=$D$518,O518,IF($H$23=$D$520,O520,IF($H$23=$D$522,O522,IF($H$23=$D$524,O524,IF($H$23=$D$526,O526,IF($H$23=$D$528,O528,IF($H$23=$D$530,O530,IF($H$23=$D$532,O532,IF($H$23=$D$534,O534,IF($H$23=$D$536,O536,""))))))))))))) -> 10 | V24: Total No. of strings | W24: Module Tilt in Degree | X24: Structure clearance in mm | Y24: Earth strip Length in Mtrs (MMS) | Z24: Earth strip size (MMS) | AA24: Earth strip Length in Mtrs (INV) | AB24: Earth strip size (INV) | AC24: Earth strip Length in Mtrs (ACCB PANEL) | AD24: Earth strip size (ACCB PANEL) | AE24: Earth strip Length in Mtrs (LA) | AF24: Earth strip size (LA) | AG24: Type of Lightening Arrestor | AH24: No. of LA's (Qty.) | AI24: Water pipe line in Mtrs | AJ24: Walkway in Mtrs | AK24: Railings in Mtrs | AL24: Lifeline Rope in Rmtrs | AM24: No. of Lifeline Post (Qty.) | AN24: DC Cable Length in Mtrs 4 Sqmm | AO24: DC Cable Length in Mtrs 6 Sqmm | AP24: DC cable tray length in Mtrs 50x50x2mm | AQ24: DC cable tray length in Mtrs 100x50x2mm | AR24: Zero Degree Walkways in Mtrs | AS24: Step Walkway in Mtrs | AT24: Gutter length for harvesting in Mtrs | AU24: Skylight Width in mm | AV24: Skylight Length in Run. Mtrs | AW24: Turbo Vent Qty. | AX24: Roof monitor cross over (Qty.) | AY24: Ladder for Roof to roof Height in Mtrs | AZ24: Type of Ladder | BA24: Building Height in Mtrs | BB24: Total Plant Area in Acrs | BC24: DWC pipe for DC cable in Mtrs | BD24: Approach Road in Mtrs | BE24: Internal Road in Mtrs | BF24: Strom Water Drainage in Mtrs | BG24: Peripheral Length in Mtrs | BH24: Peripheral Road in Mtrs
A25: 1 | B25: Main RCC B Block at LG South side | C25: RCC Raised | E25: =(3*15+2*12)*2+(254*2) -> 646 | F25: =((21*4+3*18)+(9*19+5*21)+(8*19+4*20)) -> 646 | G25: =IF(C25<>0,F25*$F$22/1000,0) -> 400.52 | H25: 2 | R25: =IF(F25<>0,H25*$H$24+I25*$I$24+J25*$J$24+K25*$K$24+L25*$L$24+$M$24*M25+N25*$N$24+$O$24*O25+$P$24*P25+$Q$24*Q25,0) -> 300 | S25: =G25/R25 -> 1.3350667 | V25: 33 | W25: 5 | X25: =_xlfn.XLOOKUP(C25,$O$124:$O$132,$P$124:$P$132," ") -> 3000 mm | Y25: =(18*2+30+40)+(50*2+70+80)+((17*2)*4)*2+16*2+40*2-100 -> 640 | Z25: 25x3mm | AA25: =(50+25+15+16+40)*2+(2*5*2)-50 -> 262 | AB25: 25x3mm | AC25: =(20+16+25)*2 -> 122 | AD25: 25x3mm | AE25: =(5+20+35)*2 -> 120 | AF25: 25x6mm | AG25: ESE 107 Mtrs Radius | AH25: 1 | AI25: =(25+18+15+4)+(40+10+20)+(80+40+18+15*2+45*2+4*2)+(60)-50 -> 408 | AJ25: =(40*2+15*2+45*2+18+65)+(22*2+18+30)-25 -> 350 | AK25: 0 | AL25: =(40*2+15*2+45*2+18+65)+(22*2+18+30)-25 -> 350 | AM25: =(5*2+3*2+6*2+3+8)+(3*2+3+4)-1 -> 51 | AN25: =33*60*2*1.1-306 -> 4050 | AO25: 0 | AP25: =(40+15+15+40)*2+(40+25)*2 -> 350 | AQ25: 0 | BA25: =IF(OR(C25=R$7,C25=R$8,C25=R$9,C25=R$10,C25=R$11),'Site Vist fomat (Design)'!B$64,0) -> 0 | BF25: =BE25*2 -> 0
A26: =A25+1 -> 2 | B26: LT Panel - 2 | G26: =IF(C26<>0,F26*$F$22/1000,0) -> 0 | R26: =IF(F26<>0,H26*$H$24+I26*$I$24+J26*$J$24+K26*$K$24+L26*$L$24+$M$24*M26+N26*$N$24+$O$24*O26+$P$24*P26+$Q$24*Q26,0) -> 0 | S26: =G26/R26 -> #DIV/0! | X26: =_xlfn.XLOOKUP(C26,$O$124:$O$132,$P$124:$P$132," ") | BA26: =IF(OR(C26=R$7,C26=R$8,C26=R$9,C26=R$10,C26=R$11),'Site Vist fomat (Design)'!C$64,0) -> 0 | BF26: =BE26*2 -> 0
A27: =A26+1 -> 3 | G27: =IF(C27<>0,F27*$F$22/1000,0) -> 0 | R27: =IF(F27<>0,H27*$H$24+I27*$I$24+J27*$J$24+K27*$K$24+L27*$L$24+$M$24*M27+N27*$N$24+$O$24*O27+$P$24*P27+$Q$24*Q27,0) -> 0 | S27: =G27/R27 -> #DIV/0! | X27: =_xlfn.XLOOKUP(C27,$O$124:$O$132,$P$124:$P$132," ") | BA27: =IF(OR(C27=R$7,C27=R$8,C27=R$9,C27=R$10,C27=R$11),'Site Vist fomat (Design)'!D$64,0) -> 0 | BF27: =BE27*2 -> 0
A28: =A27+1 -> 4 | G28: =IF(C28<>0,F28*$F$22/1000,0) -> 0 | R28: =IF(F28<>0,H28*$H$24+I28*$I$24+J28*$J$24+K28*$K$24+L28*$L$24+$M$24*M28+N28*$N$24+$O$24*O28+$P$24*P28+$Q$24*Q28,0) -> 0 | S28: =G28/R28 -> #DIV/0! | X28: =_xlfn.XLOOKUP(C28,$O$124:$O$132,$P$124:$P$132," ") | BA28: =IF(OR(C28=R$7,C28=R$8,C28=R$9,C28=R$10,C28=R$11),'Site Vist fomat (Design)'!E$64,0) -> 0 | BF28: =BE28*2 -> 0
A29: =A28+1 -> 5 | G29: =IF(C29<>0,F29*$F$22/1000,0) -> 0 | R29: =IF(F29<>0,H29*$H$24+I29*$I$24+J29*$J$24+K29*$K$24+L29*$L$24+$M$24*M29+N29*$N$24+$O$24*O29+$P$24*P29+$Q$24*Q29,0) -> 0 | S29: =G29/R29 -> #DIV/0! | X29: =_xlfn.XLOOKUP(C29,$O$124:$O$132,$P$124:$P$132," ") | BA29: =IF(OR(C29=R$7,C29=R$8,C29=R$9,C29=R$10,C29=R$11),'Site Vist fomat (Design)'!F$64,0) -> 0 | BF29: =BE29*2 -> 0
A30: =A29+1 -> 6 | G30: =IF(C30<>0,F30*$F$22/1000,0) -> 0 | R30: =IF(F30<>0,H30*$H$24+I30*$I$24+J30*$J$24+K30*$K$24+L30*$L$24+$M$24*M30+N30*$N$24+$O$24*O30+$P$24*P30+$Q$24*Q30,0) -> 0 | S30: =G30/R30 -> #DIV/0! | X30: =_xlfn.XLOOKUP(C30,$O$124:$O$132,$P$124:$P$132," ") | BA30: =IF(OR(C30=R$7,C30=R$8,C30=R$9,C30=R$10,C30=R$11),'Site Vist fomat (Design)'!G$64,0) -> 0 | BF30: =BE30*2 -> 0
A31: =A30+1 -> 7 | G31: =IF(C31<>0,F31*$F$22/1000,0) -> 0 | R31: =IF(F31<>0,H31*$H$24+I31*$I$24+J31*$J$24+K31*$K$24+L31*$L$24+$M$24*M31+N31*$N$24+$O$24*O31+$P$24*P31+$Q$24*Q31,0) -> 0 | S31: =G31/R31 -> #DIV/0! | X31: =_xlfn.XLOOKUP(C31,$O$124:$O$132,$P$124:$P$132," ") | BA31: =IF(OR(C31=R$7,C31=R$8,C31=R$9,C31=R$10,C31=R$11),'Site Vist fomat (Design)'!H$64,0) -> 0 | BF31: =BE31*2 -> 0
A32: =A31+1 -> 8 | G32: =IF(C32<>0,F32*$F$22/1000,0) -> 0 | R32: =IF(F32<>0,H32*$H$24+I32*$I$24+J32*$J$24+K32*$K$24+L32*$L$24+$M$24*M32+N32*$N$24+$O$24*O32+$P$24*P32+$Q$24*Q32,0) -> 0 | S32: =G32/R32 -> #DIV/0! | X32: =_xlfn.XLOOKUP(C32,$O$124:$O$132,$P$124:$P$132," ") | BA32: =IF(OR(C32=R$7,C32=R$8,C32=R$9,C32=R$10,C32=R$11),'Site Vist fomat (Design)'!I$64,0) -> 0 | BF32: =BE32*2 -> 0
A33: =A32+1 -> 9 | G33: =IF(C33<>0,F33*$F$22/1000,0) -> 0 | R33: =IF(F33<>0,H33*$H$24+I33*$I$24+J33*$J$24+K33*$K$24+L33*$L$24+$M$24*M33+N33*$N$24+$O$24*O33+$P$24*P33+$Q$24*Q33,0) -> 0 | S33: =G33/R33 -> #DIV/0! | X33: =_xlfn.XLOOKUP(C33,$O$124:$O$132,$P$124:$P$132," ") | BA33: =IF(OR(C33=R$7,C33=R$8,C33=R$9,C33=R$10,C33=R$11),'Site Vist fomat (Design)'!J$64,0) -> 0 | BF33: =BE33*2 -> 0
A34: =A33+1 -> 10 | G34: =IF(C34<>0,F34*$F$22/1000,0) -> 0 | R34: =IF(F34<>0,H34*$H$24+I34*$I$24+J34*$J$24+K34*$K$24+L34*$L$24+$M$24*M34+N34*$N$24+$O$24*O34+$P$24*P34+$Q$24*Q34,0) -> 0 | S34: =G34/R34 -> #DIV/0! | X34: =_xlfn.XLOOKUP(C34,$O$124:$O$132,$P$124:$P$132," ") | BA34: =IF(OR(C34=R$7,C34=R$8,C34=R$9,C34=R$10,C34=R$11),'Site Vist fomat (Design)'!K$64,0) -> 0 | BF34: =BE34*2 -> 0
A35: =A34+1 -> 11 | G35: =IF(C35<>0,F35*$F$22/1000,0) -> 0 | R35: =IF(F35<>0,H35*$H$24+I35*$I$24+J35*$J$24+K35*$K$24+L35*$L$24+$M$24*M35+N35*$N$24+$O$24*O35+$P$24*P35+$Q$24*Q35,0) -> 0 | S35: =G35/R35 -> #DIV/0! | X35: =_xlfn.XLOOKUP(C35,$O$124:$O$132,$P$124:$P$132," ") | BA35: =IF(OR(C35=R$7,C35=R$8,C35=R$9,C35=R$10,C35=R$11),'Site Vist fomat (Design)'!L$64,0) -> 0 | BF35: =BE35*2 -> 0
A36: =A35+1 -> 12 | G36: =IF(C36<>0,F36*$F$22/1000,0) -> 0 | R36: =IF(F36<>0,H36*$H$24+I36*$I$24+J36*$J$24+K36*$K$24+L36*$L$24+$M$24*M36+N36*$N$24+$O$24*O36+$P$24*P36+$Q$24*Q36,0) -> 0 | S36: =G36/R36 -> #DIV/0! | X36: =_xlfn.XLOOKUP(C36,$O$124:$O$132,$P$124:$P$132," ") | BA36: =IF(OR(C36=R$7,C36=R$8,C36=R$9,C36=R$10,C36=R$11),'Site Vist fomat (Design)'!M$64,0) -> 0 | BF36: =BE36*2 -> 0
A37: =A36+1 -> 13 | G37: =IF(C37<>0,F37*$F$22/1000,0) -> 0 | R37: =IF(F37<>0,H37*$H$24+I37*$I$24+J37*$J$24+K37*$K$24+L37*$L$24+$M$24*M37+N37*$N$24+$O$24*O37+$P$24*P37+$Q$24*Q37,0) -> 0 | S37: =G37/R37 -> #DIV/0! | X37: =_xlfn.XLOOKUP(C37,$O$124:$O$132,$P$124:$P$132," ") | BA37: =IF(OR(C37=R$7,C37=R$8,C37=R$9,C37=R$10,C37=R$11),'Site Vist fomat (Design)'!N$64,0) -> 0 | BF37: =BE37*2 -> 0
A38: =A37+1 -> 14 | G38: =IF(C38<>0,F38*$F$22/1000,0) -> 0 | R38: =IF(F38<>0,H38*$H$24+I38*$I$24+J38*$J$24+K38*$K$24+L38*$L$24+$M$24*M38+N38*$N$24+$O$24*O38+$P$24*P38+$Q$24*Q38,0) -> 0 | S38: =G38/R38 -> #DIV/0! | X38: =_xlfn.XLOOKUP(C38,$O$124:$O$132,$P$124:$P$132," ") | BA38: =IF(OR(C38=R$7,C38=R$8,C38=R$9,C38=R$10,C38=R$11),'Site Vist fomat (Design)'!O$64,0) -> 0 | BF38: =BE38*2 -> 0
A39: =A38+1 -> 15 | G39: =IF(C39<>0,F39*$F$22/1000,0) -> 0 | R39: =IF(F39<>0,H39*$H$24+I39*$I$24+J39*$J$24+K39*$K$24+L39*$L$24+$M$24*M39+N39*$N$24+$O$24*O39+$P$24*P39+$Q$24*Q39,0) -> 0 | S39: =G39/R39 -> #DIV/0! | X39: =_xlfn.XLOOKUP(C39,$O$124:$O$132,$P$124:$P$132," ") | BA39: =IF(OR(C39=R$7,C39=R$8,C39=R$9,C39=R$10,C39=R$11),'Site Vist fomat (Design)'!P$64,0) -> 0 | BF39: =BE39*2 -> 0
A40: =A39+1 -> 16 | G40: =IF(C40<>0,F40*$F$22/1000,0) -> 0 | R40: =IF(F40<>0,H40*$H$24+I40*$I$24+J40*$J$24+K40*$K$24+L40*$L$24+$M$24*M40+N40*$N$24+$O$24*O40+$P$24*P40+$Q$24*Q40,0) -> 0 | S40: =G40/R40 -> #DIV/0! | X40: =_xlfn.XLOOKUP(C40,$O$124:$O$132,$P$124:$P$132," ") | BA40: =IF(OR(C40=R$7,C40=R$8,C40=R$9,C40=R$10,C40=R$11),'Site Vist fomat (Design)'!Q$64,0) -> 0 | BF40: =BE40*2 -> 0
A41: =A40+1 -> 17 | G41: =IF(C41<>0,F41*$F$22/1000,0) -> 0 | R41: =IF(F41<>0,H41*$H$24+I41*$I$24+J41*$J$24+K41*$K$24+L41*$L$24+$M$24*M41+N41*$N$24+$O$24*O41+$P$24*P41+$Q$24*Q41,0) -> 0 | S41: =G41/R41 -> #DIV/0! | X41: =_xlfn.XLOOKUP(C41,$O$124:$O$132,$P$124:$P$132," ") | BA41: =IF(OR(C41=R$7,C41=R$8,C41=R$9,C41=R$10,C41=R$11),'Site Vist fomat (Design)'!R$64,0) -> 0 | BF41: =BE41*2 -> 0
A42: =A41+1 -> 18 | G42: =IF(C42<>0,F42*$F$22/1000,0) -> 0 | R42: =IF(F42<>0,H42*$H$24+I42*$I$24+J42*$J$24+K42*$K$24+L42*$L$24+$M$24*M42+N42*$N$24+$O$24*O42+$P$24*P42+$Q$24*Q42,0) -> 0 | S42: =G42/R42 -> #DIV/0! | X42: =_xlfn.XLOOKUP(C42,$O$124:$O$132,$P$124:$P$132," ") | BA42: =IF(OR(C42=R$7,C42=R$8,C42=R$9,C42=R$10,C42=R$11),'Site Vist fomat (Design)'!S$64,0) -> 0 | BF42: =BE42*2 -> 0
A43: =A42+1 -> 19 | G43: =IF(C43<>0,F43*$F$22/1000,0) -> 0 | R43: =IF(F43<>0,H43*$H$24+I43*$I$24+J43*$J$24+K43*$K$24+L43*$L$24+$M$24*M43+N43*$N$24+$O$24*O43+$P$24*P43+$Q$24*Q43,0) -> 0 | S43: =G43/R43 -> #DIV/0! | X43: =_xlfn.XLOOKUP(C43,$O$124:$O$132,$P$124:$P$132," ") | BA43: =IF(OR(C43=R$7,C43=R$8,C43=R$9,C43=R$10,C43=R$11),'Site Vist fomat (Design)'!T$64,0) -> 0 | BF43: =BE43*2 -> 0
A44: =A43+1 -> 20 | G44: =IF(C44<>0,F44*$F$22/1000,0) -> 0 | R44: =IF(F44<>0,H44*$H$24+I44*$I$24+J44*$J$24+K44*$K$24+L44*$L$24+$M$24*M44+N44*$N$24+$O$24*O44+$P$24*P44+$Q$24*Q44,0) -> 0 | S44: =G44/R44 -> #DIV/0! | X44: =_xlfn.XLOOKUP(C44,$O$124:$O$132,$P$124:$P$132," ") | BA44: =IF(OR(C44=R$7,C44=R$8,C44=R$9,C44=R$10,C44=R$11),'Site Vist fomat (Design)'!U$64,0) -> 0 | BF44: =BE44*2 -> 0
A45: =A44+1 -> 21 | G45: =IF(C45<>0,F45*$F$22/1000,0) -> 0 | R45: =IF(F45<>0,H45*$H$24+I45*$I$24+J45*$J$24+K45*$K$24+L45*$L$24+$M$24*M45+N45*$N$24+$O$24*O45+$P$24*P45+$Q$24*Q45,0) -> 0 | S45: =G45/R45 -> #DIV/0! | X45: =_xlfn.XLOOKUP(C45,$O$124:$O$132,$P$124:$P$132," ") | BA45: =IF(OR(C45=R$7,C45=R$8,C45=R$9,C45=R$10,C45=R$11),'Site Vist fomat (Design)'!V$64,0) -> 0 | BF45: =BE45*2 -> 0
A46: =A45+1 -> 22 | G46: =IF(C46<>0,F46*$F$22/1000,0) -> 0 | R46: =IF(F46<>0,H46*$H$24+I46*$I$24+J46*$J$24+K46*$K$24+L46*$L$24+$M$24*M46+N46*$N$24+$O$24*O46+$P$24*P46+$Q$24*Q46,0) -> 0 | S46: =G46/R46 -> #DIV/0! | X46: =_xlfn.XLOOKUP(C46,$O$124:$O$132,$P$124:$P$132," ") | BA46: =IF(OR(C46=R$7,C46=R$8,C46=R$9,C46=R$10,C46=R$11),'Site Vist fomat (Design)'!W$64,0) -> 0 | BF46: =BE46*2 -> 0
A47: =A46+1 -> 23 | G47: =IF(C47<>0,F47*$F$22/1000,0) -> 0 | R47: =IF(F47<>0,H47*$H$24+I47*$I$24+J47*$J$24+K47*$K$24+L47*$L$24+$M$24*M47+N47*$N$24+$O$24*O47+$P$24*P47+$Q$24*Q47,0) -> 0 | S47: =G47/R47 -> #DIV/0! | X47: =_xlfn.XLOOKUP(C47,$O$124:$O$132,$P$124:$P$132," ") | BA47: =IF(OR(C47=R$7,C47=R$8,C47=R$9,C47=R$10,C47=R$11),'Site Vist fomat (Design)'!X$64,0) -> 0 | BF47: =BE47*2 -> 0
A48: =A47+1 -> 24 | G48: =IF(C48<>0,F48*$F$22/1000,0) -> 0 | R48: =IF(F48<>0,H48*$H$24+I48*$I$24+J48*$J$24+K48*$K$24+L48*$L$24+$M$24*M48+N48*$N$24+$O$24*O48+$P$24*P48+$Q$24*Q48,0) -> 0 | S48: =G48/R48 -> #DIV/0! | X48: =_xlfn.XLOOKUP(C48,$O$124:$O$132,$P$124:$P$132," ") | BA48: =IF(OR(C48=R$7,C48=R$8,C48=R$9,C48=R$10,C48=R$11),'Site Vist fomat (Design)'!Y$64,0) -> 0 | BF48: =BE48*2 -> 0
A49: =A48+1 -> 25 | G49: =IF(C49<>0,F49*$F$22/1000,0) -> 0 | R49: =IF(F49<>0,H49*$H$24+I49*$I$24+J49*$J$24+K49*$K$24+L49*$L$24+$M$24*M49+N49*$N$24+$O$24*O49+$P$24*P49+$Q$24*Q49,0) -> 0 | S49: =G49/R49 -> #DIV/0! | X49: =_xlfn.XLOOKUP(C49,$O$124:$O$132,$P$124:$P$132," ") | BA49: =IF(OR(C49=R$7,C49=R$8,C49=R$9,C49=R$10,C49=R$11),'Site Vist fomat (Design)'!Z$64,0) -> 0 | BF49: =BE49*2 -> 0
A50: =A49+1 -> 26 | G50: =IF(C50<>0,F50*$F$22/1000,0) -> 0 | R50: =IF(F50<>0,H50*$H$24+I50*$I$24+J50*$J$24+K50*$K$24+L50*$L$24+$M$24*M50+N50*$N$24+$O$24*O50+$P$24*P50+$Q$24*Q50,0) -> 0 | S50: =G50/R50 -> #DIV/0! | X50: =_xlfn.XLOOKUP(C50,$O$124:$O$132,$P$124:$P$132," ") | BA50: =IF(OR(C50=R$7,C50=R$8,C50=R$9,C50=R$10,C50=R$11),'Site Vist fomat (Design)'!AA$64,0) -> 0 | BF50: =BE50*2 -> 0
A51: =A50+1 -> 27 | G51: =IF(C51<>0,F51*$F$22/1000,0) -> 0 | R51: =IF(F51<>0,H51*$H$24+I51*$I$24+J51*$J$24+K51*$K$24+L51*$L$24+$M$24*M51+N51*$N$24+$O$24*O51+$P$24*P51+$Q$24*Q51,0) -> 0 | S51: =G51/R51 -> #DIV/0! | X51: =_xlfn.XLOOKUP(C51,$O$124:$O$132,$P$124:$P$132," ") | BA51: =IF(OR(C51=R$7,C51=R$8,C51=R$9,C51=R$10,C51=R$11),'Site Vist fomat (Design)'!AB$64,0) -> 0 | BF51: =BE51*2 -> 0
A52: =A51+1 -> 28 | G52: =IF(C52<>0,F52*$F$22/1000,0) -> 0 | R52: =IF(F52<>0,H52*$H$24+I52*$I$24+J52*$J$24+K52*$K$24+L52*$L$24+$M$24*M52+N52*$N$24+$O$24*O52+$P$24*P52+$Q$24*Q52,0) -> 0 | S52: =G52/R52 -> #DIV/0! | X52: =_xlfn.XLOOKUP(C52,$O$124:$O$132,$P$124:$P$132," ") | BA52: =IF(OR(C52=R$7,C52=R$8,C52=R$9,C52=R$10,C52=R$11),'Site Vist fomat (Design)'!AC$64,0) -> 0 | BF52: =BE52*2 -> 0
A53: =A52+1 -> 29 | G53: =IF(C53<>0,F53*$F$22/1000,0) -> 0 | R53: =IF(F53<>0,H53*$H$24+I53*$I$24+J53*$J$24+K53*$K$24+L53*$L$24+$M$24*M53+N53*$N$24+$O$24*O53+$P$24*P53+$Q$24*Q53,0) -> 0 | S53: =G53/R53 -> #DIV/0! | X53: =_xlfn.XLOOKUP(C53,$O$124:$O$132,$P$124:$P$132," ") | BA53: =IF(OR(C53=R$7,C53=R$8,C53=R$9,C53=R$10,C53=R$11),'Site Vist fomat (Design)'!AD$64,0) -> 0 | BF53: =BE53*2 -> 0
A54: =A53+1 -> 30 | G54: =IF(C54<>0,F54*$F$22/1000,0) -> 0 | R54: =IF(F54<>0,H54*$H$24+I54*$I$24+J54*$J$24+K54*$K$24+L54*$L$24+$M$24*M54+N54*$N$24+$O$24*O54+$P$24*P54+$Q$24*Q54,0) -> 0 | S54: =G54/R54 -> #DIV/0! | X54: =_xlfn.XLOOKUP(C54,$O$124:$O$132,$P$124:$P$132," ") | BA54: =IF(OR(C54=R$7,C54=R$8,C54=R$9,C54=R$10,C54=R$11),'Site Vist fomat (Design)'!AE$64,0) -> 0 | BF54: =BE54*2 -> 0
A55: Total | E55: =SUM(E25:E54) -> 646 | F55: =SUM(F25:F54) -> 646 | G55: =SUM(G25:G54) -> 400.52 | H55: {=IF(H24>0, SUMPRODUCT(($F$25:$F$54>0)*H25:H54), 0)} -> 2 | I55: {=IF(I24>0, SUMPRODUCT(($F$25:$F$54>0)*I25:I54), 0)} -> 0 | J55: {=IF(J24>0, SUMPRODUCT(($F$25:$F$54>0)*J25:J54), 0)} -> 0 | K55: {=IF(K24>0, SUMPRODUCT(($F$25:$F$54>0)*K25:K54), 0)} -> 0 | L55: {=IF(L24>0, SUMPRODUCT(($F$25:$F$54>0)*L25:L54), 0)} -> 0 | M55: {=IF(M24>0, SUMPRODUCT(($F$25:$F$54>0)*M25:M54), 0)} -> 0 | N55: {=IF(N24>0, SUMPRODUCT(($F$25:$F$54>0)*N25:N54), 0)} -> 0 | O55: {=IF(O24>0, SUMPRODUCT(($F$25:$F$54>0)*O25:O54), 0)} -> 0 | ... Q55: {=IF(Q24>0, SUMPRODUCT(($F$25:$F$54>0)*Q25:Q54), 0)} -> 0 | R55: =IF(G55<1,0,SUM(R25:R54)) -> 300 | S55: =G55/R55 -> 1.3350667 | V55: =SUM(V25:V54) -> 33 | AH55: =IF(AG25<>$Q$189,AH25,0)+IF(AG26<>$Q$189,AH26,0)+IF(AG27<>$Q$189,AH27,0)+IF(AG28<>$Q$189,AH28,0) +IF(AG29<>$Q$189,AH29,0) +IF(AG30<>$Q$189,AH30,0) +IF(AG31<>$Q$189,AH31,0) +IF(AG32<>$Q$189,AH32,0) +IF(AG33<>$Q$189,AH33,0) +IF(AG34<>$Q$189,AH34,0) +IF(AG35<>$Q$189,AH35,0) +IF(AG36<>$Q$189,AH36,0) +IF(AG37<>$Q$189,AH37,0) +IF(AG38<>$Q$189,AH38,0) +IF(AG39<>$Q$189,AH39,0) +IF(AG40<>$Q$189,AH40,0) +IF(AG41<>$Q$189,AH41,0) +IF(AG42<>$Q$189,AH42,0) +IF(AG43<>$Q$189,AH43,0) +IF(AG44<>$Q$189,AH44,0)+IF(AG45<>$Q$189,AH45,0)+IF(AG46<>$Q$189,AH46,0)+IF(AG47<>$Q$189,AH47,0)+IF(AG48<>$Q$189,AH48,0)+IF(AG49<>$Q$189,AH49,0)+IF(AG50<>$Q$189,AH50,0)+IF(AG51<>$Q$189,AH51,0)+IF(AG52<>$Q$189,AH52,0)+IF(AG53<>$Q$189,AH53,0)+IF(AG54<>$Q$189,AH54,0) -> 1 | AI55: =SUM(AI25:AI54) -> 408 | AJ55: {=SUMPRODUCT((($C$25:$C$54=$R$7)+($C$25:$C$54=$R$8)+($C$25:$C$54=$R$10)+($C$25:$C$54=$R$11)+($C$25:$C$54=$R$13)+($C$25:$C$54=$R$14))*(AJ25:AJ54))} -> 350 | AK55: {=SUMPRODUCT((($C$25:$C$54=$R$7)+($C$25:$C$54=$R$8)+($C$25:$C$54=$R$10)+($C$25:$C$54=$R$11)+($C$25:$C$54=$R$13)+($C$25:$C$54=$R$14))*(AK25:AK54))} -> 0 | AL55: {=SUMPRODUCT((($C$25:$C$54=$R$7)+($C$25:$C$54=$R$8)+($C$25:$C$54=$R$10)+($C$25:$C$54=$R$11)+($C$25:$C$54=$R$13)+($C$25:$C$54=$R$14))*(AL25:AL54))} -> 350 | AM55: {=SUMPRODUCT((($C$25:$C$54=$R$7)+($C$25:$C$54=$R$8)+($C$25:$C$54=$R$10)+($C$25:$C$54=$R$11)+($C$25:$C$54=$R$13)+($C$25:$C$54=$R$14))*(AM25:AM54))} -> 51 | AN55: =IF($G$55<1,0,SUM(AN25:AN54)) -> 4050 | AO55: =IF($G$55<1,0,SUM(AO25:AO54)) -> 0 | AP55: {=SUMPRODUCT((($C$25:$C$54=$R$7)+($C$25:$C$54=$R$8)+($C$25:$C$54=$R$9)+($C$25:$C$54=$R$10)+($C$25:$C$54=$R$11))*(AP25:AP54))} -> 350 | AQ55: {=SUMPRODUCT((($C$25:$C$54=$R$7)+($C$25:$C$54=$R$8)+($C$25:$C$54=$R$9)+($C$25:$C$54=$R$10)+($C$25:$C$54=$R$11))*(AQ25:AQ54))} -> 0 | AR55: {=SUMPRODUCT((($C$25:$C$54=$R$7)+($C$25:$C$54=$R$8))*(AR25:AR54))} -> 0 | AS55: {=SUMPRODUCT((($C$25:$C$54=$R$7)+($C$25:$C$54=$R$8))*(AS25:AS54))} -> 0 | AT55: {=SUMPRODUCT((($C$25:$C$54=$R$7)+($C$25:$C$54=$R$8))*(AT25:AT54))} -> 0 | AV55: {=SUMPRODUCT((($C$25:$C$54=$R$7)+($C$25:$C$54=$R$8))*(AV25:AV54))} -> 0 | AW55: {=SUMPRODUCT((($C$25:$C$54=$R$7)+($C$25:$C$54=$R$8))*(AW25:AW54))} -> 0 | AX55: {=SUMPRODUCT((($C$25:$C$54=$R$7)+($C$25:$C$54=$R$8))*(AX25:AX54))} -> 0 | AY55: {=SUMPRODUCT((($C$25:$C$54=$R$7)+($C$25:$C$54=$R$8))*(AY25:AY54))} -> 0 | BB55: {=SUMPRODUCT((($C$25:$C$54=$R$12)+($C$25:$C$54=$R$13)+($C$25:$C$54=$R$14)+($C$25:$C$54=$R$15))*(BB25:BB54))} -> 0 | BC55: {=SUMPRODUCT((($C$25:$C$54=$R$12)+($C$25:$C$54=$R$13)+($C$25:$C$54=$R$14)+($C$25:$C$54=$R$15))*(BC25:BC54))} -> 0 | BD55: {=SUMPRODUCT((($C$25:$C$54=$R$12)+($C$25:$C$54=$R$13)+($C$25:$C$54=$R$14)+($C$25:$C$54=$R$15))*(BD25:BD54))} -> 0 | BE55: {=SUMPRODUCT((($C$25:$C$54=$R$12)+($C$25:$C$54=$R$13)+($C$25:$C$54=$R$14)+($C$25:$C$54=$R$15))*(BE25:BE54))} -> 0 | BF55: {=SUMPRODUCT((($C$25:$C$54=$R$12)+($C$25:$C$54=$R$13)+($C$25:$C$54=$R$14)+($C$25:$C$54=$R$15))*(BF25:BF54))} -> 0 | BG55: {=SUMPRODUCT((($C$25:$C$54=$R$12)+($C$25:$C$54=$R$13)+($C$25:$C$54=$R$14)+($C$25:$C$54=$R$15))*(BG25:BG54))} -> 0 | BH55: {=SUMPRODUCT((($C$25:$C$54=$R$12)+($C$25:$C$54=$R$13)+($C$25:$C$54=$R$14)+($C$25:$C$54=$R$15))*(BH25:BH54))} -> 0
H56: Per Wp cost of Inverter | Q56: =F542 -> 1.4980525
T57: IN : | U57: 1 OUT
B58: AC cable length from INV. To ACCB Panel | U58: Inv count | V58: Inv. Combination (reference) | W58: AC Capacity in KW | X58: Termination Distance as per site survey report | Y58: No. of Runs | Z58: Total running mtrs. | AA58: Selected Cable Size | AB58: Cable transmission method | AH58: ACCB Panels Details
B59: =B23 -> Building/Location Name | C59: Distance/Runs/ Cable Size | D59: Inverter-1 | E59: Inverter-2 | F59: Inverter-3 | G59: Inverter-4 | H59: Inverter-5 | I59: Inverter-6 | J59: Inverter-7 | K59: Inverter-8 | L59: Inverter-9 | M59: Inverter-10 | N59: Inverter-11 | O59: Inverter-12 | P59: Inverter-13 | Q59: Inverter-14 | R59: Inverter-15 | S59: Cable tray From Inv. To ACCB Panel in mtrs | T59: LT combination count | AA59: Note: If no match pls increase runs | AB59: New cable tray in mtrs | AC59: Soil trench in mtrs | AD59: Road Crossing | AE59: Existing cable tray in mtrs | AF59: Cable Gantry in mtrs | AH59: Sl. No. | AI59: Name of the Locations (Building) | AJ59: Inv. Combination IN & OUT | AK59: ACCB Panel Capacity | AM59: ACCB Panel Current rating | AN59: ACCB Panel Quantity
B60: =B25 -> Main RCC B Block at LG South side | C60: Cable length in mtrs | D60: 10 | S60: 10 | T60: 1 | U60: =SUM(COUNT(_xlfn._xlws.FILTER($D$60:$R$60,$T$60))) -> 1 | V60: =_xlfn.CONCAT($U$60,$T$57,$U$57) -> 1 IN :1 OUT | W60: 150 | X60: ='Site Vist fomat (Design)'!B31 -> 170 | Y60: 1 | Z60: =IF(B60<>0,X60*Y60,0) -> 170 | AA60: =IF('Cable Calcualtion'!B20<>"NO MATCH","3.5CX"&'Cable Calcualtion'!B20&"Sqmm","NO MATCH") -> 3.5CX300Sqmm | AB60: 170 | AC60: 0 | AD60: 0 | AE60: 0 | AF60: 0 | AH60: 1 | AJ60: 1 IN : 1 OUT | AK60: 10/15/20/25/30/33/50/60/66KW | AM60: 15A-90A | AN60: 0
C61: Cable size in sqmm | D61: 3.5CX300Sqmm | S61: 100x75x2mm | AB61: 100x75x2mm | AH61: =AH60+1 -> 2 | AJ61: 2 IN : 1 OUT | AK61: 10/15/20/25/30/50/60/66KW | AM61: 15A-90A | AN61: 0
B62: =B26 -> LT Panel - 2 | C62: Cable length in mtrs | D62: 10 | S62: 10 | T62: 2 | U62: =SUM(COUNT(_xlfn._xlws.FILTER($D$62:$R$62,$T$62))) -> 1 | V62: =_xlfn.CONCAT($U$62,$T$57,$U$57) -> 1 IN :1 OUT | W62: 150 | X62: ='Site Vist fomat (Design)'!C31 -> 220 | Y62: 2 | Z62: =IF(B62<>0,X62*Y62,0) -> 440 | AA62: =IF('Cable Calcualtion'!B43<>"NO MATCH","3.5CX"&'Cable Calcualtion'!B43&"Sqmm","NO MATCH") -> 3.5CX185Sqmm | AB62: 220 | AC62: 0 | AD62: 0 | AE62: 0 | AF62: 0 | AH62: =AH61+1 -> 3 | AJ62: 3 IN : 1 OUT | AK62: 15/30/35/50/60/70/80/90/99KW | AM62: 25A-130A | AN62: 0
C63: Cable size in sqmm | D63: 3.5CX300Sqmm | S63: 100x75x2mm | AB63: 200x75x2mm | AH63: =AH62+1 -> 4 | AI63: Main RCC B Block at LG South side (2 in 1 out) | AJ63: 1 IN : 1 OUT | AK63: 80/125/150KW | AM63: 110A-155A | AN63: 2
B64: =B27 -> 0 | C64: Cable length in mtrs | T64: 3 | U64: =SUM(COUNT(_xlfn._xlws.FILTER(D64:R64,T64))) -> 0 | V64: =_xlfn.CONCAT($U$64,$T$57,$U$57) -> 0 IN :1 OUT | X64: ='Site Vist fomat (Design)'!D31 -> 200 | Z64: =IF(B64<>0,X64*Y64,0) -> 0 | AA64: =IF('Cable Calcualtion'!B65<>"NO MATCH","3.5CX"&'Cable Calcualtion'!B65&"Sqmm","NO MATCH") -> #DIV/0! | AH64: =AH63+1 -> 5 | AJ64: 2 IN : 1 OUT | AK64: 100/110/120KW | AL64: 100KW | AM64: 135A- 165A | AN64: 0
C65: Cable size in sqmm | AH65: =AH64+1 -> 6 | AJ65: 2 IN : 1 OUT | AK65: 110/120/130/133/150/160/170KW | AL65: 100KW | AM65: 155A- 230A | AN65: 0
B66: =B28 -> 0 | C66: Cable length in mtrs | T66: 4 | U66: =SUM(COUNT(_xlfn._xlws.FILTER(D66:R66,T66))) -> 0 | V66: =_xlfn.CONCAT($U$66,$T$57,$U$57) -> 0 IN :1 OUT | X66: ='Site Vist fomat (Design)'!E31 -> 0 | Z66: =IF(B66<>0,X66*Y66,0) -> 0 | AA66: =IF('Cable Calcualtion'!B87<>"NO MATCH","3.5CX"&'Cable Calcualtion'!B87&"Sqmm","NO MATCH") -> #DIV/0! | AH66: =AH65+1 -> 7 | AJ66: 2 IN : 1 OUT | AK66: 200-220KW | AL66: 150KW | AM66: 265A- 300A | AN66: 0
C67: Cable size in sqmm | AH67: =AH66+1 -> 8 | AJ67: 3 IN : 1 OUT | AK67: 250-270KW | AL67: 150KW | AM67: 330A- 370A | AN67: 0
B68: =B29 -> 0 | C68: Cable length in mtrs | T68: 5 | U68: =SUM(COUNT(_xlfn._xlws.FILTER(D68:R68,T68))) -> 0 | V68: =_xlfn.CONCAT($U$68,$T$57,$U$57) -> 0 IN :1 OUT | X68: ='Site Vist fomat (Design)'!F31 -> 0 | Z68: =IF(B68<>0,X68*Y68,0) -> 0 | AA68: =IF('Cable Calcualtion'!B111<>"NO MATCH","3.5CX"&'Cable Calcualtion'!B111&"Sqmm","NO MATCH") -> #DIV/0! | AH68: =AH67+1 -> 9 | AJ68: 3 IN : 1 OUT | AK68: 300-330KW | AL68: 150KW | AM68: 400A- 450A | AN68: 0
C69: Cable size in sqmm | AH69: =AH68+1 -> 10 | AJ69: 4 IN : 1 OUT | AK69: 330-370KW | AM69: 450A- 500A | AN69: 0
B70: =B30 -> 0 | C70: Cable length in mtrs | T70: 6 | U70: =SUM(COUNT(_xlfn._xlws.FILTER(D70:R70,T70))) -> 0 | V70: =_xlfn.CONCAT($U$70,$T$57,$U$57) -> 0 IN :1 OUT | X70: ='Site Vist fomat (Design)'!G31 -> 0 | Z70: =IF(B70<>0,X70*Y70,0) -> 0 | AA70: =IF('Cable Calcualtion'!B135<>"NO MATCH","3.5CX"&'Cable Calcualtion'!B135&"Sqmm","NO MATCH") -> #DIV/0! | AH70: =AH69+1 -> 11 | AJ70: 4 IN : 1 OUT | AK70: 400-440KW | AM70: 500A- 600A | AN70: 0
C71: Cable size in sqmm | AH71: =AH70+1 -> 12 | AJ71: 5 IN : 1 OUT | AK71: 450-490KW | AM71: 600A- 650A | AN71: 0
B72: =B31 -> 0 | C72: Cable length in mtrs | T72: 7 | U72: =SUM(COUNT(_xlfn._xlws.FILTER(D72:R72,T72))) -> 0 | V72: =_xlfn.CONCAT($U$72,$T$57,$U$57) -> 0 IN :1 OUT | X72: ='Site Vist fomat (Design)'!H31 -> 0 | Z72: =IF(B72<>0,X72*Y72,0) -> 0 | AA72: =IF('Cable Calcualtion'!B159<>"NO MATCH","3.5CX"&'Cable Calcualtion'!B159&"Sqmm","NO MATCH") -> #DIV/0! | AH72: =AH71+1 -> 13 | AJ72: 5 IN : 1 OUT | AK72: 500-550KW | AM72: 670A- 730A | AN72: 0
C73: Cable size in sqmm | AH73: =AH72+1 -> 14 | AJ73: 6 IN : 1 OUT | AK73: 560-600KW | AM73: 740A- 800A | AN73: 0
B74: =B32 -> 0 | C74: Cable length in mtrs | T74: 8 | U74: =SUM(COUNT(_xlfn._xlws.FILTER(D74:R74,T74))) -> 0 | V74: =_xlfn.CONCAT($U$74,$T$57,$U$57) -> 0 IN :1 OUT | X74: ='Site Vist fomat (Design)'!I31 -> 0 | Z74: =IF(B74<>0,X74*Y74,0) -> 0 | AA74: =IF('Cable Calcualtion'!B183<>"NO MATCH","3.5CX"&'Cable Calcualtion'!B183&"Sqmm","NO MATCH") -> #DIV/0! | AH74: =AH73+1 -> 15 | AJ74: 6 IN : 1 OUT | AK74: 600-660KW | AM74: 800A- 880A | AN74: 0
C75: Cable size in sqmm | AH75: =AH74+1 -> 16 | AJ75: 7 IN : 1 OUT | AK75: 670-710KW | AM75: 900A- 950A | AN75: 0
B76: =B33 -> 0 | C76: Cable length in mtrs | T76: 9 | U76: =SUM(COUNT(_xlfn._xlws.FILTER(D76:R76,T76))) -> 0 | V76: =_xlfn.CONCAT($U$76,$T$57,$U$57) -> 0 IN :1 OUT | X76: ='Site Vist fomat (Design)'!J31 -> 0 | Z76: =IF(B76<>0,X76*Y76,0) -> 0 | AA76: =IF('Cable Calcualtion'!B207<>"NO MATCH","3.5CX"&'Cable Calcualtion'!B207&"Sqmm","NO MATCH") -> #DIV/0! | AH76: =AH75+1 -> 17 | AJ76: 7 IN : 1 OUT | AK76: 700-770KW | AM76: 950A-1050A | AN76: 0
C77: Cable size in sqmm | AH77: =AH76+1 -> 18 | AJ77: 8 IN : 1 OUT | AK77: 780-820KW | AM77: 1050A-1100A | AN77: 0
B78: =B34 -> 0 | C78: Cable length in mtrs | T78: 10 | U78: =SUM(COUNT(_xlfn._xlws.FILTER(D78:R78,T78))) -> 0 | V78: =_xlfn.CONCAT($U$78,$T$57,$U$57) -> 0 IN :1 OUT | X78: ='Site Vist fomat (Design)'!K31 -> 0 | Z78: =IF(B78<>0,X78*Y78,0) -> 0 | AA78: =IF('Cable Calcualtion'!B231<>"NO MATCH","3.5CX"&'Cable Calcualtion'!B231&"Sqmm","NO MATCH") -> #DIV/0! | AH78: =AH77+1 -> 19 | AJ78: 8 IN : 1 OUT | AK78: 800-880KW | AM78: 1100A- 1200A | AN78: 0
C79: Cable size in sqmm | AH79: =AH78+1 -> 20 | AJ79: 9 IN : 1 OUT | AK79: 890-940KW | AM79: 1200A- 1250A | AN79: 0
B80: =B35 -> 0 | C80: Cable length in mtrs | T80: 11 | U80: =SUM(COUNT(_xlfn._xlws.FILTER(D80:R80,T80))) -> 0 | V80: =_xlfn.CONCAT($U$80,$T$57,$U$57) -> 0 IN :1 OUT | X80: ='Site Vist fomat (Design)'!L31 -> 0 | Z80: =IF(B80<>0,X80*Y80,0) -> 0 | AA80: =IF('Cable Calcualtion'!B255<>"NO MATCH","3.5CX"&'Cable Calcualtion'!B255&"Sqmm","NO MATCH") -> #DIV/0! | AH80: =AH79+1 -> 21 | AJ80: 9 IN : 1 OUT | AK80: 900-990KW | AM80: 1250A- 1300A | AN80: 0
C81: Cable size in sqmm | AH81: =AH80+1 -> 22 | AJ81: 10 IN : 1 OUT | AK81: 1000-1100KW | AM81: 1320A- 1450A | AN81: 0
B82: =B36 -> 0 | C82: Cable length in mtrs | T82: 12 | U82: =SUM(COUNT(_xlfn._xlws.FILTER(D82:R82,T82))) -> 0 | V82: =_xlfn.CONCAT($U$82,$T$57,$U$57) -> 0 IN :1 OUT | X82: ='Site Vist fomat (Design)'!M31 -> 0 | Z82: =IF(B82<>0,X82*Y82,0) -> 0 | AA82: =IF('Cable Calcualtion'!B279<>"NO MATCH","3.5CX"&'Cable Calcualtion'!B279&"Sqmm","NO MATCH") -> #DIV/0! | AH82: =AH81+1 -> 23 | AJ82: 10 IN : 1 OUT | AK82: 1000-1150KW | AM82: 1320A- 1500A | AN82: 0
C83: Cable size in sqmm | AH83: =AH82+1 -> 24 | AJ83: 11 IN : 1 OUT | AK83: 1100-1210KW | AM83: 1450A- 1600A | AN83: 0
B84: =B37 -> 0 | C84: Cable length in mtrs | T84: 13 | U84: =SUM(COUNT(_xlfn._xlws.FILTER(D84:R84,T84))) -> 0 | V84: =_xlfn.CONCAT($U$84,$T$57,$U$57) -> 0 IN :1 OUT | X84: ='Site Vist fomat (Design)'!N31 -> 0 | Z84: =IF(B84<>0,X84*Y84,0) -> 0 | AA84: =IF('Cable Calcualtion'!B303<>"NO MATCH","3.5CX"&'Cable Calcualtion'!B303&"Sqmm","NO MATCH") -> #DIV/0! | AH84: =AH83+1 -> 25 | AJ84: 11 IN : 1 OUT | AK84: 1220-1260KW | AM84: 1600A-1660A | AN84: 0
C85: Cable size in sqmm | AH85: =AH84+1 -> 26 | AJ85: 12 IN : 1 OUT | AK85: 1200-1320KW | AM85: 1600A-1750A | AN85: 0
B86: =B38 -> 0 | C86: Cable length in mtrs | T86: 14 | U86: =SUM(COUNT(_xlfn._xlws.FILTER(D86:R86,T86))) -> 0 | V86: =_xlfn.CONCAT($U$86,$T$57,$U$57) -> 0 IN :1 OUT | X86: ='Site Vist fomat (Design)'!O31 -> 0 | Z86: =IF(B86<>0,X86*Y86,0) -> 0 | AA86: =IF('Cable Calcualtion'!B327<>"NO MATCH","3.5CX"&'Cable Calcualtion'!B327&"Sqmm","NO MATCH") -> #DIV/0! | AH86: =AH85+1 -> 27 | AJ86: 12 IN : 1 OUT | AK86: 1330-1370KW | AM86: 1750A- 1800A | AN86: 0
C87: Cable size in sqmm | AH87: =AH86+1 -> 28 | AJ87: 13 IN : 1 OUT | AK87: 1300-1430KW | AM87: 1750A- 1900A | AN87: 0
B88: =B39 -> 0 | C88: Cable length in mtrs | T88: 15 | U88: =SUM(COUNT(_xlfn._xlws.FILTER(D88:R88,T88))) -> 0 | V88: =_xlfn.CONCAT($U$88,$T$57,$U$57) -> 0 IN :1 OUT | X88: ='Site Vist fomat (Design)'!P31 -> 0 | Z88: =IF(B88<>0,X88*Y88,0) -> 0 | AA88: =IF('Cable Calcualtion'!B351<>"NO MATCH","3.5CX"&'Cable Calcualtion'!B351&"Sqmm","NO MATCH") -> #DIV/0! | AH88: =AH87+1 -> 29 | AJ88: 13 IN : 1 OUT | AK88: 1440-1480KW | AM88: 1900A- 2000A | AN88: 0
C89: Cable size in sqmm | AH89: =AH88+1 -> 30 | AJ89: 14 IN : 1 OUT | AK89: 1400-1540KW | AM89: 2000A- 2100A | AN89: 0
B90: =B40 -> 0 | C90: Cable length in mtrs | T90: 16 | U90: =SUM(COUNT(_xlfn._xlws.FILTER(D90:R90,T90))) -> 0 | V90: =_xlfn.CONCAT($U$90,$T$57,$U$57) -> 0 IN :1 OUT | X90: ='Site Vist fomat (Design)'!Q31 -> 0 | Z90: =IF(B90<>0,X90*Y90,0) -> 0 | AA90: =IF('Cable Calcualtion'!B375<>"NO MATCH","3.5CX"&'Cable Calcualtion'!B375&"Sqmm","NO MATCH") -> #DIV/0! | AH90: =AH89+1 -> 31 | AJ90: 14 IN : 1 OUT | AK90: 1550-1590KW | AM90: 2100A- 2150A | AN90: 0
C91: Cable size in sqmm | AH91: =AH90+1 -> 32 | AJ91: 15 IN : 1 OUT | AK91: 1500-1650KW | AM91: 2100A- 2200A | AN91: 0
B92: =B41 -> 0 | C92: Cable length in mtrs | T92: 17 | U92: =SUM(COUNT(_xlfn._xlws.FILTER(D92:R92,T92))) -> 0 | V92: =_xlfn.CONCAT($U$92,$T$57,$U$57) -> 0 IN :1 OUT | X92: ='Site Vist fomat (Design)'!R31 -> 0 | Z92: =IF(B92<>0,X92*Y92,0) -> 0 | AA92: =IF('Cable Calcualtion'!B399<>"NO MATCH","3.5CX"&'Cable Calcualtion'!B399&"Sqmm","NO MATCH") -> #DIV/0! | AH92: =AH91+1 -> 33 | AJ92: 15 IN : 1 OUT | AK92: 1660-1700KW | AM92: 2200A-2300A | AN92: 0
C93: Cable size in sqmm | AH93: Total ACCB Qty. | AN93: =IF(G55<1,0,(AN60+AN61+AN62+AN63+AN64+AN65+AN66+AN67+AN68+AN69+AN70+AN71+AN72+AN73+AN74+AN75+AN76+AN77+AN78+AN79+AN80+AN81+AN82+AN83+AN84+AN85+AN86+AN87+AN88+AN89+AN90+AN91+AN92)) -> 2
B94: =B42 -> 0 | C94: Cable length in mtrs | T94: 18 | U94: =SUM(COUNT(_xlfn._xlws.FILTER(D94:R94,T94))) -> 0 | V94: =_xlfn.CONCAT($U$94,$T$57,$U$57) -> 0 IN :1 OUT | X94: ='Site Vist fomat (Design)'!S31 -> 0 | Z94: =IF(B94<>0,X94*Y94,0) -> 0 | AA94: =IF('Cable Calcualtion'!B423<>"NO MATCH","3.5CX"&'Cable Calcualtion'!B423&"Sqmm","NO MATCH") -> #DIV/0!
C95: Cable size in sqmm
B96: =B43 -> 0 | C96: Cable length in mtrs | T96: 19 | U96: =SUM(COUNT(_xlfn._xlws.FILTER(D96:R96,T96))) -> 0 | V96: =_xlfn.CONCAT($U$96,$T$57,$U$57) -> 0 IN :1 OUT | X96: ='Site Vist fomat (Design)'!T31 -> 0 | Z96: =IF(B96<>0,X96*Y96,0) -> 0 | AA96: =IF('Cable Calcualtion'!B447<>"NO MATCH","3.5CX"&'Cable Calcualtion'!B447&"Sqmm","NO MATCH") -> #DIV/0! | AH96: Inv. To ACCB Panel Cable Calculation
C97: Cable size in sqmm | AH97: Inverter Capacity | AJ97: Inv. To ACCB Panel Distance | AM97: No.of Runs
B98: =B44 -> 0 | C98: Cable length in mtrs | T98: 20 | U98: =SUM(COUNT(_xlfn._xlws.FILTER(D98:R98,T98))) -> 0 | V98: =_xlfn.CONCAT($U$98,$T$57,$U$57) -> 0 IN :1 OUT | X98: ='Site Vist fomat (Design)'!U31 -> 0 | Z98: =IF(B98<>0,X98*Y98,0) -> 0 | AA98: =IF('Cable Calcualtion'!B471<>"NO MATCH","3.5CX"&'Cable Calcualtion'!B471&"Sqmm","NO MATCH") -> #DIV/0! | AH98: 150 | AJ98: 25 | AM98: 1
C99: Cable size in sqmm | AH99: Suitable Cable Size | AJ99: =IF('Cable Calcualtion'!B759<>"NO MATCH"," "&AM98&" Runs of "&'Cable Calcualtion'!B759&" Sq. mm","NO MATCH") -> 1 Runs of 300 Sq. mm
B100: =B45 -> 0 | C100: Cable length in mtrs | T100: 21 | U100: =SUM(COUNT(_xlfn._xlws.FILTER(D100:R100,T100))) -> 0 | V100: =_xlfn.CONCAT($U$100,$T$57,$U$57) -> 0 IN :1 OUT | X100: ='Site Vist fomat (Design)'!V31 -> 0 | Z100: =IF(B100<>0,X100*Y100,0) -> 0 | AA100: =IF('Cable Calcualtion'!B495<>"NO MATCH","3.5CX"&'Cable Calcualtion'!B495&"Sqmm","NO MATCH") -> #DIV/0!
C101: Cable size in sqmm
...

Sheet Cable Calcualtion
A1: Al. CABLE CAPACITY(3.5Core) in Sq.mm | C1: 16 | D1: 25 | E1: 35 | F1: 50 | G1: 70 | H1: 95 | I1: 120 | J1: 150 | K1: 185 | L1: 240 | M1: 300 | N1: 400
C2: 3x 16+16 | D2: 3x25+16 | E2: 3x35+16 | F2: 3x50+25 | G2: 3x70+35 | H2: 3x95+50 | I2: 3x120+70 | J2: 3x150+70 | K2: 3x185+95 | L2: 3x240+120 | M2: 3x300+150 | N2: 3x400+185
A3: Cable Amps in Al. Cond. Run in Ground | C3: 74 | D3: 94 | E3: 113 | F3: 133 | G3: 164 | H3: 196 | I3: 223 | J3: 249 | K3: 282 | L3: 326 | M3: 367 | N3: 418
A4: Cable Amps in Al. Cond. Run in Air | C4: 74 | D4: 96 | E4: 117 | F4: 142 | G4: 179 | H4: 221 | I4: 257 | J4: 292 | K4: 337 | L4: 399 | M4: 455 | N4: 530
A5: Total Derating factorb (K1*K2*K3*K4*K5*K6*K7) | B5: 0.7 | C5: =B5 -> 0.7 | D5: =C5 -> 0.7 | E5: =D5 -> 0.7 | F5: =E5 -> 0.7 | G5: =F5 -> 0.7 | H5: =G5 -> 0.7 | I5: =H5 -> 0.7 | J5: =I5 -> 0.7 | ... N5: =M5 -> 0.7
A6: Derated Current in Ground | C6: =C3*C5 -> 51.8 | D6: =D3*D5 -> 65.8 | E6: =E3*E5 -> 79.1 | F6: =F3*F5 -> 93.1 | G6: =G3*G5 -> 114.8 | H6: =H3*H5 -> 137.2 | I6: =I3*I5 -> 156.1 | J6: =J3*J5 -> 174.3 | ... N6: =N3*N5 -> 292.6
A7: Derated Current in Air | C7: =C4*C5 -> 51.8 | D7: =D4*D5 -> 67.2 | E7: =E4*E5 -> 81.9 | F7: =F4*F5 -> 99.4 | G7: =G4*G5 -> 125.3 | H7: =H4*H5 -> 154.7 | I7: =I4*I5 -> 179.9 | J7: =J4*J5 -> 204.4 | ... N7: =N4*N5 -> 371
A8: Resistance @ 90 degrees in ohm/Km | C8: 2.44 | D8: 1.54 | E8: 1.11 | F8: 0.82 | G8: 0.567 | H8: 0.41 | I8: 0.324 | J8: 0.264 | K8: 0.21 | L8: 0.16 | M8: 0.128 | N8: 0.1
A9: Reactance @ 50HZ in ohm/Km | C9: 0.0808 | D9: 0.0805 | E9: 0.0783 | F9: 0.075 | G9: 0.074 | H9: 0.0724 | I9: 0.0712 | J9: 0.0716 | K9: 0.0718 | L9: 0.071 | M9: 0.0705 | N9: 0.0704
A10: No.of amps need to carry on each phase (Amp) | B10: =A18 -> 196.82973 | C10: =B10 -> 196.82973 | D10: =C10 -> 196.82973 | E10: =D10 -> 196.82973 | F10: =E10 -> 196.82973 | G10: =F10 -> 196.82973 | H10: =G10 -> 196.82973 | I10: =H10 -> 196.82973 | J10: =I10 -> 196.82973 | ... N10: =M10 -> 196.82973
A11: No.of meters for run (Mtrs) | B11: ='Input''s from Initial Design'!X60 -> 170 | C11: =B11 -> 170 | D11: =C11 -> 170 | E11: =D11 -> 170 | F11: =E11 -> 170 | G11: =F11 -> 170 | H11: =G11 -> 170 | I11: =H11 -> 170 | J11: =I11 -> 170 | ... N11: =M11 -> 170
A12: No.of runs | B12: ='Input''s from Initial Design'!Y60 -> 1 | C12: =B12 -> 1 | D12: =C12 -> 1 | E12: =D12 -> 1 | F12: =E12 -> 1 | G12: =F12 -> 1 | H12: =G12 -> 1 | I12: =H12 -> 1 | J12: =I12 -> 1 | ... N12: =M12 -> 1
A13: Operating Voltage | B13: 415 | C13: =+B13 -> 415 | D13: =+C13 -> 415 | E13: =+D13 -> 415 | F13: =+E13 -> 415 | G13: =+F13 -> 415 | H13: =+G13 -> 415 | I13: =+H13 -> 415 | J13: =+I13 -> 415 | ... N13: =+M13 -> 415
A14: Voltage drop of cable | C14: =1.732*C10*(C8/1000*1+C9/1000*0)*C11/C12 -> 141.40909 | D14: =1.732*D10*(D8/1000*1+D9/1000*0)*D11/D12 -> 89.25 | E14: =1.732*E10*(E8/1000*1+E9/1000*0)*E11/E12 -> 64.329545 | F14: =1.732*F10*(F8/1000*1+F9/1000*0)*F11/F12 -> 47.522727 | G14: =1.732*G10*(G8/1000*1+G9/1000*0)*G11/G12 -> 32.860227 | H14: =1.732*H10*(H8/1000*1+H9/1000*0)*H11/H12 -> 23.761364 | I14: =1.732*I10*(I8/1000*1+I9/1000*0)*I11/I12 -> 18.777273 | J14: =1.732*J10*(J8/1000*1+J9/1000*0)*J11/J12 -> 15.3 | ... N14: =1.732*N10*(N8/1000*1+N9/1000*0)*N11/N12 -> 5.7954545
A15: Voltage drop of cable% | C15: =C14/C13 -> 0.3407448 | D15: =D14/D13 -> 0.21506024 | E15: =E14/E13 -> 0.15501095 | F15: =F14/F13 -> 0.1145126 | G15: =G14/G13 -> 0.079181271 | H15: =H14/H13 -> 0.057256298 | I15: =I14/I13 -> 0.04524644 | J15: =J14/J13 -> 0.03686747 | ... N15: =N14/N13 -> 0.013964951
A16: If feasable in Ground | B16: 0.02 | C16: =IF(AND((C10*1.25)<(C6*C12),(C15<$B$16)),"PASS","FAIL") -> FAIL | D16: =IF(AND((D10*1.25)<(D6*D12),(D15<$B$16)),"PASS","FAIL") -> FAIL | E16: =IF(AND((E10*1.25)<(E6*E12),(E15<$B$16)),"PASS","FAIL") -> FAIL | F16: =IF(AND((F10*1.25)<(F6*F12),(F15<$B$16)),"PASS","FAIL") -> FAIL | G16: =IF(AND((G10*1.25)<(G6*G12),(G15<$B$16)),"PASS","FAIL") -> FAIL | H16: =IF(AND((H10*1.1)<(H6*H12),(H15<$B$16)),"PASS","FAIL") -> FAIL | I16: =IF(AND((I10*1.25)<(I6*I12),(I15<$B$16)),"PASS","FAIL") -> FAIL | J16: =IF(AND((J10*1.25)<(J6*J12),(J15<$B$16)),"PASS","FAIL") -> FAIL | K16: =IF(AND((K10*1.25)<(K6*K12),(K15<$B$16)),"PASS","FAIL") -> FAIL | L16: =IF(AND((L10*1.25)<(L6*L12),(L15<$B$16)),"PASS","FAIL") -> FAIL | M16: =IF(AND((M10*1.25)<(M6*M12),(M15<$B$16)),"PASS","FAIL") -> PASS | N16: =IF(AND((N10*1.25)<(N6*N12),(N15<$B$16)),"PASS","FAIL") -> PASS
A17: If feasable in Air | C17: =IF(AND((C10*1.25)<(C7*C12),(C15<$B$16)),"PASS","FAIL") -> FAIL | D17: =IF(AND((D10*1.25)<(D7*D12),(D15<$B$16)),"PASS","FAIL") -> FAIL | E17: =IF(AND((E10*1.25)<(E7*E12),(E15<$B$16)),"PASS","FAIL") -> FAIL | F17: =IF(AND((F10*1.25)<(F7*F12),(F15<$B$16)),"PASS","FAIL") -> FAIL | G17: =IF(AND((G10*1.25)<(G7*G12),(G15<$B$16)),"PASS","FAIL") -> FAIL | H17: =IF(AND((H10*1.25)<(H7*H12),(H15<$B$16)),"PASS","FAIL") -> FAIL | I17: =IF(AND((I10*1.25)<(I7*I12),(I15<$B$16)),"PASS","FAIL") -> FAIL | J17: =IF(AND((J10*1.25)<(J7*J12),(J15<$B$16)),"PASS","FAIL") -> FAIL | ... N17: =IF(AND((N10*1.25)<(N7*N12),(N15<$B$16)),"PASS","FAIL") -> PASS
A18: =('Input''s from Initial Design'!W60*1000/(1.732*440*1)) -> 196.82973 | B18: Amps
E19: 1
A20: If feasable in Ground | B20: =IF(C16="FAIL",IF(D16="FAIL",IF(E16="FAIL",IF(F16="FAIL",IF(G16="FAIL",IF(H16="FAIL",IF(I16="FAIL",IF(J16="FAIL",IF(K16="FAIL",IF(L16="FAIL",IF(M16="FAIL","NO MATCH",$M$1),$L$1),$K$1),$J$1),$I$1),$H$1),$G$1),$F$1),$E$1),$D$1),$C$1) -> 300 | C20: Sqmm.
A21: If feasable in Air | B21: =IF(C17="FAIL",IF(D17="FAIL",IF(E17="FAIL",IF(F17="FAIL",IF(G17="FAIL",IF(H17="FAIL",IF(I17="FAIL",IF(J17="FAIL",IF(K17="FAIL",IF(L17="FAIL",IF(M17="FAIL","NO MATCH",$M$1),$L$1),$K$1),$J$1),$I$1),$H$1),$G$1),$F$1),$E$1),$D$1),$C$1) -> 300 | C21: Sqmm.
A24: Al. CABLE CAPACITY(3.5Core) in Sq.mm | C24: 16 | D24: 25 | E24: 35 | F24: 50 | G24: 70 | H24: 95 | I24: 120 | J24: 150 | K24: 185 | L24: 240 | M24: 300 | N24: 400
C25: 3x 16+16 | D25: 3x25+16 | E25: 3x35+16 | F25: 3x50+25 | G25: 3x70+35 | H25: 3x95+50 | I25: 3x120+70 | J25: 3x150+70 | K25: 3x185+95 | L25: 3x240+120 | M25: 3x300+150 | N25: 3x400+185
A26: Cable Amps in Al. Cond. Run in Ground | C26: 74 | D26: 94 | E26: 113 | F26: 133 | G26: 164 | H26: 196 | I26: 223 | J26: 249 | K26: 282 | L26: 326 | M26: 367 | N26: 418
A27: Cable Amps in Al. Cond. Run in Air | C27: 74 | D27: 96 | E27: 117 | F27: 142 | G27: 179 | H27: 221 | I27: 257 | J27: 292 | K27: 337 | L27: 399 | M27: 455 | N27: 530
A28: Total Derating factorb (K1*K2*K3*K4*K5*K6*K7) | B28: 0.7 | C28: =B28 -> 0.7 | D28: =C28 -> 0.7 | E28: =D28 -> 0.7 | F28: =E28 -> 0.7 | G28: =F28 -> 0.7 | H28: =G28 -> 0.7 | I28: =H28 -> 0.7 | J28: =I28 -> 0.7 | ... N28: =M28 -> 0.7
A29: Derated Current in Ground | C29: =C26*C28 -> 51.8 | D29: =D26*D28 -> 65.8 | E29: =E26*E28 -> 79.1 | F29: =F26*F28 -> 93.1 | G29: =G26*G28 -> 114.8 | H29: =H26*H28 -> 137.2 | I29: =I26*I28 -> 156.1 | J29: =J26*J28 -> 174.3 | ... N29: =N26*N28 -> 292.6
A30: Derated Current in Air | C30: =C27*C28 -> 51.8 | D30: =D27*D28 -> 67.2 | E30: =E27*E28 -> 81.9 | F30: =F27*F28 -> 99.4 | G30: =G27*G28 -> 125.3 | H30: =H27*H28 -> 154.7 | I30: =I27*I28 -> 179.9 | J30: =J27*J28 -> 204.4 | ... N30: =N27*N28 -> 371
A31: Resistance @ 90 degrees in ohm/Km | C31: 2.44 | D31: 1.54 | E31: 1.11 | F31: 0.82 | G31: 0.567 | H31: 0.41 | I31: 0.324 | J31: 0.264 | K31: 0.21 | L31: 0.16 | M31: 0.128 | N31: 0.1
A32: Reactance @ 50HZ in ohm/Km | C32: 0.0808 | D32: 0.0805 | E32: 0.0783 | F32: 0.075 | G32: 0.074 | H32: 0.0724 | I32: 0.0712 | J32: 0.0716 | K32: 0.0718 | L32: 0.071 | M32: 0.0705 | N32: 0.0704
A33: No.of amps need to carry on each phase (Amp) | B33: =A41 -> 196.82973 | C33: =B33 -> 196.82973 | D33: =C33 -> 196.82973 | E33: =D33 -> 196.82973 | F33: =E33 -> 196.82973 | G33: =F33 -> 196.82973 | H33: =G33 -> 196.82973 | I33: =H33 -> 196.82973 | J33: =I33 -> 196.82973 | ... N33: =M33 -> 196.82973
A34: No.of meters for run (Mtrs) | B34: ='Input''s from Initial Design'!X62 -> 220 | C34: =B34 -> 220 | D34: =C34 -> 220 | E34: =D34 -> 220 | F34: =E34 -> 220 | G34: =F34 -> 220 | H34: =G34 -> 220 | I34: =H34 -> 220 | J34: =I34 -> 220 | ... N34: =M34 -> 220
A35: No.of runs | B35: ='Input''s from Initial Design'!Y62 -> 2 | C35: =B35 -> 2 | D35: =C35 -> 2 | E35: =D35 -> 2 | F35: =E35 -> 2 | G35: =F35 -> 2 | H35: =G35 -> 2 | I35: =H35 -> 2 | J35: =I35 -> 2 | ... N35: =M35 -> 2
A36: Operating Voltage | B36: 415 | C36: =+B36 -> 415 | D36: =+C36 -> 415 | E36: =+D36 -> 415 | F36: =+E36 -> 415 | G36: =+F36 -> 415 | H36: =+G36 -> 415 | I36: =+H36 -> 415 | J36: =+I36 -> 415 | ... N36: =+M36 -> 415
A37: Voltage drop of cable | C37: =1.732*C33*(C31/1000*1+C32/1000*0)*C34/C35 -> 91.5 | D37: =1.732*D33*(D31/1000*1+D32/1000*0)*D34/D35 -> 57.75 | E37: =1.732*E33*(E31/1000*1+E32/1000*0)*E34/E35 -> 41.625 | F37: =1.732*F33*(F31/1000*1+F32/1000*0)*F34/F35 -> 30.75 | G37: =1.732*G33*(G31/1000*1+G32/1000*0)*G34/G35 -> 21.2625 | H37: =1.732*H33*(H31/1000*1+H32/1000*0)*H34/H35 -> 15.375 | I37: =1.732*I33*(I31/1000*1+I32/1000*0)*I34/I35 -> 12.15 | J37: =1.732*J33*(J31/1000*1+J32/1000*0)*J34/J35 -> 9.9 | ... N37: =1.732*N33*(N31/1000*1+N32/1000*0)*N34/N35 -> 3.75
A38: Voltage drop of cable% | C38: =C37/C36 -> 0.22048193 | D38: =D37/D36 -> 0.13915663 | E38: =E37/E36 -> 0.1003012 | F38: =F37/F36 -> 0.074096386 | G38: =G37/G36 -> 0.05123494 | H38: =H37/H36 -> 0.037048193 | I38: =I37/I36 -> 0.029277108 | J38: =J37/J36 -> 0.023855422 | ... N38: =N37/N36 -> 0.0090361446
A39: If feasable in Ground | B39: 0.02 | C39: =IF(AND((C33*1.25)<(C29*C35),(C38<$B$16)),"PASS","FAIL") -> FAIL | D39: =IF(AND((D33*1.25)<(D29*D35),(D38<$B$16)),"PASS","FAIL") -> FAIL | E39: =IF(AND((E33*1.25)<(E29*E35),(E38<$B$16)),"PASS","FAIL") -> FAIL | F39: =IF(AND((F33*1.25)<(F29*F35),(F38<$B$16)),"PASS","FAIL") -> FAIL | G39: =IF(AND((G33*1.25)<(G29*G35),(G38<$B$16)),"PASS","FAIL") -> FAIL | H39: =IF(AND((H33*1.1)<(H29*H35),(H38<$B$16)),"PASS","FAIL") -> FAIL | I39: =IF(AND((I33*1.25)<(I29*I35),(I38<$B$16)),"PASS","FAIL") -> FAIL | J39: =IF(AND((J33*1.25)<(J29*J35),(J38<$B$16)),"PASS","FAIL") -> FAIL | K39: =IF(AND((K33*1.25)<(K29*K35),(K38<$B$16)),"PASS","FAIL") -> PASS | L39: =IF(AND((L33*1.25)<(L29*L35),(L38<$B$16)),"PASS","FAIL") -> PASS | M39: =IF(AND((M33*1.25)<(M29*M35),(M38<$B$16)),"PASS","FAIL") -> PASS | N39: =IF(AND((N33*1.25)<(N29*N35),(N38<$B$16)),"PASS","FAIL") -> PASS
A40: If feasable in Air | C40: =IF(AND((C33*1.25)<(C30*C35),(C38<$B$16)),"PASS","FAIL") -> FAIL | D40: =IF(AND((D33*1.25)<(D30*D35),(D38<$B$16)),"PASS","FAIL") -> FAIL | E40: =IF(AND((E33*1.25)<(E30*E35),(E38<$B$16)),"PASS","FAIL") -> FAIL | F40: =IF(AND((F33*1.25)<(F30*F35),(F38<$B$16)),"PASS","FAIL") -> FAIL | G40: =IF(AND((G33*1.25)<(G30*G35),(G38<$B$16)),"PASS","FAIL") -> FAIL | H40: =IF(AND((H33*1.25)<(H30*H35),(H38<$B$16)),"PASS","FAIL") -> FAIL | I40: =IF(AND((I33*1.25)<(I30*I35),(I38<$B$16)),"PASS","FAIL") -> FAIL | J40: =IF(AND((J33*1.25)<(J30*J35),(J38<$B$16)),"PASS","FAIL") -> FAIL | ... N40: =IF(AND((N33*1.25)<(N30*N35),(N38<$B$16)),"PASS","FAIL") -> PASS
A41: =('Input''s from Initial Design'!W62*1000/(1.732*440*1)) -> 196.82973 | B41: Amps
E42: 2
A43: If feasable in Ground | B43: =IF(C39="FAIL",IF(D39="FAIL",IF(E39="FAIL",IF(F39="FAIL",IF(G39="FAIL",IF(H39="FAIL",IF(I39="FAIL",IF(J39="FAIL",IF(K39="FAIL",IF(L39="FAIL",IF(M39="FAIL","NO MATCH",$M$1),$L$1),$K$1),$J$1),$I$1),$H$1),$G$1),$F$1),$E$1),$D$1),$C$1) -> 185 | C43: Sqmm.
A44: If feasable in Air | B44: =IF(C40="FAIL",IF(D40="FAIL",IF(E40="FAIL",IF(F40="FAIL",IF(G40="FAIL",IF(H40="FAIL",IF(I40="FAIL",IF(J40="FAIL",IF(K40="FAIL",IF(L40="FAIL",IF(M40="FAIL","NO MATCH",$M$1),$L$1),$K$1),$J$1),$I$1),$H$1),$G$1),$F$1),$E$1),$D$1),$C$1) -> 185 | C44: Sqmm.
A46: Al. CABLE CAPACITY(3.5Core) in Sq.mm | C46: 16 | D46: 25 | E46: 35 | F46: 50 | G46: 70 | H46: 95 | I46: 120 | J46: 150 | K46: 185 | L46: 240 | M46: 300 | N46: 400
C47: 3x 16+16 | D47: 3x25+16 | E47: 3x35+16 | F47: 3x50+25 | G47: 3x70+35 | H47: 3x95+50 | I47: 3x120+70 | J47: 3x150+70 | K47: 3x185+95 | L47: 3x240+120 | M47: 3x300+150 | N47: 3x400+185
A48: Cable Amps in Al. Cond. Run in Ground | C48: 74 | D48: 94 | E48: 113 | F48: 133 | G48: 164 | H48: 196 | I48: 223 | J48: 249 | K48: 282 | L48: 326 | M48: 367 | N48: 418
A49: Cable Amps in Al. Cond. Run in Air | C49: 74 | D49: 96 | E49: 117 | F49: 142 | G49: 179 | H49: 221 | I49: 257 | J49: 292 | K49: 337 | L49: 399 | M49: 455 | N49: 530
A50: Total Derating factorb (K1*K2*K3*K4*K5*K6*K7) | B50: 0.7 | C50: =B50 -> 0.7 | D50: =C50 -> 0.7 | E50: =D50 -> 0.7 | F50: =E50 -> 0.7 | G50: =F50 -> 0.7 | H50: =G50 -> 0.7 | I50: =H50 -> 0.7 | J50: =I50 -> 0.7 | ... N50: =M50 -> 0.7
A51: Derated Current in Ground | C51: =C48*C50 -> 51.8 | D51: =D48*D50 -> 65.8 | E51: =E48*E50 -> 79.1 | F51: =F48*F50 -> 93.1 | G51: =G48*G50 -> 114.8 | H51: =H48*H50 -> 137.2 | I51: =I48*I50 -> 156.1 | J51: =J48*J50 -> 174.3 | ... N51: =N48*N50 -> 292.6
A52: Derated Current in Air | C52: =C49*C50 -> 51.8 | D52: =D49*D50 -> 67.2 | E52: =E49*E50 -> 81.9 | F52: =F49*F50 -> 99.4 | G52: =G49*G50 -> 125.3 | H52: =H49*H50 -> 154.7 | I52: =I49*I50 -> 179.9 | J52: =J49*J50 -> 204.4 | ... N52: =N49*N50 -> 371
A53: Resistance @ 90 degrees in ohm/Km | C53: 2.44 | D53: 1.54 | E53: 1.11 | F53: 0.82 | G53: 0.567 | H53: 0.41 | I53: 0.324 | J53: 0.264 | K53: 0.21 | L53: 0.16 | M53: 0.128 | N53: 0.1
A54: Reactance @ 50HZ in ohm/Km | C54: 0.0808 | D54: 0.0805 | E54: 0.0783 | F54: 0.075 | G54: 0.074 | H54: 0.0724 | I54: 0.0712 | J54: 0.0716 | K54: 0.0718 | L54: 0.071 | M54: 0.0705 | N54: 0.0704
A55: No.of amps need to carry on each phase (Amp) | B55: =A63 -> 0 | C55: =B55 -> 0 | D55: =C55 -> 0 | E55: =D55 -> 0 | F55: =E55 -> 0 | G55: =F55 -> 0 | H55: =G55 -> 0 | I55: =H55 -> 0 | J55: =I55 -> 0 | ... N55: =M55 -> 0
A56: No.of meters for run (Mtrs) | B56: ='Input''s from Initial Design'!X64 -> 200 | C56: =B56 -> 200 | D56: =C56 -> 200 | E56: =D56 -> 200 | F56: =E56 -> 200 | G56: =F56 -> 200 | H56: =G56 -> 200 | I56: =H56 -> 200 | J56: =I56 -> 200 | ... N56: =M56 -> 200
A57: No.of runs | B57: ='Input''s from Initial Design'!Y64 -> 0 | C57: =B57 -> 0 | D57: =C57 -> 0 | E57: =D57 -> 0 | F57: =E57 -> 0 | G57: =F57 -> 0 | H57: =G57 -> 0 | I57: =H57 -> 0 | J57: =I57 -> 0 | ... N57: =M57 -> 0
A58: Operating Voltage | B58: 415 | C58: =+B58 -> 415 | D58: =+C58 -> 415 | E58: =+D58 -> 415 | F58: =+E58 -> 415 | G58: =+F58 -> 415 | H58: =+G58 -> 415 | I58: =+H58 -> 415 | J58: =+I58 -> 415 | ... N58: =+M58 -> 415
A59: Voltage drop of cable | C59: =1.732*C55*(C53/1000*1+C54/1000*0)*C56/C57 -> #DIV/0! | D59: =1.732*D55*(D53/1000*1+D54/1000*0)*D56/D57 -> #DIV/0! | E59: =1.732*E55*(E53/1000*1+E54/1000*0)*E56/E57 -> #DIV/0! | F59: =1.732*F55*(F53/1000*1+F54/1000*0)*F56/F57 -> #DIV/0! | G59: =1.732*G55*(G53/1000*1+G54/1000*0)*G56/G57 -> #DIV/0! | H59: =1.732*H55*(H53/1000*1+H54/1000*0)*H56/H57 -> #DIV/0! | I59: =1.732*I55*(I53/1000*1+I54/1000*0)*I56/I57 -> #DIV/0! | J59: =1.732*J55*(J53/1000*1+J54/1000*0)*J56/J57 -> #DIV/0! | ... N59: =1.732*N55*(N53/1000*1+N54/1000*0)*N56/N57 -> #DIV/0!
A60: Voltage drop of cable% | C60: =C59/C58 -> #DIV/0! | D60: =D59/D58 -> #DIV/0! | E60: =E59/E58 -> #DIV/0! | F60: =F59/F58 -> #DIV/0! | G60: =G59/G58 -> #DIV/0! | H60: =H59/H58 -> #DIV/0! | I60: =I59/I58 -> #DIV/0! | J60: =J59/J58 -> #DIV/0! | ... N60: =N59/N58 -> #DIV/0!
A61: If feasable in Ground | B61: 0.02 | C61: =IF(AND((C55*1.25)<(C51*C57),(C60<$B$16)),"PASS","FAIL") -> #DIV/0! | D61: =IF(AND((D55*1.25)<(D51*D57),(D60<$B$16)),"PASS","FAIL") -> #DIV/0! | E61: =IF(AND((E55*1.25)<(E51*E57),(E60<$B$16)),"PASS","FAIL") -> #DIV/0! | F61: =IF(AND((F55*1.25)<(F51*F57),(F60<$B$16)),"PASS","FAIL") -> #DIV/0! | G61: =IF(AND((G55*1.25)<(G51*G57),(G60<$B$16)),"PASS","FAIL") -> #DIV/0! | H61: =IF(AND((H55*1.1)<(H51*H57),(H60<$B$16)),"PASS","FAIL") -> #DIV/0! | I61: =IF(AND((I55*1.25)<(I51*I57),(I60<$B$16)),"PASS","FAIL") -> #DIV/0! | J61: =IF(AND((J55*1.25)<(J51*J57),(J60<$B$16)),"PASS","FAIL") -> #DIV/0! | K61: =IF(AND((K55*1.25)<(K51*K57),(K60<$B$16)),"PASS","FAIL") -> #DIV/0! | L61: =IF(AND((L55*1.25)<(L51*L57),(L60<$B$16)),"PASS","FAIL") -> #DIV/0! | M61: =IF(AND((M55*1.25)<(M51*M57),(M60<$B$16)),"PASS","FAIL") -> #DIV/0! | N61: =IF(AND((N55*1.25)<(N51*N57),(N60<$B$16)),"PASS","FAIL") -> #DIV/0!
A62: If feasable in Air | C62: =IF(AND((C55*1.25)<(C52*C57),(C60<$B$16)),"PASS","FAIL") -> #DIV/0! | D62: =IF(AND((D55*1.25)<(D52*D57),(D60<$B$16)),"PASS","FAIL") -> #DIV/0! | E62: =IF(AND((E55*1.25)<(E52*E57),(E60<$B$16)),"PASS","FAIL") -> #DIV/0! | F62: =IF(AND((F55*1.25)<(F52*F57),(F60<$B$16)),"PASS","FAIL") -> #DIV/0! | G62: =IF(AND((G55*1.25)<(G52*G57),(G60<$B$16)),"PASS","FAIL") -> #DIV/0! | H62: =IF(AND((H55*1.25)<(H52*H57),(H60<$B$16)),"PASS","FAIL") -> #DIV/0! | I62: =IF(AND((I55*1.25)<(I52*I57),(I60<$B$16)),"PASS","FAIL") -> #DIV/0! | J62: =IF(AND((J55*1.25)<(J52*J57),(J60<$B$16)),"PASS","FAIL") -> #DIV/0! | ... N62: =IF(AND((N55*1.25)<(N52*N57),(N60<$B$16)),"PASS","FAIL") -> #DIV/0!
A63: =('Input''s from Initial Design'!W64*1000/(1.732*440*1)) -> 0 | B63: Amps
E64: 3
A65: If feasable in Ground | B65: =IF(C61="FAIL",IF(D61="FAIL",IF(E61="FAIL",IF(F61="FAIL",IF(G61="FAIL",IF(H61="FAIL",IF(I61="FAIL",IF(J61="FAIL",IF(K61="FAIL",IF(L61="FAIL",IF(M61="FAIL","NO MATCH",$M$1),$L$1),$K$1),$J$1),$I$1),$H$1),$G$1),$F$1),$E$1),$D$1),$C$1) -> #DIV/0! | C65: Sqmm.
A66: If feasable in Air | B66: =IF(C62="FAIL",IF(D62="FAIL",IF(E62="FAIL",IF(F62="FAIL",IF(G62="FAIL",IF(H62="FAIL",IF(I62="FAIL",IF(J62="FAIL",IF(K62="FAIL",IF(L62="FAIL",IF(M62="FAIL","NO MATCH",$M$1),$L$1),$K$1),$J$1),$I$1),$H$1),$G$1),$F$1),$E$1),$D$1),$C$1) -> #DIV/0! | C66: Sqmm.
A68: Al. CABLE CAPACITY(3.5Core) in Sq.mm | C68: 16 | D68: 25 | E68: 35 | F68: 50 | G68: 70 | H68: 95 | I68: 120 | J68: 150 | K68: 185 | L68: 240 | M68: 300 | N68: 400
C69: 3x 16+16 | D69: 3x25+16 | E69: 3x35+16 | F69: 3x50+25 | G69: 3x70+35 | H69: 3x95+50 | I69: 3x120+70 | J69: 3x150+70 | K69: 3x185+95 | L69: 3x240+120 | M69: 3x300+150 | N69: 3x400+185
A70: Cable Amps in Al. Cond. Run in Ground | C70: 74 | D70: 94 | E70: 113 | F70: 133 | G70: 164 | H70: 196 | I70: 223 | J70: 249 | K70: 282 | L70: 326 | M70: 367 | N70: 418
A71: Cable Amps in Al. Cond. Run in Air | C71: 74 | D71: 96 | E71: 117 | F71: 142 | G71: 179 | H71: 221 | I71: 257 | J71: 292 | K71: 337 | L71: 399 | M71: 455 | N71: 530
A72: Total Derating factorb (K1*K2*K3*K4*K5*K6*K7) | B72: 0.7 | C72: =B72 -> 0.7 | D72: =C72 -> 0.7 | E72: =D72 -> 0.7 | F72: =E72 -> 0.7 | G72: =F72 -> 0.7 | H72: =G72 -> 0.7 | I72: =H72 -> 0.7 | J72: =I72 -> 0.7 | ... N72: =M72 -> 0.7
A73: Derated Current in Ground | C73: =C70*C72 -> 51.8 | D73: =D70*D72 -> 65.8 | E73: =E70*E72 -> 79.1 | F73: =F70*F72 -> 93.1 | G73: =G70*G72 -> 114.8 | H73: =H70*H72 -> 137.2 | I73: =I70*I72 -> 156.1 | J73: =J70*J72 -> 174.3 | ... N73: =N70*N72 -> 292.6
A74: Derated Current in Air | C74: =C71*C72 -> 51.8 | D74: =D71*D72 -> 67.2 | E74: =E71*E72 -> 81.9 | F74: =F71*F72 -> 99.4 | G74: =G71*G72 -> 125.3 | H74: =H71*H72 -> 154.7 | I74: =I71*I72 -> 179.9 | J74: =J71*J72 -> 204.4 | ... N74: =N71*N72 -> 371
A75: Resistance @ 90 degrees in ohm/Km | C75: 2.44 | D75: 1.54 | E75: 1.11 | F75: 0.82 | G75: 0.567 | H75: 0.41 | I75: 0.324 | J75: 0.264 | K75: 0.21 | L75: 0.16 | M75: 0.128 | N75: 0.1
A76: Reactance @ 50HZ in ohm/Km | C76: 0.0808 | D76: 0.0805 | E76: 0.0783 | F76: 0.075 | G76: 0.074 | H76: 0.0724 | I76: 0.0712 | J76: 0.0716 | K76: 0.0718 | L76: 0.071 | M76: 0.0705 | N76: 0.0704
A77: No.of amps need to carry on each phase (Amp) | B77: =A85 -> 0 | C77: =B77 -> 0 | D77: =C77 -> 0 | E77: =D77 -> 0 | F77: =E77 -> 0 | G77: =F77 -> 0 | H77: =G77 -> 0 | I77: =H77 -> 0 | J77: =I77 -> 0 | ... N77: =M77 -> 0
A78: No.of meters for run (Mtrs) | B78: ='Input''s from Initial Design'!X66 -> 0 | C78: =B78 -> 0 | D78: =C78 -> 0 | E78: =D78 -> 0 | F78: =E78 -> 0 | G78: =F78 -> 0 | H78: =G78 -> 0 | I78: =H78 -> 0 | J78: =I78 -> 0 | ... N78: =M78 -> 0
A79: No.of runs | B79: ='Input''s from Initial Design'!Y66 -> 0 | C79: =B79 -> 0 | D79: =C79 -> 0 | E79: =D79 -> 0 | F79: =E79 -> 0 | G79: =F79 -> 0 | H79: =G79 -> 0 | I79: =H79 -> 0 | J79: =I79 -> 0 | ... N79: =M79 -> 0
A80: Operating Voltage | B80: 415 | C80: =+B80 -> 415 | D80: =+C80 -> 415 | E80: =+D80 -> 415 | F80: =+E80 -> 415 | G80: =+F80 -> 415 | H80: =+G80 -> 415 | I80: =+H80 -> 415 | J80: =+I80 -> 415 | ... N80: =+M80 -> 415
A81: Voltage drop of cable | C81: =1.732*C77*(C75/1000*1+C76/1000*0)*C78/C79 -> #DIV/0! | D81: =1.732*D77*(D75/1000*1+D76/1000*0)*D78/D79 -> #DIV/0! | E81: =1.732*E77*(E75/1000*1+E76/1000*0)*E78/E79 -> #DIV/0! | F81: =1.732*F77*(F75/1000*1+F76/1000*0)*F78/F79 -> #DIV/0! | G81: =1.732*G77*(G75/1000*1+G76/1000*0)*G78/G79 -> #DIV/0! | H81: =1.732*H77*(H75/1000*1+H76/1000*0)*H78/H79 -> #DIV/0! | I81: =1.732*I77*(I75/1000*1+I76/1000*0)*I78/I79 -> #DIV/0! | J81: =1.732*J77*(J75/1000*1+J76/1000*0)*J78/J79 -> #DIV/0! | ... N81: =1.732*N77*(N75/1000*1+N76/1000*0)*N78/N79 -> #DIV/0!
A82: Voltage drop of cable% | C82: =C81/C80 -> #DIV/0! | D82: =D81/D80 -> #DIV/0! | E82: =E81/E80 -> #DIV/0! | F82: =F81/F80 -> #DIV/0! | G82: =G81/G80 -> #DIV/0! | H82: =H81/H80 -> #DIV/0! | I82: =I81/I80 -> #DIV/0! | J82: =J81/J80 -> #DIV/0! | ... N82: =N81/N80 -> #DIV/0!
A83: If feasable in Ground | B83: 0.02 | C83: =IF(AND((C77*1.25)<(C73*C79),(C82<$B$16)),"PASS","FAIL") -> #DIV/0! | D83: =IF(AND((D77*1.25)<(D73*D79),(D82<$B$16)),"PASS","FAIL") -> #DIV/0! | E83: =IF(AND((E77*1.25)<(E73*E79),(E82<$B$16)),"PASS","FAIL") -> #DIV/0! | F83: =IF(AND((F77*1.25)<(F73*F79),(F82<$B$16)),"PASS","FAIL") -> #DIV/0! | G83: =IF(AND((G77*1.25)<(G73*G79),(G82<$B$16)),"PASS","FAIL") -> #DIV/0! | H83: =IF(AND((H77*1.1)<(H73*H79),(H82<$B$16)),"PASS","FAIL") -> #DIV/0! | I83: =IF(AND((I77*1.25)<(I73*I79),(I82<$B$16)),"PASS","FAIL") -> #DIV/0! | J83: =IF(AND((J77*1.25)<(J73*J79),(J82<$B$16)),"PASS","FAIL") -> #DIV/0! | K83: =IF(AND((K77*1.25)<(K73*K79),(K82<$B$16)),"PASS","FAIL") -> #DIV/0! | L83: =IF(AND((L77*1.25)<(L73*L79),(L82<$B$16)),"PASS","FAIL") -> #DIV/0! | M83: =IF(AND((M77*1.25)<(M73*M79),(M82<$B$16)),"PASS","FAIL") -> #DIV/0! | N83: =IF(AND((N77*1.25)<(N73*N79),(N82<$B$16)),"PASS","FAIL") -> #DIV/0!
A84: If feasable in Air | C84: =IF(AND((C77*1.25)<(C74*C79),(C82<$B$16)),"PASS","FAIL") -> #DIV/0! | D84: =IF(AND((D77*1.25)<(D74*D79),(D82<$B$16)),"PASS","FAIL") -> #DIV/0! | E84: =IF(AND((E77*1.25)<(E74*E79),(E82<$B$16)),"PASS","FAIL") -> #DIV/0! | F84: =IF(AND((F77*1.25)<(F74*F79),(F82<$B$16)),"PASS","FAIL") -> #DIV/0! | G84: =IF(AND((G77*1.25)<(G74*G79),(G82<$B$16)),"PASS","FAIL") -> #DIV/0! | H84: =IF(AND((H77*1.25)<(H74*H79),(H82<$B$16)),"PASS","FAIL") -> #DIV/0! | I84: =IF(AND((I77*1.25)<(I74*I79),(I82<$B$16)),"PASS","FAIL") -> #DIV/0! | J84: =IF(AND((J77*1.25)<(J74*J79),(J82<$B$16)),"PASS","FAIL") -> #DIV/0! | ... N84: =IF(AND((N77*1.25)<(N74*N79),(N82<$B$16)),"PASS","FAIL") -> #DIV/0!
A85: =('Input''s from Initial Design'!W66*1000/(1.732*440*1)) -> 0 | B85: Amps
E86: 4
A87: If feasable in Ground | B87: =IF(C83="FAIL",IF(D83="FAIL",IF(E83="FAIL",IF(F83="FAIL",IF(G83="FAIL",IF(H83="FAIL",IF(I83="FAIL",IF(J83="FAIL",IF(K83="FAIL",IF(L83="FAIL",IF(M83="FAIL","NO MATCH",$M$1),$L$1),$K$1),$J$1),$I$1),$H$1),$G$1),$F$1),$E$1),$D$1),$C$1) -> #DIV/0! | C87: Sqmm.
A88: If feasable in Air | B88: =IF(C84="FAIL",IF(D84="FAIL",IF(E84="FAIL",IF(F84="FAIL",IF(G84="FAIL",IF(H84="FAIL",IF(I84="FAIL",IF(J84="FAIL",IF(K84="FAIL",IF(L84="FAIL",IF(M84="FAIL","NO MATCH",$M$1),$L$1),$K$1),$J$1),$I$1),$H$1),$G$1),$F$1),$E$1),$D$1),$C$1) -> #DIV/0! | C88: Sqmm.
A90: Al. CABLE CAPACITY(3.5Core) in Sq.mm | C90: 16 | D90: 25 | E90: 35 | F90: 50 | G90: 70 | H90: 95 | I90: 120 | J90: 150 | K90: 185 | L90: 240 | M90: 300 | N90: 400
C91: 3x 16+16 | D91: 3x25+16 | E91: 3x35+16 | F91: 3x50+25 | G91: 3x70+35 | H91: 3x95+50 | I91: 3x120+70 | J91: 3x150+70 | K91: 3x185+95 | L91: 3x240+120 | M91: 3x300+150 | N91: 3x400+185
A92: Cable Amps in Al. Cond. Run in Ground | C92: 74 | D92: 94 | E92: 113 | F92: 133 | G92: 164 | H92: 196 | I92: 223 | J92: 249 | K92: 282 | L92: 326 | M92: 367 | N92: 418
A93: Cable Amps in Al. Cond. Run in Air | C93: 74 | D93: 96 | E93: 117 | F93: 142 | G93: 179 | H93: 221 | I93: 257 | J93: 292 | K93: 337 | L93: 399 | M93: 455 | N93: 530
A94: Total Derating factorb (K1*K2*K3*K4*K5*K6*K7) | B94: 0.7 | C94: =B94 -> 0.7 | D94: =C94 -> 0.7 | E94: =D94 -> 0.7 | F94: =E94 -> 0.7 | G94: =F94 -> 0.7 | H94: =G94 -> 0.7 | I94: =H94 -> 0.7 | J94: =I94 -> 0.7 | ... N94: =M94 -> 0.7
A95: Derated Current in Ground | C95: =C92*C94 -> 51.8 | D95: =D92*D94 -> 65.8 | E95: =E92*E94 -> 79.1 | F95: =F92*F94 -> 93.1 | G95: =G92*G94 -> 114.8 | H95: =H92*H94 -> 137.2 | I95: =I92*I94 -> 156.1 | J95: =J92*J94 -> 174.3 | ... N95: =N92*N94 -> 292.6
A96: Derated Current in Air | C96: =C93*C94 -> 51.8 | D96: =D93*D94 -> 67.2 | E96: =E93*E94 -> 81.9 | F96: =F93*F94 -> 99.4 | G96: =G93*G94 -> 125.3 | H96: =H93*H94 -> 154.7 | I96: =I93*I94 -> 179.9 | J96: =J93*J94 -> 204.4 | ... N96: =N93*N94 -> 371
A98: Resistance @ 90 degrees in ohm/Km | C98: 2.44 | D98: 1.54 | E98: 1.11 | F98: 0.82 | G98: 0.567 | H98: 0.41 | I98: 0.324 | J98: 0.264 | K98: 0.21 | L98: 0.16 | M98: 0.128 | N98: 0.1
A99: Reactance @ 50HZ in ohm/Km | C99: 0.0808 | D99: 0.0805 | E99: 0.0783 | F99: 0.075 | G99: 0.074 | H99: 0.0724 | I99: 0.0712 | J99: 0.0716 | K99: 0.0718 | L99: 0.071 | M99: 0.0705 | N99: 0.0704
A101: No.of amps need to carry on each phase (Amp) | B101: =A109 -> 0 | C101: =B101 -> 0 | D101: =C101 -> 0 | E101: =D101 -> 0 | F101: =E101 -> 0 | G101: =F101 -> 0 | H101: =G101 -> 0 | I101: =H101 -> 0 | J101: =I101 -> 0 | ... N101: =M101 -> 0
A102: No.of meters for run (Mtrs) | B102: ='Input''s from Initial Design'!X68 -> 0 | C102: =B102 -> 0 | D102: =C102 -> 0 | E102: =D102 -> 0 | F102: =E102 -> 0 | G102: =F102 -> 0 | H102: =G102 -> 0 | I102: =H102 -> 0 | J102: =I102 -> 0 | ... N102: =M102 -> 0
A103: No.of runs | B103: ='Input''s from Initial Design'!Y68 -> 0 | C103: =B103 -> 0 | D103: =C103 -> 0 | E103: =D103 -> 0 | F103: =E103 -> 0 | G103: =F103 -> 0 | H103: =G103 -> 0 | I103: =H103 -> 0 | J103: =I103 -> 0 | ... N103: =M103 -> 0
A104: Operating Voltage | B104: 415 | C104: =+B104 -> 415 | D104: =+C104 -> 415 | E104: =+D104 -> 415 | F104: =+E104 -> 415 | G104: =+F104 -> 415 | H104: =+G104 -> 415 | I104: =+H104 -> 415 | J104: =+I104 -> 415 | ... N104: =+M104 -> 415
A105: Voltage drop of cable | C105: =1.732*C101*(C98/1000*1+C99/1000*0)*C102/C103 -> #DIV/0! | D105: =1.732*D101*(D98/1000*1+D99/1000*0)*D102/D103 -> #DIV/0! | E105: =1.732*E101*(E98/1000*1+E99/1000*0)*E102/E103 -> #DIV/0! | F105: =1.732*F101*(F98/1000*1+F99/1000*0)*F102/F103 -> #DIV/0! | G105: =1.732*G101*(G98/1000*1+G99/1000*0)*G102/G103 -> #DIV/0! | H105: =1.732*H101*(H98/1000*1+H99/1000*0)*H102/H103 -> #DIV/0! | I105: =1.732*I101*(I98/1000*1+I99/1000*0)*I102/I103 -> #DIV/0! | J105: =1.732*J101*(J98/1000*1+J99/1000*0)*J102/J103 -> #DIV/0! | ... N105: =1.732*N101*(N98/1000*1+N99/1000*0)*N102/N103 -> #DIV/0!
A106: Voltage drop of cable% | C106: =C105/C104 -> #DIV/0! | D106: =D105/D104 -> #DIV/0! | E106: =E105/E104 -> #DIV/0! | F106: =F105/F104 -> #DIV/0! | G106: =G105/G104 -> #DIV/0! | H106: =H105/H104 -> #DIV/0! | I106: =I105/I104 -> #DIV/0! | J106: =J105/J104 -> #DIV/0! | ... N106: =N105/N104 -> #DIV/0!
A107: If feasable in Ground | B107: 0.02 | C107: =IF(AND((C101*1.25)<(C95*C103),(C106<$B$16)),"PASS","FAIL") -> #DIV/0! | D107: =IF(AND((D101*1.25)<(D95*D103),(D106<$B$16)),"PASS","FAIL") -> #DIV/0! | E107: =IF(AND((E101*1.25)<(E95*E103),(E106<$B$16)),"PASS","FAIL") -> #DIV/0! | F107: =IF(AND((F101*1.25)<(F95*F103),(F106<$B$16)),"PASS","FAIL") -> #DIV/0! | G107: =IF(AND((G101*1.25)<(G95*G103),(G106<$B$16)),"PASS","FAIL") -> #DIV/0! | H107: =IF(AND((H101*1.1)<(H95*H103),(H106<$B$16)),"PASS","FAIL") -> #DIV/0! | I107: =IF(AND((I101*1.25)<(I95*I103),(I106<$B$16)),"PASS","FAIL") -> #DIV/0! | J107: =IF(AND((J101*1.25)<(J95*J103),(J106<$B$16)),"PASS","FAIL") -> #DIV/0! | K107: =IF(AND((K101*1.25)<(K95*K103),(K106<$B$16)),"PASS","FAIL") -> #DIV/0! | L107: =IF(AND((L101*1.25)<(L95*L103),(L106<$B$16)),"PASS","FAIL") -> #DIV/0! | M107: =IF(AND((M101*1.25)<(M95*M103),(M106<$B$16)),"PASS","FAIL") -> #DIV/0! | N107: =IF(AND((N101*1.25)<(N95*N103),(N106<$B$16)),"PASS","FAIL") -> #DIV/0!
...

Sheet Bidcell BOM (LTS)
B1: Fourth Partner Energy Pvt Ltd | H1: DOC. No: 4PEL/DES-BCB/662 #I01, R00.
H2: Issue Date: 23/02/2026.
H3: Control Copy No. 02.
B4: BID Cell BOM
A5: SALES BOM (415V LT Level)
A6: Sales BOM Summary | E6: Client Name | G6: ='Input''s from BD(Sales)'!B11 -> West Pioneer Properties
A7: Module & Inverters | B7: =F32+F45 -> 19.498053 | C7: per Wp | E7: ='Input''s from BD(Sales)'!A16 -> Plant Type (Capex/Opex) | G7: ='Input''s from BD(Sales)'!B16 -> Capex
A8: ACCB Panel, DCDB, Optimazer & Spare feeder | B8: =F66+F73 -> 0.85972236 | C8: per Wp | E8: State Name | G8: ='Input''s from BD(Sales)'!B10 -> Maharashtra
A9: Module Mounting Structure | B9: =F59 -> 14.72 | C9: per Wp | E9: ='Input''s from Initial Design'!R7 -> Shed | G9: ='Input''s from Initial Design'!S7 -> 0
A10: DC, AC, Control & Communication Cables | B10: =F77+F81+F94+F107+F121 -> 2.7400028 | C10: per Wp | E10: ='Input''s from Initial Design'!R8 -> Long Rail | G10: ='Input''s from Initial Design'!S8 -> 0
A11: Earthing & LA, RMS and BOS | B11: =F132+F194+F305 -> 1.6775452 | C11: per Wp | E11: ='Input''s from Initial Design'!R9 -> RCC | G11: ='Input''s from Initial Design'!S9 -> 0
A12: Rooftop Infra. (Walkways, cable tray, Ladder & Etc.) | B12: =F137+F141+F150+F159+F178 -> 2.6452092 | C12: per Wp | E12: ='Input''s from Initial Design'!R10 -> RCC Raised | G12: ='Input''s from Initial Design'!S10 -> 400.52
A13: Ground Infra. (Fencing & Plant lighting) | B13: =F200 -> 0 | C13: per Wp | E13: ='Input''s from Initial Design'!R11 -> RCC Raised on Pillars | G13: ='Input''s from Initial Design'!S11 -> 0
A14: I&C and Civil works, Spare & Additional Requirements | B14: =F309+F331+F360+F317+F322 -> -14.147494 | C14: per Wp | E14: ='Input''s from Initial Design'!R12 -> Ground Mounted | G14: ='Input''s from Initial Design'!S12 -> 0
A15: Liaisoning, Net metering | B15: =F381 -> 3.7249975 | C15: per Wp | E15: ='Input''s from Initial Design'!R13 -> Parking- Car/Bike | G15: ='Input''s from Initial Design'!S13 -> 0
A16: AMC & Module cleaning | B16: =F393 -> 0 | C16: per Wp | E16: ='Input''s from Initial Design'!R14 -> Parking-Truck/Bus | G16: ='Input''s from Initial Design'!S14 -> 0
A17: Total summary break-up | E17: ='Input''s from Initial Design'!R15 -> Floating | G17: ='Input''s from Initial Design'!S15 -> 0
A18: Plant Cost (Total-A) | B18: =F362 -> 27.993038 | C18: per Wp | E18: Total Plant Capacity | G18: =SUM(G9:G17) -> 400.52
A19: Plant Cost (Total-A ) without Module | B19: =B18-F31 -> 9.9930379 | C19: per Wp | E19: RFP/RFQ Details
A20: Plant Cost (Total-B) | B20: =F383 -> 31.718035 | C20: per Wp | E20: Availability of RFP/RFQ | G20: =IF('Input''s from BD(Sales)'!B15="", "Not Updated", IFERROR('Input''s from BD(Sales)'!B15, "Not Updated")) -> Yes
A21: Selling Cost Excluding of GST (For Capex) | B21: =F399 -> 35.242262 | C21: per Wp | E21: Is Design According RFP/RFQ | G21: =IF('Input''s from Initial Design'!I6="", "Not Updated", IFERROR('Input''s from Initial Design'!I6, "Not Updated")) -> Yes
A22: Selling Cost Including of GST (For Opex) | B22: =F403 -> 38.378823 | C22: per Wp | E22: Is BOM According To RFP/RFQ | G22: No-As per 4PEL Std
A24: Approvals | B24: Name | D24: Date of Review/Approval | F24: Version no. | G24: Reason for Revision
A25: Sale BOM Reviewed By | B25: Sankar | D25: 46164 | F25: V1 | G25: Initial
A26: Sale BOM Approved By | B26: Sankar | D26: 46164
A27: Bidcell BOM Cost valid for 7 days from the date of Approval
A29: Name of the Item's | B29: Unit Cost | C29: Qty | D29: UOM | E29: Total Cost | F29: per Wp | G29: Item's Spec./Scope of Works | H29: Suggested Makes | I29: Remarks/Marketing Comment
A30: SPV Module
A31: Solar Photovoltaic Module | B31: =IFERROR(VLOOKUP('Input''s from Initial Design'!G21,'Input''s from Initial Design'!Y168:Z170,2,0),0)+2 -> 18 | C31: =$G$18 -> 400.52 | D31: kWp | E31: =IF($G$18<1,0,B31*C31*1000) -> 7209360 | F31: =E31/$G$18/1000 -> 18 | G31: ='Input''s from Initial Design'!G21&" - "&'Input''s from Initial Design'!F21&" "&'Input''s from Initial Design'!F22&" Wp" -> Indian ALMM - Renewsys 620 Wp | H31: ='Input''s from Initial Design'!F21 -> Renewsys
A32: Total Cost for PV Module | E32: =IF($G$18<1,0,SUM(E31:E31)) -> 7209360 | F32: =E32/$G$18/1000 -> 18
A33: String Inverters
A34: String Inverter Model | B34: ='Input''s from Initial Design'!F540 -> 300000 | C34: =IF($G$18<1,0,'Input''s from Initial Design'!H55) -> 2 | D34: No's | E34: =IF($G$18<1,0,B34*C34) -> 600000 | F34: =E34/$G$18/1000 -> 1.4980525 | G34: =IF(C34>0,IF('Input''s from Initial Design'!H24>0,H34&" "&'Input''s from Initial Design'!H24&" "&"kW",""),"") -> Solis 150 kW | H34: ='Input''s from Initial Design'!H23 -> Solis
A35: String Inverter Model | B35: ='Input''s from Initial Design'!G540 -> 290000 | C35: =IF($G$18<1,0,'Input''s from Initial Design'!I55) -> 0 | D35: No's | E35: =IF($G$18<1,0,B35*C35) -> 0 | F35: =E35/$G$18/1000 -> 0 | G35: =IF(C35>0,IF('Input''s from Initial Design'!I24>0,H34&" "&'Input''s from Initial Design'!I24&" "&"kW",""),"")
A36: String Inverter Model | B36: ='Input''s from Initial Design'!H540 -> 255000 | C36: =IF($G$18<1,0,'Input''s from Initial Design'!J55) -> 0 | D36: No's | E36: =IF($G$18<1,0,B36*C36) -> 0 | F36: =E36/$G$18/1000 -> 0 | G36: =IF(C36>0,IF('Input''s from Initial Design'!J24>0,H34&" "&'Input''s from Initial Design'!J24&" "&"kW",""),"")
A37: String Inverter Model | B37: ='Input''s from Initial Design'!I540 -> 135000 | C37: =IF($G$18<1,0,'Input''s from Initial Design'!K55) -> 0 | D37: No's | E37: =IF($G$18<1,0,B37*C37) -> 0 | F37: =E37/$G$18/1000 -> 0 | G37: =IF(C37>0,IF('Input''s from Initial Design'!K24>0,H34&" "&'Input''s from Initial Design'!K24&" "&"kW",""),"")
A38: String Inverter Model | B38: ='Input''s from Initial Design'!J540 -> 125000 | C38: =IF($G$18<1,0,'Input''s from Initial Design'!L55) -> 0 | D38: No's | E38: =IF($G$18<1,0,B38*C38) -> 0 | F38: =E38/$G$18/1000 -> 0 | G38: =IF(C38>0,IF('Input''s from Initial Design'!L24>0,H34&" "&'Input''s from Initial Design'!L24&" "&"kW",""),"")
A39: String Inverter Model | B39: ='Input''s from Initial Design'!K540 -> 95000 | C39: =IF($G$18<1,0,'Input''s from Initial Design'!M55) -> 0 | D39: No's | E39: =IF($G$18<1,0,B39*C39) -> 0 | F39: =E39/$G$18/1000 -> 0 | G39: =IF(C39>0,IF('Input''s from Initial Design'!M24>0,H34&" "&'Input''s from Initial Design'!M24&" "&"kW",""),"")
A40: String Inverter Model | B40: ='Input''s from Initial Design'!L540 -> 85000 | C40: =IF($G$18<1,0,'Input''s from Initial Design'!N55) -> 0 | D40: No's | E40: =IF($G$18<1,0,B40*C40) -> 0 | F40: =E40/$G$18/1000 -> 0 | G40: =IF(C40>0,IF('Input''s from Initial Design'!N24>0,H34&" "&'Input''s from Initial Design'!N24&" "&"kW",""),"")
A41: String Inverter Model | B41: ='Input''s from Initial Design'!M540 -> 70000 | C41: =IF($G$18<1,0,'Input''s from Initial Design'!O55) -> 0 | D41: No's | E41: =IF($G$18<1,0,B41*C41) -> 0 | F41: =E41/$G$18/1000 -> 0 | G41: =IF(C41>0,IF('Input''s from Initial Design'!O24>0,H34&" "&'Input''s from Initial Design'!O24&" "&"kW",""),"")
A42: String Inverter Model | B42: ='Input''s from Initial Design'!N540 -> 69000 | C42: =IF($G$18<1,0,'Input''s from Initial Design'!P55) -> 0 | D42: No's | E42: =IF($G$18<1,0,B42*C42) -> 0 | F42: =E42/$G$18/1000 -> 0 | G42: =IF(C42>0,IF('Input''s from Initial Design'!P24>0,H34&" "&'Input''s from Initial Design'!P24&" "&"kW",""),"")
A43: String Inverter Model | B43: ='Input''s from Initial Design'!O540 -> 75000 | C43: =IF($G$18<1,0,'Input''s from Initial Design'!Q55) -> 0 | D43: No's | E43: =IF($G$18<1,0,B43*C43) -> 0 | F43: =E43/$G$18/1000 -> 0 | G43: =IF(C43>0,IF('Input''s from Initial Design'!Q24>0,H34&" "&'Input''s from Initial Design'!Q24&" "&"kW",""),"")
A44: Inverter extension warranty (6-10 yrars) | B44: {=SUMPRODUCT(25%*B34:B43*IF(C34:C43=1,1,IF(C34:C43>1,C34:C43,0)))} -> 150000 | C44: 1 | D44: No's | E44: =IF(G44="YES",B44*C44) -> FALSE | F44: =IFERROR(E44/$G$18/1000,"-") -> 0 | G44: ='Input''s from BD(Sales)'!B71 -> No
A45: Total Cost for String Inverters | E45: =IF($G$18<1,0,SUM(E34:E44)) -> 600000 | F45: =E45/$G$18/1000 -> 1.4980525
A46: Module Mounting Stucture (MMS) with Hardware
A47: Module Mounting Structure Lord type | B47: =VLOOKUP(G47,G559:H563,2,0) -> #N/A | C47: =IF(G47<>0,'Input''s from Initial Design'!F379,0) -> 0 | D47: No's | E47: =IF(G47=0,0,B47*C47) -> 0 | F47: =E47/$G$18/1000 -> 0 | H47: 120mm Short Profile with make of SMS/MTE/Suncon/RPK/sunrack | I47: Profiles selected as per Designer inputs
A48: Module Mounting Structure Standing seam type | B48: =VLOOKUP(G48,G552:H555,2,0) -> #N/A | C48: =IF(G48<>0,'Input''s from Initial Design'!F379,0) -> 0 | D48: No's | E48: =IF(G48=0,0,B48*C48) -> 0 | F48: =E48/$G$18/1000 -> 0 | I48: {=_xlfn.UNIQUE(_xlfn._xlws.FILTER('Input''s from Initial Design'!$D$25:$D$54,'Input''s from Initial Design'!$D$25:$D$54<>""))} -> #VALUE!
A49: Mid and end Clamp with Hardware | B49: 31 | C49: =C47+C48 -> 0 | D49: No's | E49: =IF($G$18=0,0,B49*C49) -> 0 | F49: =E49/$G$18/1000 -> 0
A50: Long Rail Type (Rooftop) with hardware | B50: 2500 | C50: =G10 -> 0 | D50: kWp | E50: =IF($G$10<1,0,B50*C50) -> 0 | F50: =E50/$G$18/1000 -> 0 | G50: 100mm Clearance
A51: RCC type (Rooftop) with hardware | B51: 110 | C51: =(G11*27)/1000 -> 0 | D51: Tons | E51: =IF($G$11<1,0,B51*C51*1000) -> 0 | F51: =E51/$G$18/1000 -> 0 | G51: Fixed Tilt with 500mm Ground Clearance | H51: FPEL- Std. HDG /GI (min. 80 mic thick)with 180kmph (Steel-TATA, JSW,Jindal) (Tubes -Appolo)
A52: RCC Raised Structure type (Rooftop) with hardware | B52: 140 | C52: =(G12*100)/1000 -> 40.052 | D52: Tons | E52: =IF($G$12<1,0,B52*C52*1000) -> 5607280 | F52: =E52/$G$18/1000 -> 14 | G52: Anchoring with 3000mm Ground Clearance
A53: RCC Raised on Pillar Structure type with hardware | B53: 120 | C53: =(G13*90)/1000 -> 0 | D53: Tons | E53: =IF($G$13<1,0,B53*C53*1000) -> 0 | F53: =E53/$G$18/1000 -> 0
A54: Ground Mounting type with hardware | B54: 97 | C54: =(G14*22)/1000 -> 0 | D54: Tons | E54: =IF($G$14<1,0,B54*C54*1000) -> 0 | F54: =E54/$G$18/1000 -> 0 | G54: Fixed Tilt with 500mm Ground Clearance
A55: Ground Raised Structure type (Car/ Bike Parking) | B55: 140 | C55: =(G15*100)/1000 -> 0 | D55: Tons | E55: =IF($G$15<1,0,B55*C55*1000) -> 0 | F55: =E55/$G$18/1000 -> 0 | G55: J Bold Mounting with 3000mm Ground Clearance
A56: Ground Raised Structure type (Bus/Truck Parking) | B56: 120 | C56: =(G16*140)/1000 -> 0 | D56: Tons | E56: =IF($G$16<1,0,B56*C56*1000) -> 0 | F56: =E56/$G$18/1000 -> 0 | G56: J Bold Mounting with 6000mm Ground Clearance
A57: Floating Structure Along with cable Trays | B57: =10000 -> 10000 | C57: =G17 -> 0 | D57: kWp | E57: =IF($G$17<1,0,B57*C57) -> 0 | F57: =E57/$G$18/1000 -> 0 | H57: Reputed make
A58: Hardware for RCC/RCC Raised/ Ground mounted/ Parking | B58: 240 | C58: =((G11+G14)*1+(G12+G13+G15+G16)*3)/1000 -> 1.20156 | D58: Tons | E58: =IF($G$18<1,0,B58*C58*1000) -> 288374.4 | F58: =E58/$G$18/1000 -> 0.72 | H58: Reputed make
A59: Total Cost for Module Mounting Stucture (MMS) with Hardware | E59: =IF($G$18<1,0,SUM(E47:E58)) -> 5895654.4 | F59: =E59/$G$18/1000 -> 14.72
A60: Junction BOX, DCBD & Optimizers
A61: DCDB with Fuse & SPD | B61: 120000 | C61: =SUM(C34:C43) -> 2 | D61: No's | E61: =IF(H34<>'Input''s from Initial Design'!E499,0,B61*C61) -> 0 | F61: =E61/$G$18/1000 -> 0 | G61: =IF(OR('Input''s from Initial Design'!$H$23<>'Input''s from Initial Design'!$E$491),"Only for Solar edge inverter model",'Input''s from Initial Design'!$E$491) -> Only for Solar edge inverter model | H61: Solar Edge
A62: ACDB with Breaker & SPD | B62: 85000 | C62: =C61 -> 2 | D62: No's | E62: =IF(H34<>'Input''s from Initial Design'!E499,0,B62*C62) -> 0 | F62: =E62/$G$18/1000 -> 0 | G62: =IF(OR('Input''s from Initial Design'!$H$23<>'Input''s from Initial Design'!$E$491),"Only for Solar edge inverter model",'Input''s from Initial Design'!$E$491) -> Only for Solar edge inverter model
A63: Optimizers for Solar Edge Inverter | B63: =IFERROR(VLOOKUP(G63,A594:B595,2,0),0) -> 3650 | C63: ='Input''s from Initial Design'!F55/2 -> 323 | D63: No's | E63: =IF(H34<>'Input''s from Initial Design'!E499,0,B63*C63) -> 0 | F63: =E63/$G$18/1000 -> 0 | G63: ='Input''s from Initial Design'!O21 -> Optimizers- Model-S 1400/ S 1500
A64: DC/AC side fuse with SPD only for Kerala site's | B64: =35000+28000 -> 63000 | C64: =SUM(C34:C43) -> 2 | D64: No's | E64: =IF($G$8<>'Input''s from Initial Design'!B394,0,B64*C64) -> 0 | F64: =E64/$G$18/1000 -> 0 | G64: Applicable only on Kerala state | H64: IP 65 Box of DCDB & ACJB
A65: ACJB for below 50kw Inverter | B65: 3500 | C65: =SUM(C39:C43) -> 0 | D65: No's | E65: =IF(H34<>'Input''s from Initial Design'!D516,0,B65*C65) -> 0 | F65: =E65/$G$18/1000 -> 0 | G65: For Below 50KW Solis inverters | H65: IP 65 Box with Cu.busbar
A66: Total Cost for Junction BOX, DCBD & Optimizers | E66: =IF($G$18<1,0,SUM(E61:E65)) -> 0 | F66: =E66/$G$18/1000 -> 0
A67: ACCB Panel & Spare Feeder
A68: Total cost of Spare Feeder Along with Al.Bus Bar Extension | B68: =IF(AND($G$18>1,'Input''s from BD(Sales)'!B11='Input''s from BD(Sales)'!A159),'Input''s from Initial Design'!I374*8,'Input''s from Initial Design'!I374) -> 381600 | C68: =IF('Input''s from BD(Sales)'!B61='Input''s from Initial Design'!B381,1,0) -> 0 | D68: Lot | E68: =IF($G$18<1,0,B68*C68) -> 0 | F68: =E68/$G$18/1000 -> 0 | G68: ='Input''s from Initial Design'!AN93&" Set's of Spare Feeder Extention" -> 2 Set's of Spare Feeder Extention | H68: Breakers- ABB/ Schneider/ Equilent and Panel from Sri Venkateswara Power Systems/Bhagyashree/ Accupanels/ JVS/Alnico/ DB electrical
A69: Total cost of ACCB Panel at Plant End | B69: =IF('Input''s from BD(Sales)'!B11='Input''s from BD(Sales)'!A159,'Input''s from Initial Design'!AE159*6,'Input''s from Initial Design'!AE159) -> 344336 | C69: =IF(G18>1,1,0) -> 1 | D69: Lot | E69: =IF(C69<>1,0,B69*C69) -> 344336 | F69: =E69/$G$18/1000 -> 0.85972236 | G69: ='Input''s from Initial Design'!AN93&" Set's of ACCB Panels" -> 2 Set's of ACCB Panels
A70: NVR/UVR Panel (Applicable only on Gujarat state) | B70: =IF(G18<1,0,'Input''s from Initial Design'!I354) -> 37092 | C70: =IF(G8='Input''s from BD(Sales)'!A281,1,0) -> 0 | D70: Lot | E70: =IF($G$8='Input''s from BD(Sales)'!A281,B70*C70,0) -> 0 | F70: =E70/$G$18/1000 -> 0 | G70: ='Input''s from Initial Design'!AN93&" Set's of NVR or UVR Panels" -> 2 Set's of NVR or UVR Panels
A71: Contactor/ ACCB Panel(Applicable only on Andhra Pradesh state) | B71: =IF(G18<1,0,'Input''s from Initial Design'!O372) -> 74000 | C71: =IF(G8='Input''s from BD(Sales)'!A275,1,0) -> 0 | D71: Lot | E71: =IF($G$8='Input''s from BD(Sales)'!A275,B71*C71,0) -> 0 | F71: =E71/$G$18/1000 -> 0 | G71: ='Input''s from Initial Design'!AN93&" Set's of Contractor or ACB Panels" -> 2 Set's of Contractor or ACB Panels
A72: Isolation Panel | B72: 0 | C72: 0 | D72: No's | E72: =IF($G$18<1,0,B72*C72) -> 0 | F72: =E72/$G$18/1000 -> 0
A73: Total Cost for ACCB Panel & Spare Feeder | E73: =IF($G$18<1,0,SUM(E68:E72)) -> 344336 | F73: =E73/$G$18/1000 -> 0.85972236
A74: 1000V/1500V DC Cu.Cable
A75: 1CX4 Sqmm DC solar cable 1.8kV XLPO | B75: =VLOOKUP(H75,A556:B559,2,0)-1 -> 57 | C75: ='Input''s from Initial Design'!AN55 -> 4050 | D75: Mtr's | E75: =IF(H75=0,0,B75*C75) -> 230850 | F75: =E75/$G$18/1000 -> 0.57637571 | G75: ='Input''s from Initial Design'!V184&" Mtrs "&"Positive"&" & " &'Input''s from Initial Design'!V185&" Mtrs "&"Negative" -> 2025 Mtrs Positive & 2025 Mtrs Negative | H75: Siechem
A76: 1CX6 Sqmm DC solar cable 1.8kV XLPO | B76: =VLOOKUP(H75,A562:B565,2,0) -> 78 | C76: ='Input''s from Initial Design'!AO55 -> 0 | D76: Mtr's | E76: =IF(H75=0,0,B76*C76) -> 0 | F76: =E76/$G$18/1000 -> 0 | G76: ='Input''s from Initial Design'!V186&" Mtrs"&" Positive"&" & " &'Input''s from Initial Design'!V187&" Mtrs"&" Negative" -> 0 Mtrs Positive & 0 Mtrs Negative
A77: Total Cost for 1000V/1500V DC Cu.Cable | E77: =IF($G$18<1,0,SUM(E75:E76)) -> 230850 | F77: =E77/$G$18/1000 -> 0.57637571
A78: AC Cu. Cable from Inv. to ACJB for below 50kw inverters
A79: 4CX16Sqmm Cu. XLPE Copper Un- Armoured Cable-1.1kV | B79: 1168 | C79: =SUM(C41:C43)*2 -> 0 | D79: Mtr's | E79: =IF($G$18<1,0,B79*C79) -> 0 | F79: =E79/$G$18/1000 -> 0 | G79: =SUM(C41:C43) &" Run's of cables with 2 mtrs each on inverters" -> 0 Run's of cables with 2 mtrs each on inverters | H79: Polycab/ Equilent
A80: 3.5CX25Sqmm Cu. XLPE Copper Un- Armoured Cable-1.1kV | B80: 2336 | C80: =SUM(C39:C40)*2 -> 0 | D80: Mtr's | E80: =IF($G$18<1,0,B80*C80) -> 0 | F80: =E80/$G$18/1000 -> 0 | G80: =SUM(C39:C40) & " Run's of cables with 2 mtrs each on inverters" -> 0 Run's of cables with 2 mtrs each on inverters
A81: Total Cost for Cu. Cable from Inv. to ACJB for below 50kw inverter | E81: =IF($G$18<1,0,SUM(E79:E80)) -> 0 | F81: =E81/$G$18/1000 -> 0
A82: AC AL. XLPE Cable from Inv. to ACCB Panel
A83: 4CX16Sqmm XLPE Al. Armoured Cable-1.1kV | B83: =B96 -> 176.08 | C83: ='Input''s from Initial Design'!Q170 -> 0 | D83: Mtr's | E83: =IF($G$18<1,0,B83*C83) -> 0 | F83: =E83/$G$18/1000 -> 0 | G83: ='Input''s from Initial Design'!O170 & " Run's" -> 0 Run's | H83: Polycab/ Equilent
A84: 3.5CX25Sqmm XLPE Al. Armoured Cable -1.1kV | B84: =B97 -> 194.06 | C84: ='Input''s from Initial Design'!Q171 -> 0 | D84: Mtr's | E84: =IF($G$18<1,0,B84*C84) -> 0 | F84: =E84/$G$18/1000 -> 0 | G84: ='Input''s from Initial Design'!O171 & " Run's" -> 0 Run's
A85: 3.5CX35Sqmm XLPE Al. Armoured Cable -1.1kV | B85: =B98 -> 250.79 | C85: ='Input''s from Initial Design'!Q172 -> 0 | D85: Mtr's | E85: =IF($G$18<1,0,B85*C85) -> 0 | F85: =E85/$G$18/1000 -> 0 | G85: ='Input''s from Initial Design'!O172 & " Run's" -> 0 Run's
A86: 3.5CX50Sqmm XLPE Al. Armoured Cable -1.1kV | B86: =B99 -> 334.18 | C86: ='Input''s from Initial Design'!Q173 -> 0 | D86: Mtr's | E86: =IF($G$18<1,0,B86*C86) -> 0 | F86: =E86/$G$18/1000 -> 0 | G86: ='Input''s from Initial Design'!O173 & " Run's" -> 0 Run's
A87: 3.5CX70Sqmm XLPE Al. Armoured Cable -1.1kV | B87: =B100 -> 455.39 | C87: ='Input''s from Initial Design'!Q174 -> 0 | D87: Mtr's | E87: =IF($G$18<1,0,B87*C87) -> 0 | F87: =E87/$G$18/1000 -> 0 | G87: ='Input''s from Initial Design'!O174 & " Run's" -> 0 Run's
A88: 3.5CX95Sqmm XLPE Al. Armoured Cable -1.1kV | B88: =B101 -> 576.6 | C88: ='Input''s from Initial Design'!Q175 -> 0 | D88: Mtr's | E88: =IF($G$18<1,0,B88*C88) -> 0 | F88: =E88/$G$18/1000 -> 0 | G88: ='Input''s from Initial Design'!O175 & " Run's" -> 0 Run's
A89: 3.5CX120Sqmm XLPE Al. Armoured Cable -1.1kV | B89: =B102 -> 722.92 | C89: ='Input''s from Initial Design'!Q176 -> 0 | D89: Mtr's | E89: =IF($G$18<1,0,B89*C89) -> 0 | F89: =E89/$G$18/1000 -> 0 | G89: ='Input''s from Initial Design'!O176 & " Run's" -> 0 Run's
A90: 3.5CX150Sqmm XLPE Al. Armoured Cable -1.1kV | B90: =B103 -> 843.2 | C90: ='Input''s from Initial Design'!Q177 -> 0 | D90: Mtr's | E90: =IF($G$18<1,0,B90*C90) -> 0 | F90: =E90/$G$18/1000 -> 0 | G90: ='Input''s from Initial Design'!O177 & " Run's" -> 0 Run's
A91: 3.5CX185Sqmm XLPE Al. Armoured Cable -1.1kV | B91: =B104 -> 1066.71 | C91: ='Input''s from Initial Design'!Q178 -> 0 | D91: Mtr's | E91: =IF($G$18<1,0,B91*C91) -> 0 | F91: =E91/$G$18/1000 -> 0 | G91: ='Input''s from Initial Design'!O178 & " Run's" -> 0 Run's
A92: 3.5CX240Sqmm XLPE Al. Armoured Cable -1.1kV | B92: =B105 -> 1359.66 | C92: ='Input''s from Initial Design'!Q179 -> 0 | D92: Mtr's | E92: =IF($G$18<1,0,B92*C92) -> 0 | F92: =E92/$G$18/1000 -> 0 | G92: ='Input''s from Initial Design'!O179 & " Run's" -> 0 Run's
A93: 3.5CX300Sqmm XLPE Al. Armoured Cable -1.1kV | B93: =B106 -> 1686.4 | C93: ='Input''s from Initial Design'!Q180 -> 20 | D93: Mtr's | E93: =IF($G$18<1,0,B93*C93) -> 33728 | F93: =E93/$G$18/1000 -> 0.084210526 | G93: ='Input''s from Initial Design'!O180 & " Run's" -> 2 Run's
A94: Total Cost for AL. XLPE Cable from Inv. to ACCB Panel | E94: =IF($G$18<1,0,SUM(E83:E93)) -> 33728 | F94: =E94/$G$18/1000 -> 0.084210526
A95: AC Al.cable From ACCB Panel to Client Termination
A96: 4CX16Sqmm XLPE AC Al. Armoured Cable-1.1kV | B96: 176.08 | C96: ='Input''s from Initial Design'!V170 -> 0 | D96: Mtr's | E96: =IF($G$18<1,0,B96*C96) -> 0 | F96: =E96/$G$18/1000 -> 0 | G96: ='Input''s from Initial Design'!W170 & " Run's" -> 0 Run's | H96: Polycab/ Equilent
A97: 3.5CX25Sqmm XLPE Al. Armoured Cable -1.1kV | B97: 194.06 | C97: ='Input''s from Initial Design'!V171 -> 0 | D97: Mtr's | E97: =IF($G$18<1,0,B97*C97) -> 0 | F97: =E97/$G$18/1000 -> 0 | G97: ='Input''s from Initial Design'!W171 & " Run's" -> 0 Run's
A98: 3.5CX35Sqmm XLPE Al. Armoured Cable -1.1kV | B98: 250.79 | C98: ='Input''s from Initial Design'!V172 -> 0 | D98: Mtr's | E98: =IF($G$18<1,0,B98*C98) -> 0 | F98: =E98/$G$18/1000 -> 0 | G98: ='Input''s from Initial Design'!W172 & " Run's" -> 0 Run's
A99: 3.5CX50Sqmm XLPE Al. Armoured Cable -1.1kV | B99: 334.18 | C99: ='Input''s from Initial Design'!V173 -> 0 | D99: Mtr's | E99: =IF($G$18<1,0,B99*C99) -> 0 | F99: =E99/$G$18/1000 -> 0 | G99: ='Input''s from Initial Design'!W173 & " Run's" -> 0 Run's
A100: 3.5CX70Sqmm XLPE Al. Armoured Cable -1.1kV | B100: 455.39 | C100: ='Input''s from Initial Design'!V174 -> 0 | D100: Mtr's | E100: =IF($G$18<1,0,B100*C100) -> 0 | F100: =E100/$G$18/1000 -> 0 | G100: ='Input''s from Initial Design'!W174 & " Run's" -> 0 Run's
A101: 3.5CX95Sqmm XLPE Al. Armoured Cable -1.1kV | B101: 576.6 | C101: ='Input''s from Initial Design'!V175 -> 0 | D101: Mtr's | E101: =IF($G$18<1,0,B101*C101) -> 0 | F101: =E101/$G$18/1000 -> 0 | G101: ='Input''s from Initial Design'!W175 & " Run's" -> 0 Run's
A102: 3.5CX120Sqmm XLPE Al. Armoured Cable -1.1kV | B102: 722.92 | C102: ='Input''s from Initial Design'!V176 -> 0 | D102: Mtr's | E102: =IF($G$18<1,0,B102*C102) -> 0 | F102: =E102/$G$18/1000 -> 0 | G102: ='Input''s from Initial Design'!W176 & " Run's" -> 0 Run's
...

Sheet Sheet4
D2: =(4*18)+(2*19)+(5*18)+(2*19) -> 238
D3: =((4*16)+(2*20))+(1*18)+(7*18)+(2*19)+(6*19) -> 400 | E3: =SUM(D2:D3) -> 638
B5: MPPT - 1 | C5: Str - 1 | D5: 18
C6: Str - 2 | D6: 18
B7: MPPT - 2 | C7: Str - 3 | D7: 18
C8: Str - 4 | D8: 18
B9: MPPT - 3 | C9: Str - 5 | D9: 18
C10: Str - 6 | D10: 18
B11: MPPT - 4 | C11: Str - 7 | D11: 18
C12: Str - 8
B13: MPPT - 5 | C13: Str - 9
C14: Str - 10 | D14: 19
B15: MPPT - 6 | C15: Str - 11 | D15: 19
C16: Str - 12
B17: MPPT - 7 | C17: Str - 13 | D17: 19
C18: Str - 14 | D18: 19
B19: MPPT - 8 | C19: Str - 15
C20: Str - 16 | D20: 19
B21: MPPT - 9 | C21: Str - 17 | D21: 19
C22: Str - 18
B23: MPPT - 10 | C23: Str - 19 | D23: 19
C24: Str - 20 | D24: 19
D25: 125

Sheet Sheet3
A1: Items | B1: Units | C1: Makes | D1: Items | E1: Units | F1: Makes
A2: Floating Structure Along with cable Trays | B2: kWp | C2: Reputed make | D2: M4x20mm for module frame earthing | E2: No's
A3: Hardware for RCC/RCC Raised/ Ground mounted/ Parking | B3: Tons | C3: Reputed make | D3: M8x15mm for walkways | E3: No's
A4: Railings on Roof Edge's with toe guard | B4: Mtr's | D4: Hose pipe for water | E4: Mtr's
A5: Mesh Over the Skylight width <600mm | B5: Rmtr's | C5: GI | D5: 25 mm CPVC Pipe for Water piping & array looping purpose | E5: Mtr's | F5: Birla/ Equilent
A6: Mesh Over the Skylight width 600-1200mm | B6: Rmtr's | D6: 25 mm CPVC T-bend | E6: No's
A7: Mesh Over the Skylight width 1200-1700mm | B7: Rmtr's | D7: 25 mm CPVC L-bend | E7: No's
A8: Mesh Over the Skylight width 1700-2200mm | B8: Rmtr's | D8: 25 mm CPVC Ball value | E8: No's
A9: Gutter length for Cleaning / Rain water harvesting | B9: Mtr's | C9: Reputed make | D9: 25 mm CPVC Coupler | E9: No's
A10: Gutters Dropdown for every 10 mtrs length | B10: No's | C10: Reputed make | D10: CVPC Solution 934ml | E10: No's
A11: Module Temperature Sensor | B11: No's | C11: Any Reputed Make | D11: CPVC Pipe C Clamp | E11: No's
A12: Ambient Temperature Sensor | B12: No's | D12: CPVC Pipe End cap | E12: No's
A13: Anemometer | B13: No's | D13: 25mm CPVC MTA and FTA | E13: No's
A14: Rain gauge Sensor | B14: No's | D14: 25mm CPVC Union | E14: No's
A15: Weather Station Tripod Mounting Stand with junction box | B15: No's | D15: 600 KVA UPS | E15: No's
A16: Data Logger | B16: No's | D16: Earthing name plates | E16: No's
A17: Humidity Sensor | B17: No's | D17: Danger board AC 415V and DC 1500V | E17: No's
A18: Earth Strip Clamps | B18: No's | C18: Reputed make | D18: Fourthpartner Name Plant | E18: No's
A19: M8X25 Self triding screw and wooden Gutties | B19: No's | C19: Reputed make | D19: LT Cable Route marker | E19: No's
A20: M8x25mm for Earth Strip and cable tray | B20: No's | C20: Reputed make | D20: Insulation mats 1Mtrx1Mtr for Inverter & ACCB 3.3kv | E20: No's
A21: Base clamp 100mm | B21: No's | C21: Reputed make | D21: Hume Pipe 300mm Dia | E21: Mtr's
A22: M-clamp SS - Walkway clamps | B22: No's | C22: Reputed make | D22: DWC Pipe for Ground Mounted Type | E22: Mtr's | F22: Nagarjuna polymers / Equilent
A23: M8x15mm Walkway jointer with hardware | B23: No's | C23: Reputed make | D23: DWC Pipe T bend | E23: No's
A24: Step and Zero degree walkway Supports GI raised Leg | B24: No's | C24: Reputed make | D24: DWC Pipe L bend | E24: No's
A25: Bus Insulators for LA strip | B25: No's | C25: Reputed make | D25: DWC Pipe Coupler | E25: No's
A26: 32mm Flexible Pipe used for module to cable Tray | B26: Mtr's | C26: Reputed make | D26: PVC Water Tank 5000 Ltrs | E26: No's | F26: Sintex/ Equilent
A27: Industrial wall socket box with MCB (Single phase two pole) | B27: No's | D27: PVC Water Tank 2000 Ltrs | E27: No's
A28: Industrial wall socket box with MCB (Three phase four pole) | B28: No's | D28: 1 HP Water pump | E28: No's | F28: Crompton Greaves/ Equilent
A29: Module water drainage clips | B29: No's | D29: 1.5 HP Water pump | E29: No's
A30: Cable Ties -Nylon 150mm | B30: Packet's | D30: Booster Water pump | E30: No's
A31: Cable Ties -Nylon 200mm | B31: Packet's | D31: Water flow meter | E31: No's
A32: Cable Ties -Nylon 300mm | B32: Packet's | D32: Water Pressure release Value | E32: No's
A33: Cable Ties -Nylon 450mm | B33: Packet's | D33: 2.5 Sqmm Cu. & Bimetallic Lug's Pin & Ring type | E33: No's | F33: Dowell's/ Equilent
A34: Cable Ties -SS 200mm | B34: Packet's | D34: 4 Sqmm Cu. Lug's Round type | E34: No's
A35: Cable Ties -SS 300mm | B35: Packet's | D35: 16 Sqmm Cu. & Bimetallic Lug's Pin & Ring type | E35: No's
A36: Cable Ties -SS 500mm | B36: Packet's | D36: 25 Sqmm Cu. & Bimetallic Lug's Pin & Ring type | E36: No's
A37: LA support- 3 mtrs GI pipe | B37: No's | D37: 35 Sqmm Cu. & Bimetallic Lug's Pin & Ring type | E37: No's
A38: Stay wires for LA | B38: Mtr's | D38: 50 Sqmm Cu. & Bimetallic Lug's Pin & Ring type | E38: No's
A39: MC4 connector Male and Female | B39: No's | D39: 70 Sqmm Cu. & Bimetallic Lug's Pin & Ring type | E39: No's
A40: Inlie Fuse Male & Female | B40: No's | C40: Elmax/ Equilent | D40: 16 Sqmm Bimetallic Lug's Pin type | E40: No's
A41: DC cable dressing clips | B41: No's | D41: 25 Sqmm Bimetallic Lug's Pin type | E41: No's
A42: Fire extinguisher CO2 | B42: No's | D42: 35 Sqmm Bimetallic Lug's Pin type | E42: No's
A43: Fire Bucket with Stand and canopy | B43: No's | D43: 50 Sqmm Bimetallic Lug's Pin type | E43: No's
A44: Fire extinguisher ABC type | B44: No's | D44: 70 Sqmm Bimetallic Lug's Pin type | E44: No's
A45: Conduit pipe fixing(joining) Solvent (1000 ml) | B45: No's | D45: 95 Sqmm Bimetallic Lug's Pin type | E45: No's
A46: Pu sealant for closing the opening of the pipes/conduits | B46: No's | D46: 185 Sqmm Bimetallic Lug's Pin type | E46: No's
A47: Sleeves each colour 250mm length Inv. To ACCB panel | B47: Mtr's | D47: 240 Sqmm Bimetallic Lug's Pin type | E47: No's
A48: Sleeves each colour 250mm ACCB panel to Termination | B48: Mtr's | D48: 16 Sqmm AL. Lug's Ring type | E48: No's
A49: PVC Tape (R, Y, B, B, G) | B49: No's | D49: 25 Sqmm AL. Lug's Ring type | E49: No's
A50: Ferrules | B50: No's | D50: 35 Sqmm AL. Lug's Ring type | E50: No's
A51: 150 Sqmm AL. Lug's Ring type | B51: No's | C51: Dowell's/ Equilent | D51: 50 Sqmm AL. Lug's Ring type | E51: No's
A52: 185 Sqmm AL. Lug's Ring type | B52: No's | D52: 70 Sqmm AL. Lug's Ring type | E52: No's
A53: 240 Sqmm AL. Lug's Ring type | B53: No's | D53: 95 Sqmm AL. Lug's Ring type | E53: No's
A54: 300 Sqmm AL. Lug's Ring type | B54: No's | D54: 120 Sqmm AL. Lug's Ring type | E54: No's
A55: Freight & Handling By Road | B55: Truck | C55: Goods Transportation (Only BOS)

Sheet Sheet2
A1: =IF(F16<101,G480,IF(F16<501,G481,IF(F16<1001,G482,IF(F16<2501,G483,IF(F16>5001,G484,0))))) -> 0
B3: 0.5 HP | C3: 2850
B4: 1 HP | C4: 3850 | H4: g488 | I4: Base 24 mm -ECO 70
B5: 1.5 HP | C5: 10200 | H5: g489 | I5: Trapezoidal or curve type
B6: 2 HP | C6: 14500 | H6: g490 | I6: Land scape - 300MM
B7: booster | C7: 24000 | F7: 400 | H7: g491 | I7: Land scape - 250MM
F8: =F7/10 -> 40 | H8: g492 | I8: Base 40 mm - SSP 1032
B9: =VLOOKUP(G137,G523:H528,2,0) -> #N/A

Sheet Item's Make
A2: Sr.no. | B2: Item's | C2: 4PEL Standard Make's
A3: 1 | B3: Inverter | C3: Solis
A4: 2 | B4: MMS for Shed | C4: SMS, EPDM gasket (bimettalic)
B5: MMS for RCC & Ground | C5: Fourth Partner Energy- MS Hot dip galvanization (min. 80 micron thickness) with 180kmph (Steel-TATA, JSW,Jindal)(Tubes -Appolo)
A6: 4 | B6: LT Panel | C6: Indus, Bhagyashree, Accupanels, Sanjay tec, LS power
A7: 5 | B7: Switch Gears | C7: Schneider, L&T, ABB
A8: 6 | B8: Chemical Earthing | C8: Indelec/ LPI
A9: 7 | B9: DC Cu. Cable | C9: Polycab
A10: 8 | B10: Branch Connectors (Inland fuse) | C10: Elmax
A11: 9 | B11: AC Cable | C11: Polycab
A12: 10 | B12: Lightening Arrestor | C12: LPI
A13: 11 | B13: Water Pipe | C13: Astral
A14: 12 | B14: Harizonal Walkways | C14: MOC/FRP
A15: 13 | B15: Cable Tray | C15: GI/FRP
A16: 14 | B16: DWC Pipe | C16: Nagarjuna polymers/dura.line
A17: 15 | B17: Lifeline | C17: Joykco/Life Gear
... A20: 18 | B20: Pyranometer | C20: Kripp Zonen
A21: 19 | B21: Zero Feeding device | C21: =C18 -> Wattmon
A22: 20 | B22: DG Protection device | C22: =C21 -> Wattmon
A23: 21 | B23: Generation Panel before client | C23: =C6 -> Indus, Bhagyashree, Accupanels, Sanjay tec, LS power
A24: 22 | B24: Net metering Materials | C24: Secure / L&T
A25: 23 | B25: Metering Cubicle (CT&PT) | C25: Kalpa/Kappa
G35: =36877-56410 -> -19533
D36: =260000*9.16 -> 2381600 | E36: =31600 -> 31600 | F36: =9.16/2 -> 4.58
D37: 110000 | E37: =D36-E36 -> 2350000
B38: 374446 | D38: =D36+D37 -> 2491600
B39: =1200000-C42 -> 223154 | C39: =1200000-C42 -> 223154 | D39: =D36*2% -> 47632
B40: =B38-B39 -> 151292 | C40: =C39/C45 -> 0.60743003 | D40: =D38+D39 -> 2539232
C41: =26241*46 -> 1207086 | D41: =D40/9.16 -> 277208.73 | F41: =1700000 -> 1700000
C42: =976846 -> 976846 | F42: =D40-F41 -> 839232 | G42: =20*40000 -> 800000
B43: =B40/B38 -> 0.40404224 | C43: =C41-C42 -> 230240 | D43: =2600000 -> 2600000
C44: =26241*60 -> 1574460 | D44: =D43-D40 -> 60768 | F44: =D40-D55 -> 1581232
C45: =C44-C41 -> 367374 | F45: =F44*10% -> 158123.2
D46: =89800 -> 89800
C47: =C45/26241 -> 14 | D47: =113000 -> 113000
C48: =14*26241 -> 367374 | D48: =D47-D46 -> 23200
D51: =56410+26410 -> 82820
D52: =2600000 -> 2600000
D53: =D51-D52 -> -2517180
D55: 958000 | E55: 479000 | G55: =D55/9.16 -> 104585.15
C58: stamp | D58: =D55*7% -> 67060 | E58: =E55*7% -> 33530 | F58: =D58/2 -> 33530
C59: reg. fees | D59: =D55*2% -> 19160 | E59: =E55*2% -> 9580
C60: other | D60: 3000 | E60: 3000
C61: office exp. | D61: 3000 | E61: 3000
C62: fees | D62: 8000 | E62: 8000
D63: =SUM(D58:D62) -> 100220 | E63: =SUM(E58:E62) -> 57110
E64: =E63*2 -> 114220

Sheet Sheet1
A2: Sl no. | B2: Name of the Item's | C2: Current price | D2: Updated Price | E2: Price Diviation
A3: 1 | B3: 1CX4 Sqmm DC solar cable 1.8kV XLPO, FRLS | C3: 43 | D3: 44 | E3: =C3-D3 -> -1 | H3: 13050
A4: =A3+1 -> 2 | B4: 1CX6 Sqmm DC solar cable 1.8kV XLPO, FRLS | C4: 62 | D4: 63 | E4: =C4-D4 -> -1 | H4: 10000
A5: =A4+1 -> 3 | B5: 4CX16Sqmm Cu XLPE AC Copper Un- Armoured Cable-1.1kV | C5: 1044 | E5: =C5-D5 -> 1044 | H5: 6500
A6: =A5+1 -> 4 | B6: 4CX25Sqmm Cu XLPE AC Copper Un- Armoured Cable-1.1kV | C6: 1737 | E6: =C6-D6 -> 1737 | H6: 5000
A7: =A6+1 -> 5 | B7: 4CX16Sqmm Al XLPE AC Aluminium Armoured Cable-1.1kV | C7: 117.9 | E7: =C7-D7 -> 117.9
A8: =A7+1 -> 6 | B8: 3.5CX25Sqmm Al XLPE AC Aluminium Armoured Cable -1.1kV | C8: 165.6 | E8: =C8-D8 -> 165.6
A9: =A8+1 -> 7 | B9: 3.5CX35Sqmm Al XLPE AC Aluminium Armoured Cable-1.1kV | C9: 187.2 | E9: =C9-D9 -> 187.2
A10: =A9+1 -> 8 | B10: 3.5CX50Sqmm Al XLPE AC Aluminium Armoured Cable -1.1kV | C10: 253.5 | E10: =C10-D10 -> 253.5
A11: =A10+1 -> 9 | B11: 3.5CX70Sqmm Al XLPE AC Aluminium Armoured Cable -1.1kV | C11: 346.5 | E11: =C11-D11 -> 346.5
A12: =A11+1 -> 10 | B12: 3.5CX95Sqmm Al XLPE AC Aluminium Armoured Cable -1.1kV | C12: 441 | E12: =C12-D12 -> 441 | G12: total | H12: =260000*9.16 -> 2381600
A13: =A12+1 -> 11 | B13: 3.5CX120Sqmm Al XLPE AC Aluminium Armoured Cable-1.1kV | C13: 567 | E13: =C13-D13 -> 567 | G13: DD | H13: =479000*2 -> 958000
A14: =A13+1 -> 12 | B14: 3.5CX150Sqmm Al XLPE AC Aluminium Armoured Cable -1.1kV | C14: 663.3 | E14: =C14-D14 -> 663.3 | G14: cash | H14: =H12-H13 -> 1423600
A15: =A14+1 -> 13 | B15: 3.5CX185Sqmm Al XLPE AC Aluminium Armoured Cable -1.1kV | C15: 848.4 | E15: =C15-D15 -> 848.4 | H15: =1465000+15000 -> 1480000
A16: =A15+1 -> 14 | B16: 3.5CX240Sqmm Al XLPE AC Aluminium Armoured Cable-1.1kV | C16: 1038.3 | E16: =C16-D16 -> 1038.3 | H16: =H15-H14 -> 56400
A17: =A16+1 -> 15 | B17: 3.5CX300Sqmm Al XLPE AC Aluminium Armoured Cable -1.1kV | C17: 1345.5 | E17: =C17-D17 -> 1345.5 | G17: docu. | H17: =110000 -> 110000
A18: =A17+1 -> 16 | E18: =C18-D18 -> 0 | G18: SC | H18: =+H12*2% -> 47632
H19: =H18+H17 -> 157632
H20: =H19-H16 -> 101232
F21: =716700 -> 716700 | G21: =E22-F21 -> 37188 | H21: =7100+G21 -> 44288
E22: =753888 -> 753888 | F22: =742693 -> 742693 | G22: =F22-E22 -> -11195 | H22: =-7100+G22 -> -18295
B24: 2500000 | C24: 3253860 | D24: =C24-B24 -> 753860 | F24: =SUM(E25:E70) -> 1207086
A25: 1 | B25: 54231 | C25: =C24-B25 -> 3199629 | D25: 45876 | E25: 26241 | F25: =F24-E25 -> 1180845 | H25: =B25+E25 -> 80472
A26: =A25+1 -> 2 | B26: 54231 | C26: =C25-B26 -> 3145398 | D26: 45877 | E26: 26241 | F26: =F25-E26 -> 1154604 | H26: =B26+E26 -> 80472
A27: =A26+1 -> 3 | B27: 54231 | C27: =C26-B27 -> 3091167 | D27: 45878 | E27: 26241 | F27: =F26-E27 -> 1128363 | H27: =B27+E27 -> 80472
A28: =A27+1 -> 4 | B28: 54231 | C28: =C27-B28 -> 3036936 | D28: 45879 | E28: 26241 | F28: =F27-E28 -> 1102122 | H28: =B28+E28 -> 80472
A29: =A28+1 -> 5 | B29: 54231 | C29: =C28-B29 -> 2982705 | D29: 45880 | E29: 26241 | F29: =F28-E29 -> 1075881 | H29: =B29+E29 -> 80472
A30: =A29+1 -> 6 | B30: 54231 | C30: =C29-B30 -> 2928474 | D30: 45881 | E30: 26241 | F30: =F29-E30 -> 1049640 | H30: =B30+E30 -> 80472
A31: =A30+1 -> 7 | B31: 54231 | C31: =C30-B31 -> 2874243 | D31: 46235 | E31: 26241 | F31: =F30-E31 -> 1023399 | H31: =B31+E31 -> 80472
A32: =A31+1 -> 8 | B32: 54231 | C32: =C31-B32 -> 2820012 | D32: 46236 | E32: 26241 | F32: =F31-E32 -> 997158 | H32: =B32+E32 -> 80472
A33: =A32+1 -> 9 | B33: 54231 | C33: =C32-B33 -> 2765781 | D33: 46237 | E33: 26241 | F33: =F32-E33 -> 970917 | H33: =B33+E33 -> 80472
A34: =A33+1 -> 10 | B34: 54231 | C34: =C33-B34 -> 2711550 | D34: 46238 | E34: 26241 | F34: =F33-E34 -> 944676 | H34: =B34+E34 -> 80472
A35: =A34+1 -> 11 | B35: 54231 | C35: =C34-B35 -> 2657319 | D35: 46239 | E35: 26241 | F35: =F34-E35 -> 918435 | H35: =B35+E35 -> 80472
A36: =A35+1 -> 12 | B36: 54231 | C36: =C35-B36 -> 2603088 | D36: 46240 | E36: 26241 | F36: =F35-E36 -> 892194 | H36: =B36+E36 -> 80472
A37: =A36+1 -> 13 | B37: 54231 | C37: =C36-B37 -> 2548857 | D37: 46241 | E37: 26241 | F37: =F36-E37 -> 865953 | H37: =B37+E37 -> 80472
... A70: =A69+1 -> 46 | B70: 54231 | C70: =C69-B70 -> 759234 | D70: 47334 | E70: 26241 | F70: =F69-E70 -> 0 | H70: =B70+E70 -> 80472
A71: =A70+1 -> 47 | B71: 54231 | C71: =C70-B71 -> 705003 | D71: 47335 | H71: =B71+E71 -> 54231
A72: =A71+1 -> 48 | B72: 54231 | C72: =C71-B72 -> 650772 | D72: 47336 | H72: =B72+E72 -> 54231
A73: =A72+1 -> 49 | B73: 54231 | C73: =C72-B73 -> 596541 | D73: 47337 | H73: =B73+E73 -> 54231
A74: =A73+1 -> 50 | B74: 54231 | C74: =C73-B74 -> 542310 | D74: 47338 | H74: =B74+E74 -> 54231
A75: =A74+1 -> 51 | B75: 54231 | C75: =C74-B75 -> 488079 | D75: 47339 | H75: =B75+E75 -> 54231
A76: =A75+1 -> 52 | B76: 54231 | C76: =C75-B76 -> 433848 | D76: 47340 | H76: =B76+E76 -> 54231
A77: =A76+1 -> 53 | B77: 54231 | C77: =C76-B77 -> 379617 | D77: 47341 | H77: =B77+E77 -> 54231
A78: =A77+1 -> 54 | B78: 54231 | C78: =C77-B78 -> 325386 | D78: 47342 | H78: =B78+E78 -> 54231
A79: =A78+1 -> 55 | B79: 54231 | C79: =C78-B79 -> 271155 | D79: 47696 | H79: =B79+E79 -> 54231
A80: =A79+1 -> 56 | B80: 54231 | C80: =C79-B80 -> 216924 | D80: 47697 | H80: =B80+E80 -> 54231
A81: =A80+1 -> 57 | B81: 54231 | C81: =C80-B81 -> 162693 | D81: 47698 | H81: =B81+E81 -> 54231
A82: =A81+1 -> 58 | B82: 54231 | C82: =C81-B82 -> 108462 | D82: 47699 | H82: =B82+E82 -> 54231
... A84: =A83+1 -> 60 | B84: 54231 | C84: =C83-B84 -> 0 | D84: 47701 | H84: =B84+E84 -> 54231
B85: =SUM(B25:B84) -> 3253860 | E85: =SUM(E25:E84) -> 1207086 | H85: =SUM(H25:H84) -> 4460946
